Workbook

Sheet Dashboard
A1: S.LAB Research Project #1 — Dashboard
A2: Pulls live from Candidate Companies / Deep Dive Database / Comparison Group Database. Do not type values into column B below row 5 except where noted.
A4: Metric | B4: Count
A5: Companies screened | B5: =COUNTA('Pass 1 Archive'!A2:A500) -> 195
A6: Companies included | B6: =COUNTA('Pass 2'!A2:A500) -> 118
A7: Companies excluded | B7: =COUNTIF('Pass 1 Archive'!X2:X500,"Exclude") -> 23
A8: Companies pending decision | B8: =COUNTIF('Pass 1 Archive'!X2:X500,"Pending") -> 24
A9: Traffic classifications complete | B9: =COUNTA('Pass 2'!T2:T500) -> 118
A10: — Grew | B10: =COUNTIF('Pass 2'!T2:T500,"Grew") -> 44
A11: — Flat | B11: =COUNTIF('Pass 2'!T2:T500,"Flat") -> 19
A12: — Declined | B12: =COUNTIF('Pass 2'!T2:T500,"Declined") -> 55
A13: Deep dives selected | B13: =COUNTIF('Pass 1 Archive'!Z2:Z500,"Yes") -> 11
A14: Deep dives complete | B14: =COUNTIF('Deep Dive Database'!AK2:AK500,"Complete") -> 0
A15: Comparison reviews selected | B15: =COUNTIF('Pass 1 Archive'!AA2:AA500,"Yes") -> 6
A16: Comparison reviews complete | B16: =COUNTIF('Comparison Group Database'!Q2:Q500,"Complete") -> 0
A17: Patterns logged | B17: =COUNTA('Pattern Tracker'!A2:A500) -> 0
A18: Research log entries | B18: =COUNTA('Research Log'!A2:A500) -> 8
A20: Companies included by category (target 10 each)
A21: Category | B21: Included | C21: Target
A22: Sales Engagement / Sales Intelligence | B22: =COUNTIF('Pass 2'!B2:B500,A22) -> 11 | C22: 10
A23: Marketing Automation | B23: =COUNTIF('Pass 2'!B2:B500,A23) -> 11 | C23: 10
A24: Customer Support / Help Desk | B24: =COUNTIF('Pass 2'!B2:B500,A24) -> 11 | C24: 10
A25: Customer Success | B25: =COUNTIF('Pass 2'!B2:B500,A25) -> 13 | C25: 10
A26: HR / People Operations | B26: =COUNTIF('Pass 2'!B2:B500,A26) -> 11 | C26: 10
A27: Finance / Spend Management | B27: =COUNTIF('Pass 2'!B2:B500,A27) -> 11 | C27: 10
A28: Project Management / Collaboration | B28: =COUNTIF('Pass 2'!B2:B500,A28) -> 11 | C28: 10
A29: Developer Tools / DevOps | B29: =COUNTIF('Pass 2'!B2:B500,A29) -> 11 | C29: 10
A30: Security / Compliance | B30: =COUNTIF('Pass 2'!B2:B500,A30) -> 14 | C30: 10
A31: Product Analytics / Product Management | B31: =COUNTIF('Pass 2'!B2:B500,A31) -> 14 | C31: 10
A32: Total | B32: =SUM(B22:B31) -> 118
A34: Traffic Trajectory Breakdown
A35: Trajectory | B35: Count
A36: Continuous Acceleration | B36: =COUNTIF('Pass 2'!S2:S500,A36) -> 25
A37: Steady Growth | B37: =COUNTIF('Pass 2'!S2:S500,A37) -> 2
A38: Growth then Pullback | B38: =COUNTIF('Pass 2'!S2:S500,A38) -> 25
A39: Early Peak then Plateau | B39: =COUNTIF('Pass 2'!S2:S500,A39) -> 1
A40: Early Peak then Decline | B40: =COUNTIF('Pass 2'!S2:S500,A40) -> 28
A41: Decline then Recovery | B41: =COUNTIF('Pass 2'!S2:S500,A41) -> 11
A42: Flat | B42: =COUNTIF('Pass 2'!S2:S500,A42) -> 3
A43: Steady Decline | B43: =COUNTIF('Pass 2'!S2:S500,A43) -> 9
A44: Volatile | B44: =COUNTIF('Pass 2'!S2:S500,A44) -> 14
A45: Total | B45: =SUM(B36:B44) -> 118

Sheet Field Reference
A1: Field Reference — schema documentation for every tab in this workbook
A2: Read this before entering data. Each row documents one column: what it is, its data type, and its dropdown values (if any). Column order here matches the actual workflow order in each tab — it is not alphabetical.
A4: Tab | B4: Column | C4: Description | D4: Data Type | E4: Dropdown Values / Notes
A5: Company Tracker | B5: Company Name | C5: Locked/included company. Join key used across Pass 1 Archive, Deep Dive Database, and Comparison Group Database — must match exactly across all four sheets. | D5: Text
A6: Company Tracker | B6: Category | C6: Sourcing category carried over from Pass 1 Archive at lock time. | D6: Dropdown | E6: 10 locked categories (see Lists tab)
A7: Company Tracker | B7: Jan 2025 Traffic | C7: Organic traffic at study window start. From Ahrefs Performance report export. | D7: Number
A8: Company Tracker | B8: Jun 2026 Traffic | C8: Organic traffic at study window end. | D8: Number
A9: Company Tracker | B9: Traffic % Change | C9: Auto-calculated. Do not type into this column. | D9: Formula | E9: =IFERROR((JUN2026-JAN2025)/JAN2025,"")
A10: Company Tracker | B10: Jan 2025 Traffic Value | C10: Ahrefs Organic Traffic Value at study window start. | D10: Number
A11: Company Tracker | B11: Jun 2026 Traffic Value | C11: Ahrefs Organic Traffic Value at study window end. | D11: Number
A12: Company Tracker | B12: Traffic Value % Change | C12: Auto-calculated. Do not type into this column. | D12: Formula | E12: =IFERROR((end-start)/start,"")
A13: Company Tracker | B13: Jan 2025 Referring Domains | C13: Ahrefs Referring Domains at study window start. | D13: Number
A14: Company Tracker | B14: Jun 2026 Referring Domains | C14: Ahrefs Referring Domains at study window end. | D14: Number
A15: Company Tracker | B15: Referring Domains % Change | C15: Auto-calculated. Do not type into this column. | D15: Formula | E15: =IFERROR((end-start)/start,"")
A16: Company Tracker | B16: Study Window Peak Traffic | C16: Highest monthly organic traffic observed WITHIN the study window (Jan 2025-June 2026) only. | D16: Number
A17: Company Tracker | B17: Study Window Peak Month | C17: Month the within-window peak occurred (e.g., "March 2026"). Pairs with Study Window Peak Traffic. | D17: Text
A18: Company Tracker | B18: Historical Peak Traffic | C18: All-time peak monthly organic traffic, including before the study window (expanded to all 100 companies as of V1.2 - previously Pass-3-only). Pairs with Historical Peak Month. | D18: Number
A19: Company Tracker | B19: Historical Peak Month | C19: Month the all-time historical peak occurred. May fall before or during the study window. | D19: Text
A20: Company Tracker | B20: Distance from Historical Peak % | C20: Auto-calculated: how current (Jun 2026) traffic compares to the company's all-time historical peak. Negative = still below all-time peak; positive = has exceeded it. | D20: Formula | E20: =IFERROR((jun2026traffic-historicalpeaktraffic)/historicalpeaktraffic,"")
A21: Company Tracker | B21: Traffic Trajectory | C21: Describes how the company arrived at its Classification using the within-study-window time series only - shape, not outcome. Official 9-value taxonomy - choose closest match rather than inventing a new label. | D21: Dropdown | E21: Continuous Acceleration, Steady Growth, Growth then Pullback, Early Peak then Plateau, Early Peak then Decline, Decline then Recovery, Flat, Steady Decline, Volatile
A22: Company Tracker | B22: Classification | C22: Pass 2 outcome, determined from the study window only. | D22: Dropdown | E22: Grew, Flat, Declined
A23: Company Tracker | B23: Notes | C23: Freeform. | D23: Text
A24: Pass 1 Archive | B24: Company Name | C24: Join key. Every candidate ever screened gets a row here, regardless of Inclusion Decision. | D24: Text
A25: Pass 1 Archive | B25: Website/Domain | C25: Primary domain used for Ahrefs lookups. | D25: Text (URL)
A26: Pass 1 Archive | B26: Category | C26: Sourcing category from the locked 10-category list (Section 3 of operating manual). Source of truth for the Category field carried over to Company Tracker at lock time. | D26: Dropdown
A27: Pass 1 Archive | B27: Date Added | C27: Date the candidate was first logged. | D27: Date
A28: Pass 1 Archive | B28: Source List | C28: Where the candidate was discovered. | D28: Dropdown | E28: G2, Crozdesk, GetApp, Capterra, Other
A29: Pass 1 Archive | B29: Source URL | C29: Link to the specific G2/directory page the candidate was pulled from. | D29: Text (URL)
A30: Pass 1 Archive | B30: Screened By | C30: Who ran the inclusion screen. | D30: Text
A31: Pass 1 Archive | B31: Screening Date | C31: Date the inclusion screen was run. | D31: Date
A32: Pass 1 Archive | B32: B2B SaaS Confirmed? | C32: Gate 1 - quick judgment call from the company's own homepage. | D32: Dropdown | E32: Yes, No
A33: Pass 1 Archive | B33: One-Line Description | C33: What the company sells, in plain language. | D33: Text
A34: Pass 1 Archive | B34: Founded Year | C34: From Crunchbase or company site. | D34: Number
A35: Pass 1 Archive | B35: Public/Private | C35: From Crunchbase. | D35: Dropdown | E35: Public, Private
A36: Pass 1 Archive | B36: LinkedIn Employee Count | C36: Descriptive metadata only (V1.1) - not a screening gate. Standardized single source; do not average across conflicting sources. | D36: Number
A37: Pass 1 Archive | B37: Employee Count Source/Date | C37: E.g. 'LinkedIn, 2026-07-01' - keeps the standardization auditable. | D37: Text
A38: Pass 1 Archive | B38: Funding Status / Total Raised | C38: From Crunchbase. | D38: Text
A39: Pass 1 Archive | B39: M&A Status | C39: Gate 2 - exclude if the M&A/rebrand was recent or disruptive enough to break continuous attributable history; include-with-flag if clean. Requires a documented treatment decision, not just a status label. | D39: Dropdown | E39: Independent, Acquired, Merged, Rebranded
A40: Pass 1 Archive | B40: M&A Notes | C40: Date, acquirer, and the treatment decision reasoning. | D40: Text
A41: Pass 1 Archive | B41: Domain Stable During Window? | C41: Gate 3 - No = exclude (breaks Ahrefs trend continuity). | D41: Dropdown | E41: Yes, No
A42: Pass 1 Archive | B42: Primary ICP | C42: Company's own stated target customer - not G2's segment grid. | D42: Dropdown | E42: SMB, Mid-Market, Enterprise
A43: Pass 1 Archive | B43: Buying Motion | C43: Metadata only, not a selection criterion. | D43: Dropdown | E43: PLG, Sales-led, Hybrid
A44: Pass 1 Archive | B44: Primary Buyer | C44: Metadata only, not a selection criterion. | D44: Dropdown | E44: Technical, Non-technical
A45: Pass 1 Archive | B45: Non-Core Asset Flag | C45: Yes if a free tool/calculator/template library/content hub drives a meaningful share of traffic. A flag, not an exclusion. | D45: Dropdown | E45: Yes, No
A46: Pass 1 Archive | B46: Non-Core Asset Notes | C46: What the non-core asset is, if flagged. | D46: Text
A47: Pass 1 Archive | B47: Inclusion Decision | C47: Final screening outcome across all 5 gates. Keep excluded rows - don't delete them. Include = company is also added to Company Tracker. | D47: Dropdown | E47: Include, Exclude, Pending
A48: Pass 1 Archive | B48: Exclusion Reason | C48: Required if Inclusion Decision = Exclude. 'Looked fine' is not an acceptable reason. | D48: Text
A49: Pass 1 Archive | B49: Selected for Deep Dive? | C49: Top 8-10 growth winners, selected after Pass 2 classification. | D49: Dropdown | E49: Yes, No
A50: Pass 1 Archive | B50: Selected for Comparison Group? | C50: ~8 decliners, selected after Pass 2 classification. | D50: Dropdown | E50: Yes, No
A51: Pass 1 Archive | B51: Research Status | C51: Overall review progress for this company. | D51: Dropdown | E51: Not Started, In Progress, Complete
A52: Pass 1 Archive | B52: Tags | C52: Freeform, comma-separated (e.g. 'PLG, comparison-pages-heavy'). | D52: Text
A53: Pass 1 Archive | B53: Last Updated | C53: Bump whenever the row changes. | D53: Date
A54: Deep Dive Database | B54: Company Name | C54: Typed key - must match a Company Name in Company Tracker exactly. | D54: Text
A55: Deep Dive Database | B55: Category / Traffic Start/End / % Change / Ref. Domains Start/End | C55: Auto-pulled via VLOOKUP from Company Tracker. Do not type. | D55: Formula
A56: Deep Dive Database | B56: Employees | C56: Auto-pulled via VLOOKUP from Pass 1 Archive. Do not type. | D56: Formula
A57: Deep Dive Database | B57: Reviewed Date | C57: Date the deep dive was conducted. | D57: Date
A58: Deep Dive Database | B58: Time Spent (min) | C58: Time-box target: 60-90 minutes. | D58: Number
A59: Deep Dive Database | B59: Reviewer | C59: Who did the review. | D59: Text
A60: Deep Dive Database | B60: Growth URL 1-5 (URL / Content Type / Est. Traffic Change) | C60: The core of the deep dive - required. If fewer than 5 pages account for the bulk of growth, leave remaining rows blank; that concentration is itself a finding. | D60: Text/Dropdown/Number | E60: Content Type = see Content Type list
A61: Deep Dive Database | B61: Growth Concentration | C61: Concentrated = a few pages did most of the work. | D61: Dropdown | E61: Concentrated, Distributed
A62: Deep Dive Database | B62: Content Origin | C62: Net-new vs. refreshed existing content. | D62: Dropdown | E62: Net-new, Refreshed, Both
A63: Deep Dive Database | B63: Growth Timing | C63: Gradual climb vs. step-changes tied to specific publishes. | D63: Dropdown | E63: Gradual, Step-change
A64: Deep Dive Database | B64: Referring Domain Notes | C64: Notable new referring domains and any pattern in them. | D64: Text
A65: Deep Dive Database | B65: Internal Linking Observations | C65: Any visible internal-linking pattern connecting growth pages to core product pages. | D65: Text
A66: Deep Dive Database | B66: AI Visibility Spot-Check Notes | C66: Manual ChatGPT/Perplexity prompt checks, if time allows. | D66: Text
A67: Deep Dive Database | B67: Anything Surprising | C67: Required field - name at least one thing. | D67: Text
A68: Deep Dive Database | B68: Anything Contradicting Hypotheses | C68: Required field - if nothing contradicts, say so explicitly. | D68: Text
A69: Deep Dive Database | B69: Quotable Pattern Candidates | C69: Exact phrasing/numbers that could become a line in the report. | D69: Text
A70: Deep Dive Database | B70: Primary Growth Driver (confirmed) | C70: Post-deep-dive confirmed value - may differ from the original hypothesis. | D70: Dropdown | E70: See Growth Driver list
A71: Deep Dive Database | B71: Review Status | D71: Dropdown | E71: Not Started, In Progress, Complete
A72: Deep Dive Database | B72: Notes/Follow-ups | D72: Text
A73: Deep Dive Database | B73: Review Complete | C73: Simple completion flag for filtering as the project scales. Complements Review Status; does not replace it. | D73: Dropdown | E73: Yes, No
A74: Deep Dive Database | B74: Long-Term Traffic Story | C74: 1-3 sentence narrative of the company's overall long-term traffic pattern (e.g., large historical peak, long decline, recovery beginning mid-window). Interpretation, not measurement - never changes Pass 2 Classification. | D74: Text
A75: Deep Dive Database | B75: Major Inflection Points | C75: Notable dates/events where the traffic trend visibly changed direction, pre- or post-window. | D75: Text
A76: Deep Dive Database | B76: Acquisitions / Mergers | C76: Any M&A history, including pre-window, relevant to interpreting the company's trajectory. Does not retroactively change the Pass 1 Include/Exclude decision. | D76: Text
A77: Deep Dive Database | B77: Rebrands | C77: Any rebrand history relevant to interpreting the traffic story. | D77: Text
A78: Deep Dive Database | B78: Domain Migrations | C78: Any domain migration history relevant to interpreting the traffic story. | D78: Text
A79: Deep Dive Database | B79: Product Launches / Notable Events | C79: Other notable events (product launches, funding events, major press) useful for interpreting the trajectory, when discoverable. | D79: Text
A80: Comparison Group Database | B80: Company Name | C80: Typed key - must match a Company Name in Company Tracker exactly. | D80: Text
A81: Comparison Group Database | B81: Category / Employees / Traffic & Referring Domain trend | C81: Auto-pulled via VLOOKUP from Company Tracker / Pass 1 Archive. | D81: Formula
A82: Comparison Group Database | B82: Reviewed Date | D82: Date
A83: Comparison Group Database | B83: Time Spent (min) | C83: Time-box target: 20-30 minutes. | D83: Number
A84: Comparison Group Database | B84: Publishing Activity | C84: Visible publishing activity during the window, or largely static. | D84: Dropdown | E84: Active, Minimal, Static
A85: Comparison Group Database | B85: Growth-Associated Content Types Present? | C85: Are the content types associated with winners present but underperforming, or genuinely absent? | D85: Dropdown | E85: Present-underperforming, Absent, Unclear
A86: Comparison Group Database | B86: Content Types Notes | D86: Text
A87: Comparison Group Database | B87: Likely Decline Explanation | C87: Most likely plain-language explanation. | D87: Dropdown | E87: Algorithm change, Lack of publishing, Competitive displacement, Product/market issue, Other, Unclear
A88: Comparison Group Database | B88: One-Line Takeaway | D88: Text
A89: Comparison Group Database | B89: Confidence | D89: Dropdown | E89: High, Medium, Low, Unclear
A90: Comparison Group Database | B90: Review Status | D90: Dropdown | E90: Not Started, In Progress, Complete
A91: Comparison Group Database | B91: Review Complete | C91: Simple completion flag for filtering as the project scales. Complements Review Status; does not replace it. | D91: Dropdown | E91: Yes, No
A92: Research Log | B92: Log ID | C92: Format LOG-001, increments. | D92: Text
A93: Research Log | B93: Date | D93: Date
A94: Research Log | B94: Related Company | C94: Optional - not every entry ties to one company. | D94: Text
A95: Research Log | B95: Category Tag | D95: Dropdown | E95: Finding, Surprise, Question, Future-research, LinkedIn-post, Newsletter, Methodology-note
A96: Research Log | B96: Observation | D96: Text
A97: Research Log | B97: Why It's Interesting | D97: Text
A98: Research Log | B98: Action Needed | D98: Text
A99: Research Log | B99: Status | D99: Dropdown | E99: Open, Actioned, Archived
A100: Pattern Tracker | B100: Pattern ID | C100: Format PAT-001. | D100: Text
A101: Pattern Tracker | B101: Pattern | C101: Stated as a claim, e.g. 'Winners concentrate growth in comparison pages.' | D101: Text
...

Sheet Pass 2
A1: Company Name | B1: Category | C1: Jan 2025 Traffic | D1: Jun 2026 Traffic | E1: Traffic % Change | F1: Jan 2025 Traffic Value | G1: Jun 2026 Traffic Value | H1: Traffic Value % Change | I1: Jan 2025 Referring Domains | J1: Jun 2026 Referring Domains | K1: Referring Domains % Change | L1: Study Window Peak Traffic | M1: Study Window Peak Month | N1: Historical Peak Traffic | O1: Historical Peak Month | P1: Study Window Trough Traffic/Month | Q1: Study Window Trough Month | R1: Distance from Historical Peak % | S1: Traffic Trajectory | T1: Classification | U1: Notes
A2: Gainsight | B2: Customer Success | C2: 40301 | D2: 142301 | E2: =IFERROR((D2-C2)/C2,"") -> 2.5309546 | F2: 190281 | G2: 373192 | H2: =IFERROR((G2-F2)/F2,"") -> 0.96126781 | I2: 3088 | J2: 7438 | K2: =IFERROR((J2-I2)/I2,"") -> 1.4086788 | L2: 142301 | M2: Jun 2026 | N2: 142301 | O2: Jun 2026 | P2: 40301 | Q2: Jan 2025 | R2: =IFERROR((D2-N2)/N2,"") -> 0 | S2: Continuous Acceleration | T2: Grew | U2: Traffic was relatively stable through most of 2025, then accelerated sharply beginning in late 2025 and especially from Feb-Jun 2026. Current traffic is both the study-window peak and historical peak, so this is not a recovery story. It is a clear breakout/growth profile.
A3: Planhat | B3: Customer Success | C3: 10085 | D3: 10716 | E3: =IFERROR((D3-C3)/C3,"") -> 0.062568171 | F3: 98425 | G3: 114192 | H3: =IFERROR((G3-F3)/F3,"") -> 0.16019304 | I3: 653 | J3: 1107 | K3: =IFERROR((J3-I3)/I3,"") -> 0.69525268 | L3: 12270 | M3: Mar 2025 | N3: 12270 | O3: Mar 2025 | P3: 9051 | Q3: Dec 2025 | R3: =IFERROR((D3-N3)/N3,"") -> -0.12665037 | S3: Decline then Recovery | T3: Flat | U3: Traffic peaked in March 2025 before declining approximately 26% to a December 2025 trough. Organic visibility recovered steadily throughout the first half of 2026 but remains about 13% below its historical high. Overall traffic finished roughly flat versus the beginning of the study window.
A4: ClientSuccess | B4: Customer Success | C4: 3593 | D4: 3458 | E4: =IFERROR((D4-C4)/C4,"") -> -0.037573059 | F4: 17048 | G4: 25297 | H4: =IFERROR((G4-F4)/F4,"") -> 0.48386908 | I4: 766 | J4: 955 | K4: =IFERROR((J4-I4)/I4,"") -> 0.24673629 | L4: 4303 | M4: Apr 2025 | N4: 4831 | O4: Jun 2024 | P4: 2524 | Q4: May 2026 | R4: =IFERROR((D4-N4)/N4,"") -> -0.28420617 | S4: Decline then Recovery | T4: Flat | U4: Traffic peaked early in the study window before trending downward for roughly a year. Organic visibility reached its lowest point in May 2026, then rebounded sharply in June 2026. Despite the volatility, the company finished only 3.8% below where it started, though it remains 28.4% below its historical peak.
A5: Vitally | B5: Customer Success | C5: 5692 | D5: 3609 | E5: =IFERROR((D5-C5)/C5,"") -> -0.36595221 | F5: 32421 | G5: 26642 | H5: =IFERROR((G5-F5)/F5,"") -> -0.17824867 | I5: 1018 | J5: 1540 | K5: =IFERROR((J5-I5)/I5,"") -> 0.51277014 | L5: 6859 | M5: Sep 2025 | N5: 6859 | O5: Sep 2025 | P5: 3503 | Q5: May 2026 | R5: =IFERROR((D5-N5)/N5,"") -> -0.47383 | S5: Growth then Pullback | T5: Declined | U5: Traffic remained relatively stable through mid-2025 before reaching a historical peak in September 2025. Organic visibility then declined consistently for eight months, reaching a study-window low in May 2026. June showed only a minor rebound, leaving traffic 36.6% below the start of the study window and 47.4% below its historical peak.
A6: Custify | B6: Customer Success | C6: 19997 | D6: 13081 | E6: =IFERROR((D6-C6)/C6,"") -> -0.34585188 | F6: 64847 | G6: 47773 | H6: =IFERROR((G6-F6)/F6,"") -> -0.26329668 | I6: 1541 | J6: 2478 | K6: =IFERROR((J6-I6)/I6,"") -> 0.60804672 | L6: 22299 | M6: Oct 2025 | N6: 22299 | O6: Oct 2025 | P6: 12680 | Q6: May 2026 | R6: =IFERROR((D6-N6)/N6,"") -> -0.41338177 | S6: Growth then Pullback | T6: Declined | U6: Traffic remained relatively stable through mid-2025 before accelerating to a historical peak in October 2025. Organic visibility then declined sharply through spring 2026, reaching a study-window low in May 2026. June showed only a modest rebound, with traffic ending 34.6% below the start of the study window and 41.3% below its historical peak.
A7: Akita | B7: Customer Success | C7: 233 | D7: 666 | E7: =IFERROR((D7-C7)/C7,"") -> 1.8583691 | F7: 219 | G7: 1696 | H7: =IFERROR((G7-F7)/F7,"") -> 6.7442922 | I7: 200 | J7: 554 | K7: =IFERROR((J7-I7)/I7,"") -> 1.77 | L7: 666 | M7: Jun 2026 | N7: 666 | O7: Jun 2026 | P7: 101 | Q7: Feb 2025 | R7: =IFERROR((D7-N7)/N7,"") -> 0 | S7: Continuous Acceleration | T7: Grew | U7: Traffic remained low and volatile throughout most of 2025 before beginning a sustained acceleration in spring 2026. Organic visibility reached a new historical high in June 2026, nearly tripling from the beginning of the study window. This represents a clear late-stage breakout rather than a recovery from a previous decline.
A8: Kapta | B8: Customer Success | C8: 5166 | D8: 3118 | E8: =IFERROR((D8-C8)/C8,"") -> -0.39643825 | F8: 7231 | G8: 4575 | H8: =IFERROR((G8-F8)/F8,"") -> -0.36730743 | I8: 467 | J8: 805 | K8: =IFERROR((J8-I8)/I8,"") -> 0.72376874 | L8: 7754 | M8: Mar 2025 | N8: 7754 | O8: Mar 2025 | P8: 2999 | Q8: Nov 2025 | R8: =IFERROR((D8-N8)/N8,"") -> -0.59788496 | S8: Early Peak then Decline | T8: Declined | U8: Traffic reached both its study-window and historical peak in March 2025 before entering a prolonged decline. Although visibility temporarily recovered during early 2026, the gains were not sustained, and traffic fell to 3,118 by June 2026. The company finished 39.6% below the beginning of the study window and nearly 60% below its historical peak. Note: a temporary rebound occurred Jan-Apr 2026 before the final decline -- worth watching for as a recurring pattern across the dataset.
A9: ChurnZero | B9: Customer Success | C9: 18682 | D9: 23558 | E9: =IFERROR((D9-C9)/C9,"") -> 0.26099989 | F9: 236975 | G9: 181454 | H9: =IFERROR((G9-F9)/F9,"") -> -0.23429054 | I9: 1271 | J9: 2454 | K9: =IFERROR((J9-I9)/I9,"") -> 0.93076318 | L9: 37436 | M9: Mar 2026 | N9: 37436 | O9: Mar 2026 | P9: 16161 | Q9: Feb 2025 | R9: =IFERROR((D9-N9)/N9,"") -> -0.37071268 | S9: Growth then Pullback | T9: Grew | U9: Traffic remained relatively stable through most of 2025 before breaking out sharply in early 2026. Organic visibility reached a new historical peak in March 2026, then moderated over the following three months while remaining well above the beginning of the study window. The company finished 26.1% above its January 2025 traffic despite ending 37.1% below its March 2026 peak.
A10: UserGuiding | B10: Customer Success | C10: 36151 | D10: 7095 | E10: =IFERROR((D10-C10)/C10,"") -> -0.80373987 | F10: 93086 | G10: 46249 | H10: =IFERROR((G10-F10)/F10,"") -> -0.50315837 | I10: 3442 | J10: 4503 | K10: =IFERROR((J10-I10)/I10,"") -> 0.30825102 | L10: 48608 | M10: Aug 2025 | N10: 149605 | O10: Apr 2023 | P10: 6928 | Q10: May 2026 | R10: =IFERROR((D10-N10)/N10,"") -> -0.95257511 | S10: Growth then Pullback | T10: Declined | U10: Traffic grew steadily during the first half of the study window, peaking at 48.6k visits in August 2025 before entering a prolonged decline. Organic visibility fell more than 80% by June 2026 and remains over 95% below the company's historical peak from April 2023. The small uptick in June does not indicate a meaningful recovery. Largest historical-peak gap observed so far (149,605 to 7,095) -- strong Comparison Group candidate to investigate the cause of the collapse.
A11: Velaris | B11: Customer Success | C11: 975 | D11: 4887 | E11: =IFERROR((D11-C11)/C11,"") -> 4.0123077 | F11: 2002 | G11: 11764 | H11: =IFERROR((G11-F11)/F11,"") -> 4.8761239 | I11: 227 | J11: 692 | K11: =IFERROR((J11-I11)/I11,"") -> 2.0484581 | L11: 8085 | M11: Apr 2026 | N11: 8085 | O11: Apr 2026 | P11: 975 | Q11: Jan 2025 | R11: =IFERROR((D11-N11)/N11,"") -> -0.39554731 | S11: Growth then Pullback | T11: Grew | U11: Traffic grew steadily throughout the study window before accelerating sharply in early 2026. Organic visibility reached a new historical peak of 8,085 visits in April 2026, then pulled back roughly 40% over the following two months while still finishing more than 400% above the beginning of the study window. Overall, this represents a strong long-term growth trajectory despite the post-peak pullback.
A12: Rocketlane | B12: Customer Success | C12: 16602 | D12: 17994 | E12: =IFERROR((D12-C12)/C12,"") -> 0.08384532 | F12: 73974 | G12: 97479 | H12: =IFERROR((G12-F12)/F12,"") -> 0.31774678 | I12: 711 | J12: 2001 | K12: =IFERROR((J12-I12)/I12,"") -> 1.814346 | L12: 18375 | M12: Feb 2026 | N12: 19426 | O12: Sep 2024 | P12: 12331 | Q12: Jul 2025 | R12: =IFERROR((D12-N12)/N12,"") -> -0.073715639 | S12: Decline then Recovery | T12: Flat | U12: Traffic declined through the first half of the study window, reaching a low of 12.3k visits in July 2025 before recovering steadily over the following seven months. Organic visibility reached a new study-window peak in February 2026 (18,375), short of its Sep 2024 historical peak of 19,426. Overall traffic increased just 8.4% from the beginning of the study window, resulting in a 'Flat' classification despite the meaningful internal decline-and-recovery shape.
A13: Higher Logic | B13: Customer Success | C13: 6257 | D13: 8272 | E13: =IFERROR((D13-C13)/C13,"") -> 0.32203932 | F13: 22244 | G13: 28467 | H13: =IFERROR((G13-F13)/F13,"") -> 0.27976083 | I13: 1926 | J13: 2897 | K13: =IFERROR((J13-I13)/I13,"") -> 0.50415369 | L13: 9250 | M13: Apr 2026 | N13: 11653 | O13: Dec 2021 | P13: 5773 | Q13: Feb 2025 | R13: =IFERROR((D13-N13)/N13,"") -> -0.29013988 | S13: Continuous Acceleration | T13: Grew | U13: Traffic experienced a brief dip early in the study window before beginning a sustained upward trend through April 2026. Organic visibility increased more than 32% over the study period, though it remains approximately 29% below the company's historical peak from December 2021. A modest pullback (~10.6% off the study-window peak) followed the April 2026 peak but did not materially change the overall growth trajectory.
... A83: Semaphore | B83: Developer Tools / DevOps | C83: 0 | D83: 27797 | E83: =IFERROR((D83-C83)/C83,"") | F83: 0 | G83: 11325 | H83: =IFERROR((G83-F83)/F83,"") | I83: 2 | J83: 5971 | K83: =IFERROR((J83-I83)/I83,"") -> 2984.5 | L83: 27797 | M83: Jun 2026 | N83: 27797 | O83: Jun 2026 | P83: 0 | Q83: Jan 2025 | R83: =IFERROR((D83-N83)/N83,"") -> 0 | S83: Continuous Acceleration | T83: Grew | U83: EDGE CASE -- Jan 2025 traffic was literally 0 (and Feb 2025 was also 0), so the standard % change formula returns blank (div-by-zero) and Classification/Distance-from-Peak were set manually rather than via the threshold formula. This is the only company in the study so far that appears to have built its organic presence from scratch during the study window itself: traffic stayed near-zero through Q1 2025, began ramping in Mar 2025, accelerated through the rest of 2025 into 2026, and closed the window at an all-time high of 27,797 -- a genuinely different pattern from every other company's pre-existing-traffic trajectory. Strong candidate for a Research Log entry given how rare a true from-zero organic launch is in this dataset. Per user confirmation, this CSV (semaphore.io) was treated as the same entity as the existing Archive row recorded at semaphoreci.com.
A84: CloudBees | B84: Developer Tools / DevOps | C84: 47036 | D84: 80857 | E84: =(D84-C84)/C84 -> 0.71904499 | F84: 30983 | G84: 51252 | H84: =(G84-F84)/F84 -> 0.65419746 | I84: N/A - data entry error corrected 2026-06-29; no verified domain-level RD export on hand | J84: N/A - data entry error corrected 2026-06-29; no verified domain-level RD export on hand | L84: 80857 | M84: Jun 2026 | N84: 136304 | O84: Apr 2022 | P84: 38615 | Q84: Dec 2025 | R84: =(D84-N84)/N84 -> -0.40678924 | S84: Continuous Acceleration | T84: Grew | U84: Corrected 2026-06-29: original Traffic/Traffic Value/Referring Domains fields were column-shifted relative to the Ahrefs Performance export (Traffic field held the traffic-value figure, Referring Domains field held the traffic figure, Traffic Value field held the Organic positions 1-3 keyword count). Verified Referring Domains has no source in the perf export; left N/A pending a domain-level Ahrefs export. Corrected traffic series: choppy/range-bound through 2025 (38,615-56,024), trough Dec 2025 (38,615), then sustained acceleration from Jan 2026 onward to a new study-window high (80,857) by Jun 2026, the most recent month, with no pullback at window end. Historical peak is 136,304 (Apr 2022), well above the current window peak (Distance from Historical Peak -40.7%), so growth represents partial recovery toward a much larger historical level, not a new all-time high.
A85: Bitbucket | B85: Developer Tools / DevOps | C85: 298258 | D85: 287294 | E85: =IFERROR((D85-C85)/C85,"") -> -0.03676012 | F85: 455205 | G85: 428505 | H85: =IFERROR((G85-F85)/F85,"") -> -0.058654892 | I85: 58324 | J85: 59328 | K85: =IFERROR((J85-I85)/I85,"") -> 0.017214183 | L85: 309467 | M85: Sep 2025 | N85: 1416653 | O85: Mar 2023 | P85: 266714 | Q85: Apr 2026 | R85: =IFERROR((D85-N85)/N85,"") -> -0.79720228 | S85: Flat | T85: Flat | U85: Traffic stayed within a fairly narrow band (~267K-309K, ~14% spread) for the entire window with no dominant directional trend, netting to essentially flat (-3.7%). Note on the historical peak: 1,416,653 (Mar 2023) is itself a striking outlier -- more than 4x the window's range and more than 2x the next-highest historical month (638,481, Apr 2023, the same anomalous period) -- while every other year in the 2017-2026 series sits in the 270K-520K range like the study window. This looks like a one-time spike event in early 2023 rather than a representative historical baseline; worth noting if Distance-from-Historical-Peak figures are used in reporting, since this one is disproportionately skewed by an outlier month.
A86: Perforce | B86: Developer Tools / DevOps | C86: 80785 | D86: 62949 | E86: =IFERROR((D86-C86)/C86,"") -> -0.22078356 | F86: 105825 | G86: 78244 | H86: =IFERROR((G86-F86)/F86,"") -> -0.2606284 | I86: 9353 | J86: 13935 | K86: =IFERROR((J86-I86)/I86,"") -> 0.48989629 | L86: 81807 | M86: Apr 2025 | N86: 112197 | O86: Mar 2024 | P86: 57113 | Q86: Dec 2025 | R86: =IFERROR((D86-N86)/N86,"") -> -0.43894222 | S86: Early Peak then Decline | T86: Declined | U86: Traffic peaked early in the window (Apr 2025) and declined fairly steadily through Dec 2025, recovered modestly Jan-Mar 2026, then declined again into window end. All-time historical peak (112,197, Mar 2024) predates the window by about 10 months and sits well above the in-window peak, suggesting the decline was already underway before the study window opened -- consistent with the broader pre-window peak-decay pattern logged in the Research Log.
A87: JFrog | B87: Developer Tools / DevOps | C87: 191144 | D87: 195356 | E87: =IFERROR((D87-C87)/C87,"") -> 0.022035743 | F87: 3815 | G87: 4763 | H87: =IFERROR((G87-F87)/F87,"") -> 0.24849279 | I87: 84685 | J87: 87362 | K87: =IFERROR((J87-I87)/I87,"") -> 0.031611265 | L87: 219538 | M87: Sep 2025 | N87: 261639 | O87: Sep 2020 | P87: 185004 | Q87: Dec 2025 | R87: =IFERROR((D87-N87)/N87,"") -> -0.25333761 | S87: Flat | T87: Flat | U87: Traffic stayed range-bound (185K-220K, ~19% spread) for the entire window with minor noise (a Sep 2025 spike, a Feb-Mar 2026 bump) but no dominant trend, netting to essentially flat (+2.2%). All-time historical peak (261,639, Sep 2020) predates the window by ~4.3 years.
A88: CircleCI | B88: Developer Tools / DevOps | C88: 132735 | D88: 182297 | E88: =IFERROR((D88-C88)/C88,"") -> 0.37339059 | F88: 99992 | G88: 158125 | H88: =IFERROR((G88-F88)/F88,"") -> 0.58137651 | I88: 10943 | J88: 15397 | K88: =IFERROR((J88-I88)/I88,"") -> 0.40701819 | L88: 182297 | M88: Jun 2026 | N88: 182297 | O88: Jun 2026 | P88: 82217 | Q88: Dec 2025 | R88: =IFERROR((D88-N88)/N88,"") -> 0 | S88: Decline then Recovery | T88: Grew | U88: Traffic declined steadily from the window start through a Dec 2025 trough, then recovered and accelerated strongly through H1 2026, more than doubling from trough to close the window at a new all-time high (182,297, surpassing the prior record of 153,477 from Jan 2023). The recovery phase was strong enough to produce net growth (+37.3%) rather than just a return to baseline -- a more emphatic version of the monday.com decline-then-recovery shape.
A89: Harness | B89: Developer Tools / DevOps | C89: 35174 | D89: 72397 | E89: =IFERROR((D89-C89)/C89,"") -> 1.0582533 | F89: 40268 | G89: 66206 | H89: =IFERROR((G89-F89)/F89,"") -> 0.6441343 | I89: 3096 | J89: 7753 | K89: =IFERROR((J89-I89)/I89,"") -> 1.504199 | L89: 72397 | M89: Jun 2026 | N89: 72397 | O89: Jun 2026 | P89: 33988 | Q89: Feb 2025 | R89: =IFERROR((D89-N89)/N89,"") -> 0 | S89: Continuous Acceleration | T89: Grew | U89: Traffic grew to a Jul 2025 local peak, pulled back through a Nov 2025 trough (a genuine ~17% multi-month dip -- closer to the Growth-then-Pullback shape through that stretch), then accelerated sharply from Dec 2025 onward, more than doubling between Jan and Jun 2026 to close the window at a new all-time high (81% above the first peak). Classified by the dominant, larger movement -- the sustained second-phase acceleration to record highs -- rather than the smaller mid-window pullback.
A90: GitLab | B90: Developer Tools / DevOps | C90: 588819 | D90: 577739 | E90: =IFERROR((D90-C90)/C90,"") -> -0.018817328 | F90: 28955 | G90: 41064 | H90: =IFERROR((G90-F90)/F90,"") -> 0.41820066 | I90: 1148700 | J90: 1354947 | K90: =IFERROR((J90-I90)/I90,"") -> 0.17954818 | L90: 1944249 | M90: Jul 2025 | N90: 1944249 | O90: Jul 2025 | P90: 547848 | Q90: Dec 2025 | R90: =IFERROR((D90-N90)/N90,"") -> -0.70284722 | S90: Volatile | T90: Flat | U90: Traffic was stable (~588K-623K) through H1 2025, then spiked dramatically in Jul 2025 to more than 3x baseline (1,944,249 -- the largest single-month anomaly by absolute traffic seen in this study, exceeding the Wrike/Hive/Float.com spikes), stayed partially elevated in Aug, then decayed back to roughly the same baseline level it started from and stayed flat through window end. Unlike Wrike/Hive (where the spike preceded a genuine post-spike decline), GitLab's pre- and post-spike baselines are nearly identical, making this a true one-time blip on an otherwise flat trend rather than an inflection point. Worth a Research Log mention alongside the other single-month anomalies.
A91: GitHub | B91: Developer Tools / DevOps | C91: 172263997 | D91: 48205217 | E91: =IFERROR((D91-C91)/C91,"") -> -0.72016662 | F91: 32328621 | G91: 18220273 | H91: =IFERROR((G91-F91)/F91,"") -> -0.43640426 | I91: 0 | J91: 0 | K91: =IFERROR((J91-I91)/I91,"") | L91: 172263997 | M91: Jan 2025 | N91: 214693421 | O91: Oct 2024 | P91: 39574026 | Q91: Feb 2026 | R91: =IFERROR((D91-N91)/N91,"") -> -0.77546952 | S91: Early Peak then Decline | T91: Declined | U91: DATA NOTE: Referring Domains is 0 for every month in this export -- almost certainly an Ahrefs metric-computation gap at GitHub's scale rather than a true zero; treat columns I/J as not meaningful for this company rather than indicating no backlinks. Traffic: GitHub's organic traffic was already declining sharply by window start (window peak = Jan 2025, the first month) and fell roughly 72% from Jan 2025 to a Feb 2026 trough, before stabilizing and ticking up slightly in the final months. The all-time historical peak (214,693,421, Oct 2024) sits just 3 months before the window opened, meaning the entire window captures GitHub already mid-collapse from its late-2024 high. This is by far the largest decline (both absolute and proportional) of any company in the study to date, on what is likely the single most authoritative domain in the entire dataset -- a strong candidate for the Research Log given the obvious hypothesis that developers increasingly route code/repo questions through AI assistants (ChatGPT, Claude, Copilot) rather than searching Google for GitHub pages, which would be directly relevant to this project's AEO/GEO thesis. Worth investigating before treating as confirmed causation.
A92: ISMS.online | B92: Security / Compliance | C92: 34543 | D92: 32713 | E92: =IFERROR((D92-C92)/C92,"") -> -0.052977448 | F92: 73852 | G92: 78625 | H92: =IFERROR((G92-F92)/F92,"") -> 0.064629259 | I92: 950 | J92: 3032 | K92: =IFERROR((J92-I92)/I92,"") -> 2.1915789 | L92: 46389 | M92: Jul 2025 | N92: 46389 | O92: Jul 2025 | P92: 28602 | Q92: Feb 2025 | R92: =IFERROR((D92-N92)/N92,"") -> -0.29481127 | S92: Volatile | T92: Flat | U92: Multiple inflection points: rose to peak Jul2025, declined through Dec2025, recovered into Q1-Q2 2026 to a near-peak Apr2026, then dipped again into Jun2026. Net change -5.30% lands in Flat band despite meaningful intra-window swings.
A93: Hyperproof | B93: Security / Compliance | C93: 36277 | D93: 45989 | E93: =IFERROR((D93-C93)/C93,"") -> 0.26771784 | F93: 105979 | G93: 117478 | H93: =IFERROR((G93-F93)/F93,"") -> 0.10850263 | I93: 1160 | J93: 2540 | K93: =IFERROR((J93-I93)/I93,"") -> 1.1896552 | L93: 50450 | M93: Mar 2026 | N93: 50450 | O93: Mar 2026 | P93: 27941 | Q93: Nov 2025 | R93: =IFERROR((D93-N93)/N93,"") -> -0.088424182 | S93: Decline then Recovery | T93: Grew | U93: Early rise to Mar2025 local peak, decline to Nov2025 trough, then strong recovery to a new all-time high in Mar2026, with slight pullback into Jun2026. Recovery phase dominates; net +26.78% (Grew), consistent with the CircleCI/Harness decline-then-recovery-to-new-high pattern.
A94: SAI360 | B94: Security / Compliance | C94: 5436 | D94: 6332 | E94: =IFERROR((D94-C94)/C94,"") -> 0.16482708 | F94: 21986 | G94: 23354 | H94: =IFERROR((G94-F94)/F94,"") -> 0.062221414 | I94: 555 | J94: 986 | K94: =IFERROR((J94-I94)/I94,"") -> 0.77657658 | L94: 10923 | M94: May 2026 | N94: 10923 | O94: May 2026 | P94: 4577 | Q94: Nov 2025 | R94: =IFERROR((D94-N94)/N94,"") -> -0.42030578 | S94: Growth then Pullback | T94: Grew | U94: ANOMALY FLAG: traffic was flat/declining (~4,600-5,500) through most of the window, then spiked sharply in Apr-May2026 (8,018 -> 10,923) before partially crashing back to 6,332 in Jun2026. Net +16.49% (Grew) is driven almost entirely by this 2-month spike, not sustained growth. Worth Pass 3 investigation for cause (campaign, content publish, etc.) -- same pattern class as Wrike/Hive/Float.com spikes flagged earlier in the study.
A95: Secfix | B95: Security / Compliance | C95: 378 | D95: 380 | E95: =IFERROR((D95-C95)/C95,"") -> 0.0052910053 | F95: 1316 | G95: 639 | H95: =IFERROR((G95-F95)/F95,"") -> -0.51443769 | I95: 170 | J95: 461 | K95: =IFERROR((J95-I95)/I95,"") -> 1.7117647 | L95: 383 | M95: Feb 2025 | N95: 425 | O95: Sep 2024 | P95: 240 | Q95: Nov 2025 | R95: =IFERROR((D95-N95)/N95,"") -> -0.10588235 | S95: Decline then Recovery | T95: Flat | U95: Small-base series (traffic in the 240-425 range) -- treat percentage changes with caution. Early local peak Feb2025, decline through 2025 to Nov2025 trough, then recovery back to near-starting level by Jun2026 (net +0.53%, Flat). Notable divergence: Traffic Value fell -51.44% while raw traffic was flat, suggesting a shift toward lower-value/less-commercial queries -- worth a Pass 3 look at which terms gained vs. lost. Historical peak (425, Sep2024) predates the study window by ~4 months.
A96: LogicGate | B96: Security / Compliance | C96: 10844 | D96: 8506 | E96: =IFERROR((D96-C96)/C96,"") -> -0.2156031 | F96: 60508 | G96: 54067 | H96: =IFERROR((G96-F96)/F96,"") -> -0.10644873 | I96: 1052 | J96: 1988 | K96: =IFERROR((J96-I96)/I96,"") -> 0.88973384 | L96: 15432 | M96: Jun 2025 | N96: 15432 | O96: Jun 2025 | P96: 7607 | Q96: Nov 2025 | R96: =IFERROR((D96-N96)/N96,"") -> -0.44880767 | S96: Early Peak then Decline | T96: Declined | U96: Peaked early in the window (Jun2025), declined to a Nov2025 trough, then a partial recovery into Q1 2026 (back up to 10,274 in Mar2026) before declining again into Jun2026. Net -21.57% (Declined); the 2026 bounce was not sustained.
... A114: Fullstory | B114: Product Analytics / Product Management | C114: 112678 | D114: 114258 | E114: =IFERROR((D114-C114)/C114,"") -> 0.014022258 | F114: 186001 | G114: 273477 | H114: =IFERROR((G114-F114)/F114,"") -> 0.47029855 | I114: 7643 | J114: 11531 | K114: =IFERROR((J114-I114)/I114,"") -> 0.50870077 | L114: 124188 | M114: May 2026 | N114: 124626 | O114: Sep 2023 | P114: 77278 | Q114: Dec 2025 | R114: =IFERROR((D114-N114)/N114,"") -> -0.083192913 | S114: Decline then Recovery | T114: Flat | U114: Declined through most of 2025 to a Dec2025 trough, then recovered strongly through 2026 to near its historical peak by Apr-May2026, with a slight pullback in Jun2026. Net traffic change is only +1.40% (Flat), but that masks the underlying recovery shape and a meaningful quality shift: Traffic Value rose +47.03% while raw traffic was essentially flat, suggesting Fullstory is now ranking for higher-value queries than it was a year ago. Historical peak (124,626, Sep2023) predates the window by ~2.3 years; current traffic sits only 8.32% below that all-time high.
A115: Mixpanel | B115: Product Analytics / Product Management | C115: 74281 | D115: 137293 | E115: =IFERROR((D115-C115)/C115,"") -> 0.8482923 | F115: 167594 | G115: 285510 | H115: =IFERROR((G115-F115)/F115,"") -> 0.70358127 | K115: =IFERROR((J115-I115)/I115,"") | L115: 137293 | M115: Jun 2026 | N115: 137293 | O115: Jun 2026 | P115: 74281 | Q115: Jan 2025 | R115: =IFERROR((D115-N115)/N115,"") -> 0 | S115: Continuous Acceleration | T115: Grew | U115: DATA NOTE: this CSV export did not include a Referring Domains column at all (unlike every other company in this study) -- Referring Domains fields (I/J) are left blank rather than guessed, per the no-invented-numbers rule. Traffic was roughly flat through most of 2025 (74k-88k), then jumped sharply in Nov2025 (130,274, a ~50% step up from Oct's 78,012) and held/grew from that new higher level through Jun2026 (137,293, all-time high). Unlike Whatfix's one-month spike-and-revert, this step-change has persisted for 8 months, so it reads as a real shift (content/product launch, ranking breakthrough) rather than an anomaly -- but still worth a Pass 3 check on what happened in Nov2025.
A116: PostHog | B116: Product Analytics / Product Management | C116: 77411 | D116: 179118 | E116: =IFERROR((D116-C116)/C116,"") -> 1.3138572 | F116: 326692 | G116: 656176 | H116: =IFERROR((G116-F116)/F116,"") -> 1.0085463 | I116: 3725 | J116: 18299 | K116: =IFERROR((J116-I116)/I116,"") -> 3.9124832 | L116: 179118 | M116: Jun 2026 | N116: 179118 | O116: Jun 2026 | P116: 77411 | Q116: Jan 2025 | R116: =IFERROR((D116-N116)/N116,"") -> 0 | S116: Continuous Acceleration | T116: Grew | U116: Clean, nearly monotonic climb across the entire window with only minor dips, ending at an all-time high in Jun2026. Net +131.39% traffic, +391.18% referring domains -- the strongest and cleanest growth profile recorded in this vertical.
A117: LogRocket | B117: Product Analytics / Product Management | C117: 103495 | D117: 124037 | E117: =IFERROR((D117-C117)/C117,"") -> 0.19848302 | F117: 65864 | G117: 66216 | H117: =IFERROR((G117-F117)/F117,"") -> 0.0053443459 | I117: 10201 | J117: 13472 | K117: =IFERROR((J117-I117)/I117,"") -> 0.32065484 | L117: 124037 | M117: Jun 2026 | N117: 368021 | O117: Aug 2023 | P117: 64962 | Q117: Nov 2025 | R117: =IFERROR((D117-N117)/N117,"") -> -0.66296217 | S117: Decline then Recovery | T117: Grew | U117: Declined from the start of the window to a Nov2025 trough, then a strong, sustained recovery through Jun2026 to a new within-window high (124,037), enough to flip the net result to Grew (+19.85%). Important long-term context: the historical peak (368,021) was set in Aug2023, nearly 3 years before the window opens, and current traffic is still 66.29% below that all-time high -- so this recovery is happening from a much lower baseline than LogRocket once had, not a return to past strength.
A118: Pendo | B118: Product Analytics / Product Management | C118: 41126 | D118: 67492 | E118: =IFERROR((D118-C118)/C118,"") -> 0.64110295 | F118: 372242 | G118: 390477 | H118: =IFERROR((G118-F118)/F118,"") -> 0.048986949 | I118: 3652 | J118: 5395 | K118: =IFERROR((J118-I118)/I118,"") -> 0.47727273 | L118: 72776 | M118: May 2026 | N118: 72776 | O118: May 2026 | P118: 37771 | Q118: Dec 2025 | R118: =IFERROR((D118-N118)/N118,"") -> -0.072606354 | S118: Continuous Acceleration | T118: Grew | U118: Flat/oscillating through 2025 (37k-48k range) with a Dec2025 dip, then a sharp acceleration through 2026 to an all-time high in May2026 (72,776), holding near that level into Jun2026 (R=-7.26%). Net +64.12% (Grew) -- same late-window-surge pattern as LaunchDarkly and Vanta.
A119: Amplitude Analytics | B119: Product Analytics / Product Management | C119: 160010 | D119: 164467 | E119: =IFERROR((D119-C119)/C119,"") -> 0.027854509 | F119: 257879 | G119: 269587 | H119: =IFERROR((G119-F119)/F119,"") -> 0.045401138 | I119: 9910 | J119: 17265 | K119: =IFERROR((J119-I119)/I119,"") -> 0.74217962 | L119: 210195 | M119: Apr 2026 | N119: 210195 | O119: Apr 2026 | P119: 132257 | Q119: Aug 2025 | R119: =IFERROR((D119-N119)/N119,"") -> -0.21755037 | S119: Growth then Pullback | T119: Flat | U119: Oscillated through 2025 (decline to an Aug2025 trough, partial recovery), then accelerated through Q1-Q2 2026 to an all-time high in Apr2026 (210,195), before a real pullback to 164,467 by Jun2026 (-21.76% off peak). Net change is only +2.78% (Flat) -- the late pullback erased most of the 2026 acceleration, similar in shape to Secureframe's growth-then-pullback pattern but landing in Flat rather than Declined.
E120: =IFERROR((D120-C120)/C120,"") | H120: =IFERROR((G120-F120)/F120,"") | K120: =IFERROR((J120-I120)/I120,"") | R120: =IFERROR((D120-N120)/N120,"")
E121: =IFERROR((D121-C121)/C121,"") | H121: =IFERROR((G121-F121)/F121,"") | K121: =IFERROR((J121-I121)/I121,"") | R121: =IFERROR((D121-N121)/N121,"")
E122: =IFERROR((D122-C122)/C122,"") | H122: =IFERROR((G122-F122)/F122,"") | K122: =IFERROR((J122-I122)/I122,"") | R122: =IFERROR((D122-N122)/N122,"")
E123: =IFERROR((D123-C123)/C123,"") | H123: =IFERROR((G123-F123)/F123,"") | K123: =IFERROR((J123-I123)/I123,"") | R123: =IFERROR((D123-N123)/N123,"")
E124: =IFERROR((D124-C124)/C124,"") | H124: =IFERROR((G124-F124)/F124,"") | K124: =IFERROR((J124-I124)/I124,"") | R124: =IFERROR((D124-N124)/N124,"")
E125: =IFERROR((D125-C125)/C125,"") | H125: =IFERROR((G125-F125)/F125,"") | K125: =IFERROR((J125-I125)/I125,"") | R125: =IFERROR((D125-N125)/N125,"")
E126: =IFERROR((D126-C126)/C126,"") | H126: =IFERROR((G126-F126)/F126,"") | K126: =IFERROR((J126-I126)/I126,"") | R126: =IFERROR((D126-N126)/N126,"")
E127: =IFERROR((D127-C127)/C127,"") | H127: =IFERROR((G127-F127)/F127,"") | K127: =IFERROR((J127-I127)/I127,"") | R127: =IFERROR((D127-N127)/N127,"")
E128: =IFERROR((D128-C128)/C128,"") | H128: =IFERROR((G128-F128)/F128,"") | K128: =IFERROR((J128-I128)/I128,"") | R128: =IFERROR((D128-N128)/N128,"")
E129: =IFERROR((D129-C129)/C129,"") | H129: =IFERROR((G129-F129)/F129,"") | K129: =IFERROR((J129-I129)/I129,"") | R129: =IFERROR((D129-N129)/N129,"")
E130: =IFERROR((D130-C130)/C130,"") | H130: =IFERROR((G130-F130)/F130,"") | K130: =IFERROR((J130-I130)/I130,"") | R130: =IFERROR((D130-N130)/N130,"")
E131: =IFERROR((D131-C131)/C131,"") | H131: =IFERROR((G131-F131)/F131,"") | K131: =IFERROR((J131-I131)/I131,"") | R131: =IFERROR((D131-N131)/N131,"")
... E500: =IFERROR((D500-C500)/C500,"") | H500: =IFERROR((G500-F500)/F500,"") | K500: =IFERROR((J500-I500)/I500,"") | R500: =IFERROR((D500-N500)/N500,"")

Sheet Pass 1 Archive
A1: Company Name | B1: Website/Domain | C1: Category | D1: Date Added | E1: Source List | F1: Source URL | G1: Screened By | H1: Screening Date | I1: B2B SaaS Confirmed? | J1: One-Line Description | K1: Founded Year | L1: Public/Private | M1: LinkedIn Employee Count | N1: Employee Count Source/Date | O1: Funding Status / Total Raised | P1: M&A Status | Q1: M&A Notes | R1: Domain Stable During Window? | S1: Primary ICP | T1: Buying Motion | U1: Primary Buyer | V1: Non-Core Asset Flag | W1: Non-Core Asset Notes | X1: Inclusion Decision | Y1: Exclusion Reason | Z1: Selected for Deep Dive? | AA1: Selected for Comparison Group? | AB1: Research Status | AC1: Tags | AD1: Last Updated
A2: Apollo.io | B2: apollo.io | C2: Sales Engagement / Sales Intelligence | D2: 2026-06-26 | E2: G2 | F2: https://www.g2.com/categories/sales-engagement | G2: Claude (S.LAB Research) | H2: 2026-06-26 | I2: Yes | J2: AI-powered sales engagement and intelligence platform (sequencing, dialer, contact database). | K2: 2015 | L2: Private | M2: 1,431 | N2: LinkedIn (cross-checked via job postings/RocketReach), 2026-06-26 — G2 page field showed placeholder '1 employee' DataOps artifact; verified independently | P2: Independent | R2: Yes | X2: Include | AB2: In Progress | AC2: Sourced from both SE and SI G2 category pages. G2 LinkedIn-employee field is a known data artifact for this company; real figure verified independently. | AD2: 2026-06-26
A3: Outreach | B3: outreach.io | C3: Sales Engagement / Sales Intelligence | D3: 2026-06-26 | E3: G2 | F3: https://www.g2.com/categories/sales-engagement | G3: Claude (S.LAB Research) | H3: 2026-06-26 | I3: Yes | J3: Sales engagement platform: multichannel sequencing, dialer, conversation intelligence. | R3: Yes | X3: Include | AB3: In Progress | AC3: Founded year/employee count/M&A status not yet verified this session — flagged for follow-up before Pass 3. | AD3: 2026-06-26
A4: Salesloft | B4: salesloft.com | C4: Sales Engagement / Sales Intelligence | D4: 2026-06-26 | E4: G2 | F4: https://www.g2.com/categories/sales-engagement | G4: Claude (S.LAB Research) | H4: 2026-06-26 | I4: Yes | J4: Sales engagement platform: cadences, dialer, deal/revenue orchestration. | P4: Independent | Q4: Merged with Clari, Dec 2025 (inside study window). Clari's revenue-intelligence/forecasting capability was absorbed into Salesloft; Clari ceases to exist as a standalone entity. Per 2026-06-26 decision, documented here only — no separate Clari row created. | R4: Yes | X4: Include | AB4: In Progress | AC4: Founded year/employee count/M&A status not yet verified this session — flagged for follow-up before Pass 3. | AD4: 2026-06-26
A5: Close | B5: close.com | C5: Sales Engagement / Sales Intelligence | D5: 2026-06-26 | E5: G2 | F5: https://www.g2.com/categories/sales-engagement | G5: Claude (S.LAB Research) | H5: 2026-06-26 | I5: Yes | J5: CRM with built-in calling/email sales engagement, aimed at SMB sales teams. | R5: Yes | X5: Include | AB5: In Progress | AC5: Founded year/employee count/M&A status not yet verified this session — flagged for follow-up before Pass 3. | AD5: 2026-06-26
A6: Amplemarket | B6: amplemarket.com | C6: Sales Engagement / Sales Intelligence | D6: 2026-06-26 | E6: G2 | F6: https://www.g2.com/categories/sales-engagement | G6: Claude (S.LAB Research) | H6: 2026-06-26 | I6: Yes | J6: AI sales platform combining lead sourcing, intelligence, and multichannel outreach. | K6: 2019 | L6: Private | M6: 40 | N6: LinkedIn (cross-checked via RocketReach), 2026-06-26 — G2 page field showed placeholder '1 employee' DataOps artifact; verified independently | P6: Independent | R6: Yes | X6: Include | AB6: In Progress | AC6: G2 LinkedIn-employee field is a known data artifact for this company; real figure verified independently. | AD6: 2026-06-26
A7: Lemlist | B7: lemlist.com | C7: Sales Engagement / Sales Intelligence | D7: 2026-06-26 | E7: G2 | F7: https://www.g2.com/categories/sales-engagement | G7: Claude (S.LAB Research) | H7: 2026-06-26 | I7: Yes | J7: Cold email and multichannel sales engagement / outreach automation tool. | R7: Yes | X7: Include | AB7: In Progress | AC7: Founded year/employee count/M&A status not yet verified this session — flagged for follow-up before Pass 3. | AD7: 2026-06-26
A8: Instantly.ai | B8: instantly.ai | C8: Sales Engagement / Sales Intelligence | D8: 2026-06-26 | E8: G2 | F8: https://www.g2.com/categories/sales-intelligence | G8: Claude (S.LAB Research) | H8: 2026-06-26 | I8: Yes | J8: Cold email outreach and deliverability platform for sales engagement. | K8: 2021 | L8: Private | M8: 275 | N8: LinkedIn (per G2), 2026-06-26 | P8: Independent | R8: Yes | X8: Include | AB8: In Progress | AC8: G2's structured 'Year Founded' field showed 2001 (data-entry error); body text and independent search confirm 2021. Confirmed 'Instantly' and 'Instantly.ai' are the same company. | AD8: 2026-06-26
A9: GetAccept | B9: getaccept.com | C9: Sales Engagement / Sales Intelligence | D9: 2026-06-26 | E9: G2 | F9: https://www.g2.com/categories/sales-engagement | G9: Claude (S.LAB Research) | H9: 2026-06-26 | I9: Yes | J9: Sales engagement, digital sales room, and e-signature platform. | R9: Yes | X9: Include | AB9: In Progress | AC9: Founded year/employee count/M&A status not yet verified this session — flagged for follow-up before Pass 3. | AD9: 2026-06-26
A10: Mixmax | B10: mixmax.com | C10: Sales Engagement / Sales Intelligence | D10: 2026-06-26 | E10: G2 | F10: https://www.g2.com/categories/sales-engagement | G10: Claude (S.LAB Research) | H10: 2026-06-26 | I10: Yes | J10: Sales engagement and email productivity platform. | R10: Yes | X10: Include | AB10: In Progress | AC10: Founded year/employee count/M&A status not yet verified this session — flagged for follow-up before Pass 3. | AD10: 2026-06-26
A11: Reply.io | B11: reply.io | C11: Sales Engagement / Sales Intelligence | D11: 2026-06-26 | E11: G2 | F11: https://www.g2.com/categories/sales-engagement | G11: Claude (S.LAB Research) | H11: 2026-06-26 | I11: Yes | J11: Multichannel sales engagement and outreach automation platform. | R11: Yes | X11: Include | AB11: In Progress | AC11: Founded year/employee count/M&A status not yet verified this session — flagged for follow-up before Pass 3. | AD11: 2026-06-26
A12: ZoomInfo | B12: zoominfo.com | C12: Sales Engagement / Sales Intelligence | D12: 2026-06-26 | E12: G2 | F12: https://www.g2.com/categories/sales-intelligence | G12: Claude (S.LAB Research) | H12: 2026-06-26 | I12: Yes | J12: Go-to-market intelligence platform: contact/company data, intent signals. | K12: 2000 | L12: Public | M12: 4,221 | N12: LinkedIn (per G2), 2026-06-26 | P12: Independent | R12: Yes | X12: Include | Z12: Yes | AB12: In Progress | AC12: Listed on G2 under rebranded product name 'GTM Workspace'; parent company is ZoomInfo Technologies (NASDAQ: ZI). | AD12: 2026-06-26
A13: Cognism | B13: cognism.com | C13: Sales Engagement / Sales Intelligence | D13: 2026-06-26 | E13: G2 | F13: https://www.g2.com/categories/sales-intelligence | G13: Claude (S.LAB Research) | H13: 2026-06-26 | I13: Yes | J13: B2B sales intelligence platform: contact data, intent signals, compliance-focused (EU/UK). | K13: 2015 | L13: Private | M13: 451 | N13: LinkedIn (per G2), 2026-06-26 | P13: Independent | R13: Yes | X13: Include | AA13: Yes | AB13: In Progress | AD13: 2026-06-26
A14: Seamless.AI | B14: seamless.ai | C14: Sales Engagement / Sales Intelligence | D14: 2026-06-26 | E14: G2 | F14: https://www.g2.com/categories/sales-intelligence | G14: Claude (S.LAB Research) | H14: 2026-06-26 | I14: Yes | J14: Real-time sales lead/contact database and prospecting intelligence platform. | K14: 2015 | L14: Private | P14: Independent | R14: Yes | X14: Include | AB14: In Progress | AC14: Listed on G2 as 'Seamless' (Seamless.AI). Employee count not shown in captured G2 excerpt — flagged for follow-up. | AD14: 2026-06-26
A15: Lusha | B15: lusha.com | C15: Sales Engagement / Sales Intelligence | D15: 2026-06-26 | E15: G2 | F15: https://www.g2.com/categories/sales-intelligence | G15: Claude (S.LAB Research) | H15: 2026-06-26 | I15: Yes | J15: B2B contact and company data / sales intelligence platform. | K15: 2016 | L15: Private | M15: 359-370 | N15: LinkedIn (per G2), 2026-06-26 — range reflects minor source discrepancy | P15: Independent | R15: Yes | X15: Include | AB15: In Progress | AD15: 2026-06-26
A16: RocketReach | B16: rocketreach.co | C16: Sales Engagement / Sales Intelligence | D16: 2026-06-26 | E16: G2 | F16: https://www.g2.com/categories/sales-intelligence | G16: Claude (S.LAB Research) | H16: 2026-06-26 | I16: Yes | J16: Contact-finding and sales intelligence / prospecting database platform. | K16: 2016 | L16: Private | M16: 95 | N16: LinkedIn (per G2), 2026-06-26 | P16: Independent | R16: Yes | X16: Include | AB16: In Progress | AD16: 2026-06-26
A17: Mailshake | B17: mailshake.com | C17: Sales Engagement / Sales Intelligence | D17: 2026-06-26 | E17: G2 | F17: https://www.g2.com/categories/sales-engagement | G17: Claude (S.LAB Research) | H17: 2026-06-26 | I17: Yes | J17: Cold email outreach and sales engagement automation tool for SMB sales teams. | R17: Yes | X17: Pending | AB17: Pending | AC17: Founded year/employee count/M&A status not yet verified this session — flagged for follow-up before Pass 3. Passed all Pass 1 gates; not selected for this round's top 15. Marked Pending — available for future rounds or swaps, per 2026-06-26 decision. | AD17: 2026-06-26
A18: Saleshandy | B18: saleshandy.com | C18: Sales Engagement / Sales Intelligence | D18: 2026-06-26 | E18: G2 | F18: https://www.g2.com/categories/sales-engagement | G18: Claude (S.LAB Research) | H18: 2026-06-26 | I18: Yes | J18: Cold email outreach and sales engagement platform with deliverability tooling. | R18: Yes | X18: Pending | AB18: Pending | AC18: Founded year/employee count/M&A status not yet verified this session — flagged for follow-up before Pass 3. Passed all Pass 1 gates; not selected for this round's top 15. Marked Pending — available for future rounds or swaps, per 2026-06-26 decision. | AD18: 2026-06-26
A19: Wiza | B19: wiza.co | C19: Sales Engagement / Sales Intelligence | D19: 2026-06-26 | E19: G2 | F19: https://www.g2.com/categories/sales-intelligence | G19: Claude (S.LAB Research) | H19: 2026-06-26 | I19: Yes | J19: LinkedIn-based contact/lead extraction and sales intelligence tool. | K19: 2019 | L19: Private | M19: 53 | N19: LinkedIn (per G2), 2026-06-26 | P19: Independent | R19: Yes | X19: Pending | AB19: Pending | AC19: Passed all Pass 1 gates; not selected for this round's top 15. Marked Pending — available for future rounds or swaps, per 2026-06-26 decision. | AD19: 2026-06-26
A20: Skrapp.io | B20: skrapp.io | C20: Sales Engagement / Sales Intelligence | D20: 2026-06-26 | E20: G2 | F20: https://www.g2.com/categories/sales-intelligence | G20: Claude (S.LAB Research) | H20: 2026-06-26 | I20: Yes | J20: Email-finding and B2B lead intelligence tool. | K20: 2019 | L20: Private | M20: 14 | N20: LinkedIn (per G2), 2026-06-26 | P20: Independent | R20: Yes | X20: Pending | AB20: Pending | AC20: Passed all Pass 1 gates; not selected for this round's top 15. Marked Pending — available for future rounds or swaps, per 2026-06-26 decision. | AD20: 2026-06-26
A21: Prospeo.io | B21: prospeo.io | C21: Sales Engagement / Sales Intelligence | D21: 2026-06-26 | E21: G2 | F21: https://www.g2.com/categories/sales-intelligence | G21: Claude (S.LAB Research) | H21: 2026-06-26 | I21: Yes | J21: Email/phone finding and verification tool for sales prospecting. | K21: 2019 | L21: Private | M21: 31 | N21: LinkedIn (per G2), 2026-06-26 | P21: Independent | R21: Yes | X21: Pending | AB21: Pending | AC21: Passed all Pass 1 gates; not selected for this round's top 15. Marked Pending — available for future rounds or swaps, per 2026-06-26 decision. | AD21: 2026-06-26
A22: BookYourData | B22: bookyourdata.com | C22: Sales Engagement / Sales Intelligence | D22: 2026-06-26 | E22: G2 | F22: https://www.g2.com/categories/sales-intelligence | G22: Claude (S.LAB Research) | H22: 2026-06-26 | I22: Yes | J22: B2B contact list and data provider for sales prospecting. | K22: 2015 | L22: Private | M22: 7 | N22: LinkedIn (per G2), 2026-06-26 | P22: Independent | R22: Yes | X22: Pending | AB22: Pending | AC22: Passed all Pass 1 gates; not selected for this round's top 15. Marked Pending — available for future rounds or swaps, per 2026-06-26 decision. | AD22: 2026-06-26
A23: Mr. E by EasyLeadz | B23: easyleadz.com | C23: Sales Engagement / Sales Intelligence | D23: 2026-06-26 | E23: G2 | F23: https://www.g2.com/categories/sales-intelligence | G23: Claude (S.LAB Research) | H23: 2026-06-26 | I23: Yes | J23: Direct-dial / contact-finding sales intelligence tool. | K23: 2016 | L23: Private | M23: 33 | N23: LinkedIn (per G2), 2026-06-26 | P23: Independent | R23: Yes | X23: Pending | AB23: Pending | AC23: Passed all Pass 1 gates; not selected for this round's top 15. Marked Pending — available for future rounds or swaps, per 2026-06-26 decision. | AD23: 2026-06-26
A24: Revenue Grid | B24: revenuegrid.com | C24: Sales Engagement / Sales Intelligence | D24: 2026-06-26 | E24: G2 | F24: https://www.g2.com/categories/sales-engagement | G24: Claude (S.LAB Research) | H24: 2026-06-26 | I24: Yes | J24: Sales engagement and revenue intelligence / guided-selling platform. | R24: Yes | X24: Pending | AB24: Pending | AC24: Founded year/employee count/M&A status not yet verified this session — flagged for follow-up before Pass 3. Passed all Pass 1 gates; not selected for this round's top 15. Marked Pending — available for future rounds or swaps, per 2026-06-26 decision. | AD24: 2026-06-26
A25: 6sense (Sales Intelligence) | B25: 6sense.com | C25: Sales Engagement / Sales Intelligence | D25: 2026-06-26 | E25: G2 | F25: https://www.g2.com/categories/sales-intelligence | G25: Claude (S.LAB Research) | H25: 2026-06-26 | I25: Yes | J25: Account-based intent and sales intelligence platform. | K25: 2013 | L25: Private | M25: 1,576 | N25: LinkedIn (per G2), 2026-06-26 | P25: Independent | R25: Yes | X25: Pending | AB25: Pending | AC25: Passed all Pass 1 gates; not selected for this round's top 15. Marked Pending — available for future rounds or swaps, per 2026-06-26 decision. | AD25: 2026-06-26
A26: Gong | B26: gong.io | C26: Sales Engagement / Sales Intelligence | D26: 2026-06-26 | E26: G2 | F26: https://www.g2.com/categories/sales-engagement | G26: Claude (S.LAB Research) | H26: 2026-06-26 | I26: Yes | J26: Revenue / conversation intelligence platform (call recording, deal insights). | R26: Yes | X26: Pending | AB26: Pending | AC26: Founded year/employee count/M&A status not yet verified this session — flagged for follow-up before Pass 3. Category fit borderline — conversation/revenue intelligence, adjacent to but distinct from contact-data sales intelligence (ZoomInfo/Apollo/Cognism style). Passed all Pass 1 gates; not selected for this round's top 15. Marked Pending — available for future rounds or swaps, per 2026-06-26 decision. | AD26: 2026-06-26
A27: Nooks | B27: nooks.ai | C27: Sales Engagement / Sales Intelligence | D27: 2026-06-26 | E27: G2 | F27: https://www.g2.com/categories/sales-engagement | G27: Claude (S.LAB Research) | H27: 2026-06-26 | I27: Yes | J27: AI-powered sales engagement: parallel dialer and virtual sales floor platform. | R27: Yes | X27: Pending | AB27: Pending | AC27: Founded year/employee count/M&A status not yet verified this session — flagged for follow-up before Pass 3. CONFLICT OF INTEREST FLAG: Nooks is an existing S.LAB client (case study at /case-studies/nooks-aeo). Passed all Pass 1 screening gates on the merits. Marked Pending rather than Include/Exclude per 2026-06-26 decision — requires explicit go/no-go before any use in deep-dive or comparison work. | AD27: 2026-06-26
A28: Agentforce Sales (Salesforce) | B28: salesforce.com | C28: Sales Engagement / Sales Intelligence | D28: 2026-06-26 | E28: G2 | F28: https://www.g2.com/categories/sales-engagement | G28: Claude (S.LAB Research) | H28: 2026-06-26 | I28: Yes | J28: AI sales agent / Sales Cloud module within the broader Salesforce CRM platform. | R28: Yes | X28: Exclude | Y28: Gate 4 fail — category fit weak. Core product is a module within Salesforce's broader CRM platform, not a standalone sales engagement product (cf. Outreach/Salesloft). | AB28: Complete | AC28: Founded year/employee count/M&A status not yet verified this session — flagged for follow-up before Pass 3. | AD28: 2026-06-26
A29: HubSpot Sales Hub | B29: hubspot.com | C29: Sales Engagement / Sales Intelligence | D29: 2026-06-26 | E29: G2 | F29: https://www.g2.com/categories/sales-engagement | G29: Claude (S.LAB Research) | H29: 2026-06-26 | I29: Yes | J29: Sales engagement module within HubSpot's broader marketing/sales/service suite. | R29: Yes | X29: Exclude | Y29: Gate 4 fail — category fit weak. Sales Hub is one module within HubSpot's broader platform, not a standalone sales engagement product. | AB29: Complete | AC29: Founded year/employee count/M&A status not yet verified this session — flagged for follow-up before Pass 3. | AD29: 2026-06-26
A30: Zoho CRM | B30: zoho.com/crm | C30: Sales Engagement / Sales Intelligence | D30: 2026-06-26 | E30: G2 | F30: https://www.g2.com/categories/sales-engagement | G30: Claude (S.LAB Research) | H30: 2026-06-26 | I30: Yes | J30: Horizontal CRM product within the broader Zoho One business suite. | R30: Yes | X30: Exclude | Y30: Gate 4 fail — category fit weak. Core product is a horizontal CRM within the broader Zoho suite, not a standalone sales engagement/intelligence product. | AB30: Complete | AC30: Founded year/employee count/M&A status not yet verified this session — flagged for follow-up before Pass 3. | AD30: 2026-06-26
A31: Bigin by Zoho CRM | B31: zoho.com/bigin | C31: Sales Engagement / Sales Intelligence | D31: 2026-06-26 | E31: G2 | F31: https://www.g2.com/categories/sales-engagement | G31: Claude (S.LAB Research) | H31: 2026-06-26 | I31: Yes | J31: Lightweight CRM product within the broader Zoho suite, aimed at small businesses. | R31: Yes | X31: Exclude | Y31: Gate 4 fail — category fit weak. Lightweight CRM module of the Zoho suite, not a standalone sales engagement product. | AB31: Complete | AC31: Founded year/employee count/M&A status not yet verified this session — flagged for follow-up before Pass 3. | AD31: 2026-06-26
A32: ActiveCampaign | B32: activecampaign.com | C32: Sales Engagement / Sales Intelligence | D32: 2026-06-26 | E32: G2 | F32: https://www.g2.com/categories/sales-engagement | G32: Claude (S.LAB Research) | H32: 2026-06-26 | I32: Yes | J32: Email marketing automation platform with bundled CRM/sales features. | R32: Yes | X32: Exclude | Y32: Gate 4 fail — category fit weak. Core product is email marketing automation; sales/CRM features are a bundled add-on, not the core product. | AB32: Complete | AC32: Founded year/employee count/M&A status not yet verified this session — flagged for follow-up before Pass 3. | AD32: 2026-06-26
A33: LinkedIn Sales Navigator | B33: linkedin.com | C33: Sales Engagement / Sales Intelligence | D33: 2026-06-26 | E33: G2 | F33: https://www.g2.com/categories/sales-intelligence | G33: Claude (S.LAB Research) | H33: 2026-06-26 | I33: Yes | J33: Prospecting and sales intelligence tool bundled into the LinkedIn platform. | K33: 2003 | L33: Private (Microsoft-owned) | M33: 23,847 | N33: LinkedIn (per G2), 2026-06-26 | P33: Acquired | Q33: Owned by Microsoft since 2016 acquisition of LinkedIn. | R33: Yes | X33: Exclude | Y33: Gate 1 fail — primary business is not B2B SaaS. LinkedIn's primary business is a professional social network; Sales Navigator is one product line within a company owned by Microsoft, not a standalone B2B SaaS company. | AB33: Complete | AD33: 2026-06-26
A34: Microsoft Relationship Sales | B34: microsoft.com | C34: Sales Engagement / Sales Intelligence | D34: 2026-06-26 | E34: G2 | F34: https://www.g2.com/categories/sales-intelligence | G34: Claude (S.LAB Research) | H34: 2026-06-26 | I34: Yes | J34: Bundled LinkedIn Sales Navigator + Dynamics 365 sales product line. | K34: 1975 | L34: Public | M34: 231,632 | N34: LinkedIn (per G2), 2026-06-26 | P34: Independent | R34: Yes | X34: Exclude | Y34: Gate 1 fail — primary business is not B2B SaaS. Microsoft is a diversified technology conglomerate (OS, cloud infrastructure, hardware, gaming, productivity); Relationship Sales is a bundled product line, not the company's core/primary business. | AB34: Complete | AD34: 2026-06-26
A35: LinkedIn Sales Insights | B35: linkedin.com | C35: Sales Engagement / Sales Intelligence | D35: 2026-06-26 | E35: G2 | F35: https://www.g2.com/categories/sales-intelligence | G35: Claude (S.LAB Research) | H35: 2026-06-26 | I35: Yes | J35: Sales analytics product bundled into the LinkedIn platform; discontinued Dec 31, 2024. | P35: Acquired | Q35: Owned by Microsoft since 2016 acquisition of LinkedIn. | R35: Yes | X35: Exclude | Y35: Gate 1 and Gate 3 fail — primary business not B2B SaaS (see LinkedIn Sales Navigator), and product was discontinued Dec 31, 2024, before the study window (Jan 2025–Jun 2026) began — fully inactive for the entire window. | AB35: Complete | AC35: Per G2's own page text, product was discontinued Dec 31, 2024. | AD35: 2026-06-26
A36: DealHub | B36: dealhub.io | C36: Sales Engagement / Sales Intelligence | D36: 2026-06-26 | E36: G2 | F36: https://www.g2.com/categories/sales-engagement | G36: Claude (S.LAB Research) | H36: 2026-06-26 | I36: Yes | J36: CPQ (configure-price-quote) and deal management platform. | R36: Yes | X36: Exclude | Y36: Gate 4 fail — category fit weak. Core product is CPQ/deal management, not sales engagement or sales intelligence. | AB36: Complete | AC36: Founded year/employee count/M&A status not yet verified this session — flagged for follow-up before Pass 3. | AD36: 2026-06-26
A37: Seismic Enablement Cloud | B37: seismic.com | C37: Sales Engagement / Sales Intelligence | D37: 2026-06-26 | E37: G2 | F37: https://www.g2.com/categories/sales-engagement | G37: Claude (S.LAB Research) | H37: 2026-06-26 | I37: Yes | J37: Sales enablement and content management platform. | R37: Yes | X37: Exclude | Y37: Gate 4 fail — category fit weak. Core product is sales enablement/content management, a distinct category from sales engagement (cadence/sequencing) or sales intelligence (contact/intent data). | AB37: Complete | AC37: Founded year/employee count/M&A status not yet verified this session — flagged for follow-up before Pass 3. | AD37: 2026-06-26
A38: CaptivateIQ | B38: captivateiq.com | C38: Sales Engagement / Sales Intelligence | D38: 2026-06-26 | E38: G2 | F38: https://www.g2.com/categories/sales-intelligence | G38: Claude (S.LAB Research) | H38: 2026-06-26 | I38: Yes | J38: Sales compensation / SPM (commission management) platform. | K38: 2017 | L38: Private | M38: 271 | N38: LinkedIn (per G2), 2026-06-26 | P38: Independent | R38: Yes | X38: Exclude | Y38: Gate 4 fail — wrong category entirely. Core product is sales compensation/SPM (commission management), not sales engagement or sales intelligence. | AB38: Complete | AD38: 2026-06-26
A39: D&B Hoovers | B39: dnb.com | C39: Sales Engagement / Sales Intelligence | D39: 2026-06-26 | E39: G2 | F39: https://www.g2.com/categories/sales-intelligence | G39: Claude (S.LAB Research) | H39: 2026-06-26 | I39: Yes | J39: Sales intelligence and business data platform (Dun & Bradstreet). | L39: Private (post take-private) | M39: 5,747 | N39: LinkedIn (per G2), 2026-06-26 | P39: Acquired | Q39: Parent company Dun & Bradstreet taken private by Clearlake Capital, $7.7B, deal closed Aug 26, 2025 (inside study window: Jan 2025–Jun 2026); NYSE delisting. | R39: Yes | X39: Exclude | Y39: Gate 2/3 fail — recent, disruptive M&A event inside the study window per manual's M&A treatment rule; no clean continuous ownership/attribution story available. | AB39: Complete | AC39: G2 page lists 'Ownership: NYSE: DNB' — outdated as of Aug 2025 take-private. Verify independently if revisited. | AD39: 2026-06-26
A40: Klaviyo | B40: klaviyo.com | C40: Marketing Automation | D40: 2026-06-26 | E40: G2 | F40: https://www.g2.com/categories/marketing-automation | G40: Claude (S.LAB Research) | H40: 2026-06-26 | I40: Yes | J40: Email/SMS marketing automation and customer data platform built for ecommerce brands. | L40: Public (NYSE: KVYO) | O40: Public company; IPO Sept 2023 | P40: Independent | Q40: Acquired Gatsby (social automation), Aug 14, 2025 — Klaviyo as acquirer; not disruptive to Klaviyo itself. | R40: Yes | X40: Include | AB40: In Progress | AC40: LOCKED — Marketing Automation vertical (15). Founded year and employee count not verified this session — flag for follow-up before Pass 2. | AD40: 2026-06-26
A41: Braze | B41: braze.com | C41: Marketing Automation | D41: 2026-06-26 | E41: G2 | F41: https://www.g2.com/categories/marketing-automation | G41: Claude (S.LAB Research) | H41: 2026-06-26 | I41: Yes | J41: Cross-channel customer engagement platform (push, email, SMS, in-app) for marketing automation. | L41: Public (NASDAQ: BRZE) | O41: Public company | P41: Independent | Q41: Acquired OfferFit ($325M, cash + stock), completed June 2, 2025 — Braze as acquirer; not disruptive to Braze itself. | R41: Yes | X41: Include | Z41: Yes | AB41: In Progress | AC41: LOCKED — Marketing Automation vertical (15). Founded year and employee count not verified this session — flag for follow-up before Pass 2. | AD41: 2026-06-26
A42: HubSpot Marketing Hub | B42: hubspot.com | C42: Marketing Automation | D42: 2026-06-26 | E42: G2 | F42: https://www.g2.com/categories/marketing-automation | G42: Claude (S.LAB Research) | H42: 2026-06-26 | I42: Yes | J42: Marketing automation product line (email, landing pages, workflows, lead nurturing) within the HubSpot platform. | L42: Public (NYSE: HUBS) | O42: Public company | P42: Independent | R42: Yes | V42: Yes | W42: Part of HubSpot's broader CRM platform, but core product function matches the category (unlike Sales Hub in the Sales Engagement vertical). | X42: Include | AB42: In Progress | AC42: LOCKED — Marketing Automation vertical (15). Gate-4 judgment note: unlike HubSpot Sales Hub (excluded from Sales Engagement vertical as a generic CRM module), Marketing Hub's core function IS marketing automation/email — this is the company's original, namesake product line, not an adjacent bundled module. Founded year/employee count not verified this session. | AD42: 2026-06-26
A43: ActiveCampaign | B43: activecampaign.com | C43: Marketing Automation | D43: 2026-06-26 | E43: G2 | F43: https://www.g2.com/categories/marketing-automation | G43: Claude (S.LAB Research) | H43: 2026-06-26 | I43: Yes | J43: Email marketing automation and CRM platform for small and mid-sized businesses. | R43: Yes | X43: Include | AA43: Yes | AB43: In Progress | AC43: LOCKED — Marketing Automation vertical (15). Cross-vertical reassignment: excluded from Sales Engagement/Sales Intelligence vertical (2026-06-26) on Gate 4 grounds because its core product is marketing automation, not sales engagement. Per user decision (one company, one best-fit category), it is included here instead, where Marketing Automation is its correct primary category. M&A/employee count not verified this session — flag for follow-up before Pass 2. | AD43: 2026-06-26
A44: Customer.io | B44: customer.io | C44: Marketing Automation | D44: 2026-06-26 | E44: G2 | F44: https://www.g2.com/categories/marketing-automation | G44: Claude (S.LAB Research) | H44: 2026-06-26 | I44: Yes | J44: Customer messaging and marketing automation platform for product-led growth companies. | L44: Private | O44: $40.3M total raised across 6 rounds; $690M valuation set in 2022 Series A ($35M) | P44: Independent | Q44: Acquired Parcel (productivity/business software), Aug 23, 2022 — Customer.io as acquirer; not disruptive. Reported $100M ARR as of Sept 2025 (revenue metric, not funding). | R44: Yes | X44: Include | AB44: In Progress | AC44: LOCKED — Marketing Automation vertical (15). Founded year/employee count not verified this session — flag for follow-up before Pass 2. | AD44: 2026-06-26
A45: Omnisend | B45: omnisend.com | C45: Marketing Automation | D45: 2026-06-26 | E45: G2 | F45: https://www.g2.com/categories/marketing-automation | G45: Claude (S.LAB Research) | H45: 2026-06-26 | I45: Yes | J45: Email and SMS marketing automation platform for ecommerce brands. | L45: Private | O45: $1.57M total raised, single round (Dec 18, 2019) — minimal external VC funding, bootstrapped-leaning | P45: Independent | R45: Yes | X45: Include | AB45: In Progress | AC45: LOCKED — Marketing Automation vertical (15). Founded year/employee count not verified this session — flag for follow-up before Pass 2. | AD45: 2026-06-26
A46: Attentive | B46: attentive.com | C46: Marketing Automation | D46: 2026-06-26 | E46: G2 | F46: https://www.g2.com/categories/marketing-automation | G46: Claude (S.LAB Research) | H46: 2026-06-26 | I46: Yes | J46: SMS and email marketing platform for ecommerce and retail brands. | L46: Private | O46: $922M total raised | P46: Independent | Q46: Acquired Yotpo's email and SMS marketing customer base, Aug 6, 2025 — Attentive as acquirer (Yotpo exited the category and laid off ~200 staff); not disruptive to Attentive itself. | R46: Yes | X46: Include | AB46: In Progress | AC46: LOCKED — Marketing Automation vertical (15). Founded year/employee count not verified this session — flag for follow-up before Pass 2. | AD46: 2026-06-26
A47: Iterable | B47: iterable.com | C47: Marketing Automation | D47: 2026-06-26 | E47: G2 | F47: https://www.g2.com/categories/marketing-automation | G47: Claude (S.LAB Research) | H47: 2026-06-26 | I47: Yes | J47: Cross-channel customer engagement and marketing automation platform. | K47: 2013 | L47: Private | M47: 867 | N47: Tracxn (LinkedIn-sourced), as of 2026-04-30 | O47: $343M total raised; $200M Series E, June 15, 2021 | P47: Independent | Q47: No acquisitions made or received as of this screening. | R47: Yes | X47: Include | AB47: In Progress | AC47: LOCKED — Marketing Automation vertical (15). | AD47: 2026-06-26
A48: Brevo | B48: brevo.com | C48: Marketing Automation | D48: 2026-06-26 | E48: G2 | F48: https://www.g2.com/categories/email-marketing | G48: Claude (S.LAB Research) | H48: 2026-06-26 | I48: Yes | J48: Customer engagement platform (email, SMS, CRM) for SMBs; formerly Sendinblue, rebranded 2022. | L48: Private (unicorn, 2025) | M48: 898 | N48: LinkedIn (per G2), 2026-06-26 | O48: €500M (~$583M) round in 2025 led by General Atlantic and Oakley Capital; valuation exceeds $1B | P48: Independent | Q48: Acquired Cohort, Sept 17, 2025 — Brevo as acquirer; not disruptive. Note: rebranded from "Sendinblue" to "Brevo" in 2022 — same legal entity, not an M&A event. | R48: Yes | X48: Include | AB48: In Progress | AC48: LOCKED — Marketing Automation vertical (15). Founded year not verified this session. | AD48: 2026-06-26
A49: Insider | B49: useinsider.com | C49: Marketing Automation | D49: 2026-06-26 | E49: G2 | F49: https://www.g2.com/categories/marketing-automation | G49: Claude (S.LAB Research) | H49: 2026-06-26 | I49: Yes | J49: AI-native omnichannel customer engagement and personalization platform. | K49: 2012 | L49: Private | O49: $771M total raised; $500M Series E led by General Atlantic (Oct 2024) | P49: Independent | Q49: No acquisitions found. | R49: Yes | X49: Include | AB49: In Progress | AC49: LOCKED — Marketing Automation vertical (15). G2 product listing name is 'Insider One'; company/brand is 'Insider' (useinsider.com). Company press materials cite ~1,100+ team members, but this is not an independently confirmed LinkedIn company-page figure — left blank pending verification rather than recording an unconfirmed number. | AD49: 2026-06-26
A50: CleverTap | B50: clevertap.com | C50: Marketing Automation | D50: 2026-06-26 | E50: G2 | F50: https://www.g2.com/categories/marketing-automation | G50: Claude (S.LAB Research) | H50: 2026-06-26 | I50: Yes | J50: Customer engagement and retention platform (push, in-app, email, web) with CDP capabilities. | L50: Private | M50: 472 | N50: Tracxn (LinkedIn-sourced), as of 2025-04-30 | O50: $303M total raised per one source ($182M over 8 rounds per another — sources disagree, flagging both) | P50: Independent | Q50: Acquired Rehook.ai, Apr 15, 2025, and Leanplum (2022) — CleverTap as acquirer in both cases. ~60-70 Leanplum-origin staff laid off in 2025 during integration (operating note, not disruptive to CleverTap continuity). | R50: Yes | X50: Include | AB50: In Progress | AC50: LOCKED — Marketing Automation vertical (15). Founded year not verified this session. Funding total figure disagreement between sources — disclosed, not resolved. | AD50: 2026-06-26
A51: GetResponse | B51: getresponse.com | C51: Marketing Automation | D51: 2026-06-26 | E51: G2 | F51: https://www.g2.com/categories/marketing-automation | G51: Claude (S.LAB Research) | H51: 2026-06-26 | I51: Yes | J51: Email marketing and marketing automation platform with lifecycle/CRM features. | K51: 1998 | L51: Private | M51: 428 | N51: LinkedIn (per G2), 2026-06-26 | P51: Independent | Q51: No acquisitions found. HQ: Poland. | R51: Yes | X51: Include | AB51: In Progress | AC51: LOCKED — Marketing Automation vertical (15). Sourced from both Marketing Automation and Email Marketing G2 category pages. | AD51: 2026-06-26
A52: ContactPigeon | B52: contactpigeon.com | C52: Marketing Automation | D52: 2026-06-26 | E52: G2 | F52: https://www.g2.com/categories/marketing-automation | G52: Claude (S.LAB Research) | H52: 2026-06-26 | I52: Yes | J52: Omnichannel customer engagement and marketing automation platform for ecommerce/retail. | K52: 2014 | L52: Private | P52: Independent | Q52: No acquisitions found. HQ: Athens, Greece (registered HQ New York, US). | R52: Yes | X52: Include | AB52: In Progress | AC52: LOCKED — Marketing Automation vertical (15). Employee count sources disagreed/imprecise (e.g., "51-100" for one office location only) — left blank rather than recording an unconfirmed figure; flag for follow-up. | AD52: 2026-06-26
A53: MailerLite | B53: mailerlite.com | C53: Marketing Automation | D53: 2026-06-26 | E53: G2 | F53: https://www.g2.com/categories/email-marketing | G53: Claude (S.LAB Research) | H53: 2026-06-26 | I53: Yes | J53: Email marketing and automation platform for creators and small businesses. | K53: 2010 | L53: Private | M53: 168 | N53: LinkedIn (per G2), 2026-06-26 | P53: Independent | Q53: No acquisitions found. HQ: San Francisco, CA (Lithuania origin). | R53: Yes | X53: Include | AB53: In Progress | AC53: LOCKED — Marketing Automation vertical (15). | AD53: 2026-06-26
A54: Flodesk | B54: flodesk.com | C54: Marketing Automation | D54: 2026-06-26 | E54: G2 | F54: https://www.g2.com/categories/email-marketing | G54: Claude (S.LAB Research) | H54: 2026-06-26 | I54: Yes | J54: Email marketing platform for small businesses and creators with brand-first design tools. | K54: 2018 | L54: Private | M54: 88 | N54: LinkedIn (per G2), 2026-06-26 | O54: Bootstrapped, no external funding; $36M+ ARR, profitable since second week after launch | P54: Independent | Q54: No acquisitions found. HQ: San Francisco, CA. | R54: Yes | X54: Include | AB54: In Progress | AC54: LOCKED — Marketing Automation vertical (15). G2 page shows a discrepancy: long-form description says 'Founded in 2019,' but the structured 'Year Founded' field says 2018 — used the structured field (2018) per established standardization practice, flagging the discrepancy. | AD54: 2026-06-26
A55: Bloomreach | B55: bloomreach.com | C55: Marketing Automation | D55: 2026-06-26 | E55: G2 | F55: https://www.g2.com/categories/marketing-automation | G55: Claude (S.LAB Research) | H55: 2026-06-26 | I55: Yes | J55: Ecommerce-focused marketing automation and customer data platform with AI-driven personalization. | K55: 2009 | L55: Private | O55: $422M total raised; $2.2B valuation following $175M round led by Goldman Sachs Asset Management (2022) | P55: Independent | Q55: Acquired Exponea (CDP/marketing automation) and Radiance Commerce (Jan 2024) as acquirer — exact Exponea acquisition date not verified this session. No acquisitions in 2025 per available sources. | R55: Yes | X55: Pending | AB55: Pending | AC55: PENDING alternate — Marketing Automation vertical. Employee count not verified this session. | AD55: 2026-06-26
A56: Mailchimp (Intuit Mailchimp) | B56: mailchimp.com | C56: Marketing Automation | D56: 2026-06-26 | E56: G2 | F56: https://www.g2.com/categories/marketing-automation | G56: Claude (S.LAB Research) | H56: 2026-06-26 | I56: Yes | J56: All-in-one email marketing and marketing automation platform for small businesses. | K56: 2001 | L56: Private subsidiary of Intuit (public parent, NASDAQ: INTU) | M56: 1,553 | N56: LinkedIn (per G2, Email Marketing category listing), 2026-06-26 | P56: Acquired (continuous) | Q56: Acquired by Intuit — announced Sept 13, 2021 (~$12B), closed end of Jan 2022. Well before the Jan 2025 study window; continuous integration since. Per manual calibration, include-with-flag (not exclude) — pre-window, well-documented, continuous. | R56: Yes | V56: Yes | W56: Intuit's primary business is broader financial software (TurboTax, QuickBooks); Mailchimp is a major acquired, non-core product line. | X56: Pending | AB56: Pending | AC56: PENDING alternate — Marketing Automation vertical. Sourced from both Marketing Automation ("All-in-One Marketing Platform") and Email Marketing ("Email Marketing") G2 listings — same underlying product/company. | AD56: 2026-06-26
A57: Dotdigital | B57: dotdigital.com | C57: Marketing Automation | D57: 2026-06-26 | E57: G2 | F57: https://www.g2.com/categories/marketing-automation | G57: Claude (S.LAB Research) | H57: 2026-06-26 | I57: Yes | J57: Cross-channel marketing automation platform (email, SMS, and more) for ecommerce/retail. | K57: 1999 | L57: Public (LSE: DOTD) | M57: 465 | N57: LinkedIn (per G2 Email Marketing page's structured field), 2026-06-26 | P57: Independent | Q57: M&A status not explicitly verified this session — flag for follow-up before Pass 2. | R57: Yes | X57: Pending | AB57: Pending | AC57: PENDING alternate — Marketing Automation vertical. Formerly Dotmailer. Sourced from both Marketing Automation and Email Marketing G2 pages. Minor employee-count discrepancy: company's own description text says '450+', G2's structured LinkedIn field says 465 — used 465 per standard practice of trusting the structured field. | AD57: 2026-06-26
A58: Adobe Marketo Engage | B58: marketo.com | C58: Marketing Automation | D58: 2026-06-26 | E58: G2 | F58: https://www.g2.com/categories/marketing-automation | G58: Claude (S.LAB Research) | H58: 2026-06-26 | I58: Yes | J58: Enterprise B2B marketing automation platform (lead management, campaign orchestration). | L58: Subsidiary of Adobe (public parent, NASDAQ: ADBE) | P58: Acquired (continuous) | Q58: Acquired by Adobe, Oct 31, 2018 (~$4.74B cash); Adobe itself had acquired Marketo from Vista Equity Partners (which bought it May 2016). Well before the study window; continuous integration since as "Marketo Engage" within Adobe Experience/Marketing Cloud. Per manual calibration, include-with-flag. | R58: Yes | V58: Yes | W58: Adobe's primary business is broader creative/digital-experience software; Marketo Engage is one component within Adobe Experience Cloud, though its core function is still marketing automation (Gate 4 pass). | X58: Pending | AB58: Pending | AC58: PENDING alternate — Marketing Automation vertical. Founded year and employee count not verified this session. | AD58: 2026-06-26
A59: Agentforce Marketing (Salesforce Marketing Cloud) | B59: salesforce.com | C59: Marketing Automation | D59: 2026-06-26 | E59: G2 | F59: https://www.g2.com/categories/marketing-automation | G59: Claude (S.LAB Research) | H59: 2026-06-26 | I59: Yes | J59: Enterprise marketing automation and cross-channel engagement platform; renamed from "Salesforce Marketing Cloud" to "Agentforce Marketing" in 2025. | L59: Subsidiary product of Salesforce (public parent, NYSE: CRM) | P59: Independent | Q59: No ownership change — internal product rebrand announced at Dreamforce 2025 (part of Salesforce dropping the "Cloud" naming convention fleet-wide in favor of "Agentforce"). Underlying product traces to the ExactTarget acquisition (2013), well before the study window. | R59: Yes | V59: Yes | W59: Salesforce's primary business is broad CRM platform; Agentforce Marketing is one of several Agentforce-branded product lines, though its core function is still marketing automation (Gate 4 pass). | X59: Pending | AB59: Pending | AC59: PENDING alternate — Marketing Automation vertical. Founded year and employee count not verified this session. 2025 rebrand is a renaming, not an M&A event. | AD59: 2026-06-26
A60: EngageBay | B60: engagebay.com | C60: Marketing Automation | D60: 2026-06-26 | E60: G2 | F60: https://www.g2.com/categories/marketing-automation | G60: Claude (S.LAB Research) | H60: 2026-06-26 | I60: Yes | J60: All-in-one marketing, sales, and support CRM software for small businesses. | L60: Private, bootstrapped | M60: 28 | N60: As of 2025-07-31 (source citing company-reported headcount; down 41% YoY) | O60: No external funding reported | P60: Independent | Q60: No acquisitions found. | R60: Yes | X60: Pending | AB60: Pending | AC60: PENDING alternate — Marketing Automation vertical. Headcount decline noted as an operating trend; not a gate factor since employee count is metadata-only per manual V1.1. | AD60: 2026-06-26
A61: Constant Contact | B61: constantcontact.com | C61: Marketing Automation | D61: 2026-06-26 | E61: G2 | F61: https://www.g2.com/categories/email-marketing | G61: Claude (S.LAB Research) | H61: 2026-06-26 | I61: Yes | J61: Email marketing and digital marketing platform for small businesses. | K61: 1995 | L61: Private, PE-owned (Clearlake Capital Group) | M61: 1,147 | N61: LinkedIn (per G2), 2026-06-26 | O61: New Clearlake-managed strategic investment closed Oct 7, 2025 (capital raise, not ownership change) | P61: Independent (continuous PE ownership) | Q61: Majority-owned by Clearlake Capital since early 2024; previously a Clearlake/Siris Capital joint venture spun out of Endurance International Group in 2021 — continuous ownership, not a disruptive event inside the window. Acquired Moosend, June 6, 2025, as acquirer (see Moosend exclusion row). | R61: Yes | X61: Pending | AB61: Pending | AC61: PENDING alternate — Marketing Automation vertical. | AD61: 2026-06-26
A62: Sender.net | B62: sender.net | C62: Marketing Automation | D62: 2026-06-26 | E62: G2 | F62: https://www.g2.com/categories/email-marketing | G62: Claude (S.LAB Research) | H62: 2026-06-26 | I62: Yes | J62: Email and SMS marketing automation platform for small businesses. | K62: 2012 | L62: Private | M62: 30 | N62: LinkedIn (per G2), 2026-06-26 | Q62: M&A status not explicitly verified this session — flag for follow-up before Pass 2. | R62: Yes | X62: Pending | AB62: Pending | AC62: PENDING alternate — Marketing Automation vertical. HQ: Vilnius, Lithuania. | AD62: 2026-06-26
A63: Levitate | B63: levitate.ai | C63: Marketing Automation | D63: 2026-06-26 | E63: G2 | F63: https://www.g2.com/categories/email-marketing | G63: Claude (S.LAB Research) | H63: 2026-06-26 | I63: Yes | J63: Relationship-marketing platform for small businesses (personalized email/SMS at scale, client engagement). | K63: 2017 | L63: Private | M63: 432 | N63: LinkedIn (per G2), 2026-06-26 | Q63: M&A status not explicitly verified this session — flag for follow-up before Pass 2. | R63: Yes | X63: Pending | AB63: Pending | AC63: PENDING alternate — Marketing Automation vertical. Founded by Jesse Lipson (creator of ShareFile). HQ: Raleigh, NC. | AD63: 2026-06-26
A64: Systeme.io | B64: systeme.io | C64: Marketing Automation | D64: 2026-06-26 | E64: G2 | F64: https://www.g2.com/categories/email-marketing | G64: Claude (S.LAB Research) | H64: 2026-06-26 | I64: Yes | J64: All-in-one online business platform (funnels, email marketing, courses) for entrepreneurs. | K64: 2017 | L64: Private | M64: 217 | N64: LinkedIn (per G2), 2026-06-26 | Q64: M&A status not explicitly verified this session — flag for follow-up before Pass 2. | R64: Yes | X64: Pending | AB64: Pending | AC64: PENDING alternate — Marketing Automation vertical. HQ: Dublin (Tyrrelstown). | AD64: 2026-06-26
A65: Zoho Campaigns | B65: zoho.com/campaigns | C65: Marketing Automation | D65: 2026-06-26 | E65: G2 | F65: https://www.g2.com/categories/email-marketing | G65: Claude (S.LAB Research) | H65: 2026-06-26 | I65: Yes | J65: Email marketing and automation product within the Zoho suite. | K65: 1996 | L65: Private (Zoho Corp — bootstrapped, never raised VC, never acquired) | M65: 30,766 | N65: LinkedIn (per G2), 2026-06-26 — company-wide Zoho Corp figure, NOT specific to the Campaigns product | P65: Independent | Q65: No acquisitions found for Zoho Corp. | R65: Yes | V65: Yes | W65: Zoho Campaigns is one of dozens of products in Zoho's broad horizontal SaaS suite — flagging for Pass 2 category-fit judgment given how large/diversified the parent suite is. | X65: Pending | AB65: Pending | AC65: PENDING alternate — Marketing Automation vertical. Employee count is a known parent-company-wide figure, not product-specific — same data-confound pattern flagged elsewhere in this project. | AD65: 2026-06-26
A66: Netcore Cloud (Customer Engagement Platform) | B66: netcorecloud.com | C66: Marketing Automation | D66: 2026-06-26 | E66: G2 | F66: https://www.g2.com/categories/marketing-automation | G66: Claude (S.LAB Research) | H66: 2026-06-26 | I66: Yes | J66: AI-powered customer engagement and marketing platform (email, push, in-app, WhatsApp). | L66: Private | Q66: Not verified this session — flag for follow-up before Pass 2. | R66: Yes | X66: Pending | AB66: Pending | AC66: PENDING alternate — Marketing Automation vertical. Consolidated entry: G2 separately lists 'Netcore Customer Engagement Platform' (Marketing Automation page) and 'Netcore Email API' (Email Marketing page) as separate product pages under the same parent company (Netcore Cloud, formerly Netcore Smartech) — kept as one candidate; see Netcore Email API exclusion row. | AD66: 2026-06-26
A67: Evam | B67: evam.com | C67: Marketing Automation | D67: 2026-06-26 | E67: G2 | F67: https://www.g2.com/categories/marketing-automation | G67: Claude (S.LAB Research) | H67: 2026-06-26 | I67: Uncertain — Gate 1 concern | J67: Real-time, cross-channel customer engagement/martech platform; clients include Vodafone, T-Mobile, Turkcell, ING Bank, Garanti BBVA. | X67: Pending | AB67: Pending | AC67: FLAGGED for user decision — Marketing Automation vertical. Gate 1 ambiguity: serves telecom/banking enterprise clients at carrier/bank scale, which is more characteristic of licensed enterprise software or systems-integration-style deployment than confirmed self-serve multi-tenant SaaS. Not enough evidence gathered this session to confirm or rule out B2B SaaS classification — recommend exclude on Gate 1 caution pending confirmation, per standing 'ask if unsure' rule. | AD67: 2026-06-26
A68: Zapier | B68: zapier.com | C68: Marketing Automation | D68: 2026-06-26 | E68: G2 | F68: https://www.g2.com/categories/marketing-automation | G68: Claude (S.LAB Research) | H68: 2026-06-26 | I68: Yes | J68: Workflow/iPaaS automation platform connecting apps via triggers and actions. | R68: Yes | X68: Exclude | Y68: Gate 4 fail — wrong category entirely. Core product is workflow/iPaaS automation connecting apps, not marketing automation or email marketing software, even though marketers use it adjacently. | AB68: Complete | AD68: 2026-06-26
A69: Pipedrive | B69: pipedrive.com | C69: Marketing Automation | D69: 2026-06-26 | E69: G2 | F69: https://www.g2.com/categories/email-marketing | G69: Claude (S.LAB Research) | H69: 2026-06-26 | I69: Yes | J69: Sales CRM with customizable pipelines, used by sales teams to close deals. | K69: 2010 | M69: 1,045 | N69: LinkedIn (per G2), 2026-06-26 | R69: Yes | X69: Exclude | Y69: Gate 4 fail — wrong category entirely. Core product is CRM/sales pipeline management, not email marketing software, despite appearing on G2's Email Marketing category page. | AB69: Complete | AC69: HQ: New York. | AD69: 2026-06-26
A70: GMass | B70: gmass.co | C70: Marketing Automation | D70: 2026-06-26 | E70: G2 | F70: https://www.g2.com/categories/email-marketing | G70: Claude (S.LAB Research) | H70: 2026-06-26 | I70: Yes | J70: Gmail-based mail-merge and cold-outreach automation tool (follow-up sequences, deliverability testing). | K70: 2014 | M70: 12 | N70: LinkedIn (per G2), 2026-06-26 | R70: Yes | X70: Exclude | Y70: Gate 4 fail — better category fit elsewhere. Core function (Gmail-based mail merge, cold-outreach follow-up sequences) matches the Sales Engagement/cold-outreach category (same use case as Instantly/lemlist), not marketing-team email marketing software. Not screened against the Sales Engagement vertical, which is already closed. | AB70: Complete | AC70: HQ: Chicago, IL. | AD70: 2026-06-26
A71: Success.ai | B71: success.ai | C71: Marketing Automation | D71: 2026-06-26 | E71: G2 | F71: https://www.g2.com/categories/email-marketing | G71: Claude (S.LAB Research) | H71: 2026-06-26 | I71: Yes | J71: B2B lead-generation and cold email outreach platform (700M+ contact database, email warm-up, AI writer). | M71: 87 | N71: LinkedIn (per G2), 2026-06-26 | R71: Yes | X71: Exclude | Y71: Gate 4 fail — better category fit elsewhere. Explicitly positioned for B2B lead generation and cold email outreach by sales teams — same category as Instantly/lemlist (Sales Engagement, already a closed vertical), not marketing-team email marketing software. | AB71: Complete | AC71: HQ: Sheridan, WY. | AD71: 2026-06-26
A72: Sendpilot AI | B72: sendpilot.ai | C72: Marketing Automation | D72: 2026-06-26 | E72: G2 | F72: https://www.g2.com/categories/marketing-automation | G72: Claude (S.LAB Research) | H72: 2026-06-26 | I72: Yes | J72: LinkedIn outreach and revenue-management tool (sequence builder, LinkedIn lead database). | R72: Yes | X72: Exclude | Y72: Gate 4 fail — wrong category. Core product is a LinkedIn outreach/sales-engagement tool, not marketing automation or email marketing software. Appears to be a G2 miscategorization/cross-listing. | AB72: Complete | AD72: 2026-06-26
A73: Comarch Marketing Automation | B73: comarch.com | C73: Marketing Automation | D73: 2026-06-26 | E73: G2 | F73: https://www.g2.com/categories/marketing-automation | G73: Claude (S.LAB Research) | H73: 2026-06-26 | I73: No | J73: Marketing automation module within Comarch, a diversified IT solutions provider and systems integrator. | R73: Yes | X73: Exclude | Y73: Gate 1 fail — parent’s primary business is not B2B SaaS. Comarch operates as a diversified IT solutions provider/systems integrator across telecom, banking, ERP, and public-sector verticals, combining SaaS, PaaS, IaaS, and consulting/systems-integration services rather than operating primarily as a B2B SaaS company. | AB73: Complete | AD73: 2026-06-26
A74: Birdeye | B74: birdeye.com | C74: Marketing Automation | D74: 2026-06-26 | E74: G2 | F74: https://www.g2.com/categories/marketing-automation | G74: Claude (S.LAB Research) | H74: 2026-06-26 | I74: Yes | J74: Reputation and review management platform for multi-location brands, with bundled marketing automation features. | R74: Yes | X74: Exclude | Y74: Gate 4 fail — category fit weak. Core/foundational product is online reputation and review management; marketing automation is a secondary capability layered onto that core, not the product's primary function. | AB74: Complete | AD74: 2026-06-26
A75: Instantly | B75: instantly.ai | C75: Marketing Automation | D75: 2026-06-26 | E75: G2 | F75: https://www.g2.com/categories/email-marketing | G75: Claude (S.LAB Research) | H75: 2026-06-26 | I75: Yes | J75: Cold email outreach platform with sending infrastructure and AI-assisted campaigns. | M75: 275 | N75: LinkedIn (per G2), 2026-06-26 | R75: Yes | X75: Exclude | Y75: Already locked to the Sales Engagement/Sales Intelligence vertical per the 2026-06-26 user decision: one company, one best-fit category. Not double-counted here even though it appears on G2’s Email Marketing category page. | AB75: Complete | AC75: G2 structured "Year Founded" field shows 2001 — known recurring data error for this company; actual founding year is 2021 (confirmed independently in the Sales Engagement vertical screening). | AD75: 2026-06-26
A76: lemlist | B76: lemlist.com | C76: Marketing Automation | D76: 2026-06-26 | E76: G2 | F76: https://www.g2.com/categories/email-marketing | G76: Claude (S.LAB Research) | H76: 2026-06-26 | I76: Yes | J76: Cold email and multichannel outreach platform for sales teams. | K76: 2018 | M76: 245 | N76: LinkedIn (per G2), 2026-06-26 | R76: Yes | X76: Exclude | Y76: Already locked to the Sales Engagement/Sales Intelligence vertical per the 2026-06-26 user decision: one company, one best-fit category. Not double-counted here even though it appears on G2’s Email Marketing category page. | AB76: Complete | AC76: Founded year (2018) newly verified via this G2 page — fills a gap left blank in the already-written Sales Engagement Pass 1 Archive row for lemlist; consider backfilling that row. | AD76: 2026-06-26
A77: Moosend | B77: moosend.com | C77: Marketing Automation | D77: 2026-06-26 | E77: G2 | F77: https://www.g2.com/categories/email-marketing | G77: Claude (S.LAB Research) | H77: 2026-06-26 | I77: Yes | J77: Email marketing and automation platform, now owned by Constant Contact. | M77: 1,147 | N77: LinkedIn (per G2) — this is Constant Contact’s (the acquirer’s) company-wide figure, not Moosend-specific | P77: Acquired (recent, in-window) | Q77: Acquired by Constant Contact, June 6, 2025 (from Sitecore) — inside the Jan 2025–Jun 2026 study window. | R77: Yes | X77: Exclude | Y77: Gate 2/3 fail — recent, disruptive M&A event inside the study window. Acquired by Constant Contact, June 6, 2025. Per the manual's M&A calibration default, recent acquisitions inside the window lean toward exclude; Constant Contact (the acquirer) is retained in the pool as the surviving entity. | AB77: Complete | AD77: 2026-06-26
A78: Netcore Email API | B78: netcorecloud.com/email/email-api | C78: Marketing Automation | D78: 2026-06-26 | E78: G2 | F78: https://www.g2.com/categories/email-marketing | G78: Claude (S.LAB Research) | H78: 2026-06-26 | I78: Yes | J78: Cloud-based transactional/marketing email delivery API, a product of Netcore Cloud. | R78: Yes | X78: Exclude | Y78: Duplicate listing — same parent company/product family as Netcore Customer Engagement Platform (Netcore Cloud), which is retained as the consolidated candidate. Email API is one channel/component within Netcore’s broader engagement platform, not a separately screened company. | AB78: Complete | AD78: 2026-06-26
A79: Gainsight | B79: gainsight.com | C79: Customer Success | D79: 2026-06-26 | I79: Yes | J79: Customer success and product experience platform for B2B SaaS companies managing renewals, expansion, and onboarding at scale. | R79: Yes | X79: Include | Z79: Yes | AB79: Locked (Pass 2) | AC79: BACKFILL — Customer Success vertical (13, locked in Pass 2/Company Tracker). Original Pass 1 gate-screening data (founded year, employee count, funding status, M&A detail, ICP/buying motion) predates the current Pass 1 Archive schema and was not preserved in this workbook. Operating manual V1.2 addendum confirms 13 as the finalized count. Founded year, employee count, funding, and M&A status left blank — verify before Deep Dive selection. | AD79: 2026-06-26
A80: Planhat | B80: planhat.com | C80: Customer Success | D80: 2026-06-26 | I80: Yes | J80: Customer success platform combining health scoring, customer data hub, and revenue analytics for B2B SaaS teams. | R80: Yes | X80: Include | AB80: Locked (Pass 2) | AC80: BACKFILL — Customer Success vertical (13, locked in Pass 2/Company Tracker). Original Pass 1 gate-screening data (founded year, employee count, funding status, M&A detail, ICP/buying motion) predates the current Pass 1 Archive schema and was not preserved in this workbook. Operating manual V1.2 addendum confirms 13 as the finalized count. Founded year, employee count, funding, and M&A status left blank — verify before Deep Dive selection. | AD80: 2026-06-26
A81: ClientSuccess | B81: clientsuccess.com | C81: Customer Success | D81: 2026-06-26 | I81: Yes | J81: Customer success management software focused on health scoring, onboarding, and renewal/expansion tracking for SaaS companies. | R81: Yes | X81: Include | AB81: Locked (Pass 2) | AC81: BACKFILL — Customer Success vertical (13, locked in Pass 2/Company Tracker). Original Pass 1 gate-screening data (founded year, employee count, funding status, M&A detail, ICP/buying motion) predates the current Pass 1 Archive schema and was not preserved in this workbook. Operating manual V1.2 addendum confirms 13 as the finalized count. Founded year, employee count, funding, and M&A status left blank — verify before Deep Dive selection. | AD81: 2026-06-26
A82: Vitally | B82: vitally.io | C82: Customer Success | D82: 2026-06-26 | I82: Yes | J82: Customer success platform built on a customer data hub, combining health scoring, workflows, and analytics for B2B SaaS teams. | R82: Yes | X82: Include | AB82: Locked (Pass 2) | AC82: BACKFILL — Customer Success vertical (13, locked in Pass 2/Company Tracker). Original Pass 1 gate-screening data (founded year, employee count, funding status, M&A detail, ICP/buying motion) predates the current Pass 1 Archive schema and was not preserved in this workbook. Operating manual V1.2 addendum confirms 13 as the finalized count. Founded year, employee count, funding, and M&A status left blank — verify before Deep Dive selection. | AD82: 2026-06-26
A83: Custify | B83: custify.com | C83: Customer Success | D83: 2026-06-26 | I83: Yes | J83: Customer success platform for SaaS companies, providing health scores, automated playbooks, and churn-risk alerts. | R83: Yes | X83: Include | AB83: Locked (Pass 2) | AC83: BACKFILL — Customer Success vertical (13, locked in Pass 2/Company Tracker). Original Pass 1 gate-screening data (founded year, employee count, funding status, M&A detail, ICP/buying motion) predates the current Pass 1 Archive schema and was not preserved in this workbook. Operating manual V1.2 addendum confirms 13 as the finalized count. Founded year, employee count, funding, and M&A status left blank — verify before Deep Dive selection. | AD83: 2026-06-26
A84: Akita | B84: akitaapp.com | C84: Customer Success | D84: 2026-06-26 | I84: Yes | J84: Customer success management platform offering health scoring and customer data integration for SaaS businesses; Dublin-headquartered. | R84: Yes | X84: Include | AB84: Locked (Pass 2) | AC84: BACKFILL — Customer Success vertical (13, locked in Pass 2/Company Tracker). Original Pass 1 gate-screening data (founded year, employee count, funding status, M&A detail, ICP/buying motion) predates the current Pass 1 Archive schema and was not preserved in this workbook. Operating manual V1.2 addendum confirms 13 as the finalized count. Founded year, employee count, funding, and M&A status left blank — verify before Deep Dive selection. | AD84: 2026-06-26
A85: Kapta | B85: kapta.com | C85: Customer Success | D85: 2026-06-26 | I85: Yes | J85: Key account management and customer success software for B2B teams focused on retention and expansion of existing accounts. | R85: Yes | X85: Include | AB85: Locked (Pass 2) | AC85: BACKFILL — Customer Success vertical (13, locked in Pass 2/Company Tracker). Original Pass 1 gate-screening data (founded year, employee count, funding status, M&A detail, ICP/buying motion) predates the current Pass 1 Archive schema and was not preserved in this workbook. Operating manual V1.2 addendum confirms 13 as the finalized count. Founded year, employee count, funding, and M&A status left blank — verify before Deep Dive selection. | AD85: 2026-06-26
A86: ChurnZero | B86: churnzero.com | C86: Customer Success | D86: 2026-06-26 | I86: Yes | J86: Customer success and growth platform providing health scoring, automated engagement, and renewal/upsell workflows for subscription businesses. | R86: Yes | X86: Include | AB86: Locked (Pass 2) | AC86: BACKFILL — Customer Success vertical (13, locked in Pass 2/Company Tracker). Original Pass 1 gate-screening data (founded year, employee count, funding status, M&A detail, ICP/buying motion) predates the current Pass 1 Archive schema and was not preserved in this workbook. Operating manual V1.2 addendum confirms 13 as the finalized count. Founded year, employee count, funding, and M&A status left blank — verify before Deep Dive selection. | AD86: 2026-06-26
A87: UserGuiding | B87: userguiding.com | C87: Customer Success | D87: 2026-06-26 | I87: Yes | J87: No-code product adoption and user onboarding platform used by customer success and product teams to drive activation. | R87: Yes | X87: Include | AB87: Locked (Pass 2) | AC87: BACKFILL — Customer Success vertical (13, locked in Pass 2/Company Tracker). Original Pass 1 gate-screening data (founded year, employee count, funding status, M&A detail, ICP/buying motion) predates the current Pass 1 Archive schema and was not preserved in this workbook. Operating manual V1.2 addendum confirms 13 as the finalized count. Founded year, employee count, funding, and M&A status left blank — verify before Deep Dive selection. | AD87: 2026-06-26
A88: Velaris | B88: velaris.io | C88: Customer Success | D88: 2026-06-26 | I88: Yes | J88: AI-native customer success platform for mid-market and enterprise B2B SaaS teams, covering health scoring, onboarding, renewals, and expansion. | R88: Yes | X88: Include | AB88: Locked (Pass 2) | AC88: BACKFILL — Customer Success vertical (13, locked in Pass 2/Company Tracker). Original Pass 1 gate-screening data (founded year, employee count, funding status, M&A detail, ICP/buying motion) predates the current Pass 1 Archive schema and was not preserved in this workbook. Operating manual V1.2 addendum confirms 13 as the finalized count. Founded year, employee count, funding, and M&A status left blank — verify before Deep Dive selection. | AD88: 2026-06-26
A89: Rocketlane | B89: rocketlane.com | C89: Customer Success | D89: 2026-06-26 | I89: Yes | J89: Customer onboarding and professional services automation platform used by customer success and implementation teams. | R89: Yes | X89: Include | AB89: Locked (Pass 2) | AC89: BACKFILL — Customer Success vertical (13, locked in Pass 2/Company Tracker). Original Pass 1 gate-screening data (founded year, employee count, funding status, M&A detail, ICP/buying motion) predates the current Pass 1 Archive schema and was not preserved in this workbook. Operating manual V1.2 addendum confirms 13 as the finalized count. Founded year, employee count, funding, and M&A status left blank — verify before Deep Dive selection. | AD89: 2026-06-26
A90: Higher Logic | B90: higherlogic.com | C90: Customer Success | D90: 2026-06-26 | I90: Yes | J90: Online community and customer engagement software (including Higher Logic Vanilla) used by customer success teams for self-service and retention. | R90: Yes | X90: Include | AB90: Locked (Pass 2) | AC90: BACKFILL — Customer Success vertical (13, locked in Pass 2/Company Tracker). Original Pass 1 gate-screening data (founded year, employee count, funding status, M&A detail, ICP/buying motion) predates the current Pass 1 Archive schema and was not preserved in this workbook. Operating manual V1.2 addendum confirms 13 as the finalized count. Founded year, employee count, funding, and M&A status left blank — verify before Deep Dive selection. | AD90: 2026-06-26
A91: EverAfter | B91: everafter.ai | C91: Customer Success | D91: 2026-06-26 | I91: Yes | J91: AI-powered digital customer success platform providing a shared customer-facing workspace for onboarding, adoption, and renewal preparation. | R91: Yes | X91: Include | AB91: Locked (Pass 2) | AC91: BACKFILL — Customer Success vertical (13, locked in Pass 2/Company Tracker). Original Pass 1 gate-screening data (founded year, employee count, funding status, M&A detail, ICP/buying motion) predates the current Pass 1 Archive schema and was not preserved in this workbook. Operating manual V1.2 addendum confirms 13 as the finalized count. Founded year, employee count, funding, and M&A status left blank — verify before Deep Dive selection. | AD91: 2026-06-26
A92: Rippling | B92: rippling.com | C92: HR / People Operations | D92: 2026-06-26 | E92: G2 | F92: https://www.g2.com/categories/core-hr | G92: Claude (S.LAB Research) | H92: 2026-06-26 | I92: Yes | J92: Unified HR, IT, and finance platform (payroll, benefits, device management, spend) for businesses managing global workforces. | K92: 2016 | L92: Private | M92: 7569 | N92: LeadIQ/Tracxn aggregate, May 2026 (third-party estimate, not directly verified) | O92: Private; VC-backed, recent rounds valued company above $16B (exact current total raised not independently verified this session) | P92: Independent | Q92: No M&A this study window. | R92: Yes | X92: Include | Z92: Yes | AB92: In Progress | AC92: Customer Success-style verification depth applied (LinkedIn/Crunchbase/Tracxn aggregates via web search, June 2026). HR/People Operations vertical (15, locked). Employee counts vary across third-party aggregators for several candidates (flagged per-row) — treat as directional, not precise, until independently re-verified via LinkedIn directly. | AD92: 2026-06-26
A93: BambooHR | B93: bamboohr.com | C93: HR / People Operations | D93: 2026-06-26 | E93: G2 | F93: https://www.g2.com/categories/core-hr | G93: Claude (S.LAB Research) | H93: 2026-06-26 | I93: Yes | J93: HR software for small and midsize businesses covering hiring, onboarding, employee records, and culture/performance tools. | K93: 2008 | L93: Private | M93: 1899 | N93: Tracxn/Crunchbase aggregate, May 2026 | O93: Private; sources vary (bootstrapped historically, also reported $125M round in 2024 at $2.5B valuation) — total raised not independently verified this session | P93: Independent | Q93: No M&A this study window. | R93: Yes | X93: Include | AB93: In Progress | AC93: Customer Success-style verification depth applied (LinkedIn/Crunchbase/Tracxn aggregates via web search, June 2026). HR/People Operations vertical (15, locked). Employee counts vary across third-party aggregators for several candidates (flagged per-row) — treat as directional, not precise, until independently re-verified via LinkedIn directly. | AD93: 2026-06-26
A94: Gusto | B94: gusto.com | C94: HR / People Operations | D94: 2026-06-26 | E94: G2 | F94: https://www.g2.com/categories/core-hr | G94: Claude (S.LAB Research) | H94: 2026-06-26 | I94: Yes | J94: Payroll, benefits, and HR platform built for small and midsize businesses. | K94: 2012 | L94: Private | M94: 4000 | N94: Tracxn/Growjo aggregate, 2026 | O94: Private; ~$746M total raised; completed $200M+ tender offer June 2025 at $9.3B valuation | P94: Independent | Q94: No M&A this study window. | R94: Yes | X94: Include | AB94: In Progress | AC94: Customer Success-style verification depth applied (LinkedIn/Crunchbase/Tracxn aggregates via web search, June 2026). HR/People Operations vertical (15, locked). Employee counts vary across third-party aggregators for several candidates (flagged per-row) — treat as directional, not precise, until independently re-verified via LinkedIn directly. | AD94: 2026-06-26
A95: HiBob | B95: hibob.com | C95: HR / People Operations | D95: 2026-06-26 | E95: G2 | F95: https://www.g2.com/categories/core-hr | G95: Claude (S.LAB Research) | H95: 2026-06-26 | I95: Yes | J95: HRIS platform ("Bob") for mid-market companies, covering people data, performance, compensation, and engagement. | K95: 2015 | L95: Private | M95: 2000 | N95: Tracxn/Growjo aggregate, 2026 | O95: Private; ~$574M total raised; $2.5B valuation (2023, $150M Series D) | P95: Independent | Q95: No M&A this study window. | R95: Yes | X95: Include | AB95: In Progress | AC95: Customer Success-style verification depth applied (LinkedIn/Crunchbase/Tracxn aggregates via web search, June 2026). HR/People Operations vertical (15, locked). Employee counts vary across third-party aggregators for several candidates (flagged per-row) — treat as directional, not precise, until independently re-verified via LinkedIn directly. | AD95: 2026-06-26
A96: Paylocity | B96: paylocity.com | C96: HR / People Operations | D96: 2026-06-26 | E96: G2 | F96: https://www.g2.com/categories/core-hr | G96: Claude (S.LAB Research) | H96: 2026-06-26 | I96: Yes | J96: Cloud HR and payroll software platform for midsize organizations, including talent, workforce management, and benefits. | K96: 1997 | L96: Public (NASDAQ: PCTY) | M96: 6700 | N96: Company-reported aggregate, 2026 | O96: Public company; IPO 2014 | P96: Independent | Q96: No M&A this study window. | R96: Yes | X96: Include | AA96: Yes | AB96: In Progress | AC96: Customer Success-style verification depth applied (LinkedIn/Crunchbase/Tracxn aggregates via web search, June 2026). HR/People Operations vertical (15, locked). Employee counts vary across third-party aggregators for several candidates (flagged per-row) — treat as directional, not precise, until independently re-verified via LinkedIn directly. | AD96: 2026-06-26
A97: Deel | B97: deel.com | C97: HR / People Operations | D97: 2026-06-26 | E97: G2 | F97: https://www.g2.com/categories/core-hr | G97: Claude (S.LAB Research) | H97: 2026-06-26 | I97: Yes | J97: Global payroll, HR, and Employer-of-Record (EOR) platform for hiring and paying international teams. | K97: 2019 | L97: Private | M97: 9619 | N97: Tracxn aggregate, May 2026 | O97: Private; ~$982M total raised; $17.3B valuation (Oct 2025, $300M Series E) | P97: Independent | Q97: No M&A this study window; active acquirer of smaller tools (does not affect own domain stability). | R97: Yes | X97: Include | AB97: In Progress | AC97: Customer Success-style verification depth applied (LinkedIn/Crunchbase/Tracxn aggregates via web search, June 2026). HR/People Operations vertical (15, locked). Employee counts vary across third-party aggregators for several candidates (flagged per-row) — treat as directional, not precise, until independently re-verified via LinkedIn directly. | AD97: 2026-06-26
A98: Keka | B98: keka.com | C98: HR / People Operations | D98: 2026-06-26 | E98: G2 | F98: https://www.g2.com/categories/core-hr | G98: Claude (S.LAB Research) | H98: 2026-06-26 | I98: Yes | J98: HR, payroll, and performance management software for mid-market companies, primarily in India. | K98: 2014 | L98: Private | M98: 1000 | N98: Sources vary 886-1,241 across LinkedIn/Tracxn/EasyLeadz, 2025-2026 — not independently verified to a single figure | O98: Private; reported ~$59.2M raised (incl. WestBridge Capital); also reported as largely bootstrapped/revenue-funded ($85.9M ARR per Latka) | P98: Independent | Q98: No M&A this study window. | R98: Yes | X98: Include | AB98: In Progress | AC98: Customer Success-style verification depth applied (LinkedIn/Crunchbase/Tracxn aggregates via web search, June 2026). HR/People Operations vertical (15, locked). Employee counts vary across third-party aggregators for several candidates (flagged per-row) — treat as directional, not precise, until independently re-verified via LinkedIn directly. | AD98: 2026-06-26
A99: TriNet | B99: trinet.com | C99: HR / People Operations | D99: 2026-06-26 | E99: G2 | F99: https://www.g2.com/categories/core-hr | G99: Claude (S.LAB Research) | H99: 2026-06-26 | I99: Yes | J99: Professional Employer Organization (PEO) providing HR, payroll, benefits, and risk management for small and midsize businesses. | K99: 1988 | L99: Public (NYSE: TNET) | N99: Not verified this session — public filings would have exact headcount | O99: Public company; IPO 2014 | P99: Independent | Q99: No M&A this study window. | R99: Yes | X99: Include | AB99: In Progress | AC99: Customer Success-style verification depth applied (LinkedIn/Crunchbase/Tracxn aggregates via web search, June 2026). HR/People Operations vertical (15, locked). Employee counts vary across third-party aggregators for several candidates (flagged per-row) — treat as directional, not precise, until independently re-verified via LinkedIn directly. | AD99: 2026-06-26
A100: Remote | B100: remote.com | C100: HR / People Operations | D100: 2026-06-26 | E100: G2 | F100: https://www.g2.com/categories/core-hr | G100: Claude (S.LAB Research) | H100: 2026-06-26 | I100: Yes | J100: Global HR platform offering Employer-of-Record, global payroll, and contractor management for distributed teams. | K100: 2019 | L100: Private | M100: 11900 | N100: Tracxn aggregate, 2026 (other sources report up to 14,569 — range not reconciled) | O100: Private; ~$506M total raised; $3B valuation (Series C, April 2022) | P100: Independent | Q100: No M&A this study window; active acquirer of smaller tools (Atlas, Jan 2026; Bravas, Apr 2026) — does not affect own domain stability but may add inorganic traffic; note for Pass 2 interpretation. | R100: Yes | X100: Include | AB100: In Progress | AC100: Customer Success-style verification depth applied (LinkedIn/Crunchbase/Tracxn aggregates via web search, June 2026). HR/People Operations vertical (15, locked). Employee counts vary across third-party aggregators for several candidates (flagged per-row) — treat as directional, not precise, until independently re-verified via LinkedIn directly. | AD100: 2026-06-26
...

Sheet Deep Dive Database
A1: Company Name | B1: Category | C1: Employees | D1: Traffic Start | E1: Traffic End | F1: % Change | G1: Ref. Domains Start | H1: Ref. Domains End | I1: Reviewed Date | J1: Time Spent (min) | K1: Reviewer | L1: URL 1 | M1: Content Type 1 | N1: Traffic Change 1 | O1: URL 2 | P1: Content Type 2 | Q1: Traffic Change 2 | R1: URL 3 | S1: Content Type 3 | T1: Traffic Change 3 | U1: URL 4 | V1: Content Type 4 | W1: Traffic Change 4 | X1: URL 5 | Y1: Content Type 5 | Z1: Traffic Change 5 | AA1: Growth Concentration | AB1: Content Origin | AC1: Growth Timing | AD1: Referring Domain Notes | AE1: Internal Linking Observations | AF1: AI Visibility Spot-Check Notes | AG1: Anything Surprising | AH1: Anything Contradicting Hypotheses | AI1: Quotable Pattern Candidates | AJ1: Primary Growth Driver (confirmed) | AK1: Review Status | AL1: Notes/Follow-ups | AM1: Review Complete | AN1: Long-Term Traffic Story | AO1: Major Inflection Points | AP1: Acquisitions / Mergers | AQ1: Rebrands | AR1: Domain Migrations | AS1: Product Launches / Notable Events
B2: =IFERROR(VLOOKUP(A2,'Pass 2'!$A:$S,MATCH("Category",'Pass 2'!$1:$1,0),FALSE()),"") | C2: =IFERROR(VLOOKUP(A2,'Pass 1 Archive'!$A:$AD,MATCH("LinkedIn Employee Count",'Pass 1 Archive'!$1:$1,0),FALSE()),"") | D2: =IFERROR(VLOOKUP(A2,'Pass 2'!$A:$S,MATCH("Jan 2025 Traffic",'Pass 2'!$1:$1,0),FALSE()),"") | E2: =IFERROR(VLOOKUP(A2,'Pass 2'!$A:$S,MATCH("Jun 2026 Traffic",'Pass 2'!$1:$1,0),FALSE()),"") | F2: =IFERROR(VLOOKUP(A2,'Pass 2'!$A:$S,MATCH("Traffic % Change",'Pass 2'!$1:$1,0),FALSE()),"") | G2: =IFERROR(VLOOKUP(A2,'Pass 2'!$A:$S,MATCH("Jan 2025 Referring Domains",'Pass 2'!$1:$1,0),FALSE()),"") | H2: =IFERROR(VLOOKUP(A2,'Pass 2'!$A:$S,MATCH("Jun 2026 Referring Domains",'Pass 2'!$1:$1,0),FALSE()),"")
B3: =IFERROR(VLOOKUP(A3,'Pass 2'!$A:$S,MATCH("Category",'Pass 2'!$1:$1,0),FALSE()),"") | C3: =IFERROR(VLOOKUP(A3,'Pass 1 Archive'!$A:$AD,MATCH("LinkedIn Employee Count",'Pass 1 Archive'!$1:$1,0),FALSE()),"") | D3: =IFERROR(VLOOKUP(A3,'Pass 2'!$A:$S,MATCH("Jan 2025 Traffic",'Pass 2'!$1:$1,0),FALSE()),"") | E3: =IFERROR(VLOOKUP(A3,'Pass 2'!$A:$S,MATCH("Jun 2026 Traffic",'Pass 2'!$1:$1,0),FALSE()),"") | F3: =IFERROR(VLOOKUP(A3,'Pass 2'!$A:$S,MATCH("Traffic % Change",'Pass 2'!$1:$1,0),FALSE()),"") | G3: =IFERROR(VLOOKUP(A3,'Pass 2'!$A:$S,MATCH("Jan 2025 Referring Domains",'Pass 2'!$1:$1,0),FALSE()),"") | H3: =IFERROR(VLOOKUP(A3,'Pass 2'!$A:$S,MATCH("Jun 2026 Referring Domains",'Pass 2'!$1:$1,0),FALSE()),"")
B4: =IFERROR(VLOOKUP(A4,'Pass 2'!$A:$S,MATCH("Category",'Pass 2'!$1:$1,0),FALSE()),"") | C4: =IFERROR(VLOOKUP(A4,'Pass 1 Archive'!$A:$AD,MATCH("LinkedIn Employee Count",'Pass 1 Archive'!$1:$1,0),FALSE()),"") | D4: =IFERROR(VLOOKUP(A4,'Pass 2'!$A:$S,MATCH("Jan 2025 Traffic",'Pass 2'!$1:$1,0),FALSE()),"") | E4: =IFERROR(VLOOKUP(A4,'Pass 2'!$A:$S,MATCH("Jun 2026 Traffic",'Pass 2'!$1:$1,0),FALSE()),"") | F4: =IFERROR(VLOOKUP(A4,'Pass 2'!$A:$S,MATCH("Traffic % Change",'Pass 2'!$1:$1,0),FALSE()),"") | G4: =IFERROR(VLOOKUP(A4,'Pass 2'!$A:$S,MATCH("Jan 2025 Referring Domains",'Pass 2'!$1:$1,0),FALSE()),"") | H4: =IFERROR(VLOOKUP(A4,'Pass 2'!$A:$S,MATCH("Jun 2026 Referring Domains",'Pass 2'!$1:$1,0),FALSE()),"")
B5: =IFERROR(VLOOKUP(A5,'Pass 2'!$A:$S,MATCH("Category",'Pass 2'!$1:$1,0),FALSE()),"") | C5: =IFERROR(VLOOKUP(A5,'Pass 1 Archive'!$A:$AD,MATCH("LinkedIn Employee Count",'Pass 1 Archive'!$1:$1,0),FALSE()),"") | D5: =IFERROR(VLOOKUP(A5,'Pass 2'!$A:$S,MATCH("Jan 2025 Traffic",'Pass 2'!$1:$1,0),FALSE()),"") | E5: =IFERROR(VLOOKUP(A5,'Pass 2'!$A:$S,MATCH("Jun 2026 Traffic",'Pass 2'!$1:$1,0),FALSE()),"") | F5: =IFERROR(VLOOKUP(A5,'Pass 2'!$A:$S,MATCH("Traffic % Change",'Pass 2'!$1:$1,0),FALSE()),"") | G5: =IFERROR(VLOOKUP(A5,'Pass 2'!$A:$S,MATCH("Jan 2025 Referring Domains",'Pass 2'!$1:$1,0),FALSE()),"") | H5: =IFERROR(VLOOKUP(A5,'Pass 2'!$A:$S,MATCH("Jun 2026 Referring Domains",'Pass 2'!$1:$1,0),FALSE()),"")
B6: =IFERROR(VLOOKUP(A6,'Pass 2'!$A:$S,MATCH("Category",'Pass 2'!$1:$1,0),FALSE()),"") | C6: =IFERROR(VLOOKUP(A6,'Pass 1 Archive'!$A:$AD,MATCH("LinkedIn Employee Count",'Pass 1 Archive'!$1:$1,0),FALSE()),"") | D6: =IFERROR(VLOOKUP(A6,'Pass 2'!$A:$S,MATCH("Jan 2025 Traffic",'Pass 2'!$1:$1,0),FALSE()),"") | E6: =IFERROR(VLOOKUP(A6,'Pass 2'!$A:$S,MATCH("Jun 2026 Traffic",'Pass 2'!$1:$1,0),FALSE()),"") | F6: =IFERROR(VLOOKUP(A6,'Pass 2'!$A:$S,MATCH("Traffic % Change",'Pass 2'!$1:$1,0),FALSE()),"") | G6: =IFERROR(VLOOKUP(A6,'Pass 2'!$A:$S,MATCH("Jan 2025 Referring Domains",'Pass 2'!$1:$1,0),FALSE()),"") | H6: =IFERROR(VLOOKUP(A6,'Pass 2'!$A:$S,MATCH("Jun 2026 Referring Domains",'Pass 2'!$1:$1,0),FALSE()),"")
B7: =IFERROR(VLOOKUP(A7,'Pass 2'!$A:$S,MATCH("Category",'Pass 2'!$1:$1,0),FALSE()),"") | C7: =IFERROR(VLOOKUP(A7,'Pass 1 Archive'!$A:$AD,MATCH("LinkedIn Employee Count",'Pass 1 Archive'!$1:$1,0),FALSE()),"") | D7: =IFERROR(VLOOKUP(A7,'Pass 2'!$A:$S,MATCH("Jan 2025 Traffic",'Pass 2'!$1:$1,0),FALSE()),"") | E7: =IFERROR(VLOOKUP(A7,'Pass 2'!$A:$S,MATCH("Jun 2026 Traffic",'Pass 2'!$1:$1,0),FALSE()),"") | F7: =IFERROR(VLOOKUP(A7,'Pass 2'!$A:$S,MATCH("Traffic % Change",'Pass 2'!$1:$1,0),FALSE()),"") | G7: =IFERROR(VLOOKUP(A7,'Pass 2'!$A:$S,MATCH("Jan 2025 Referring Domains",'Pass 2'!$1:$1,0),FALSE()),"") | H7: =IFERROR(VLOOKUP(A7,'Pass 2'!$A:$S,MATCH("Jun 2026 Referring Domains",'Pass 2'!$1:$1,0),FALSE()),"")
B8: =IFERROR(VLOOKUP(A8,'Pass 2'!$A:$S,MATCH("Category",'Pass 2'!$1:$1,0),FALSE()),"") | C8: =IFERROR(VLOOKUP(A8,'Pass 1 Archive'!$A:$AD,MATCH("LinkedIn Employee Count",'Pass 1 Archive'!$1:$1,0),FALSE()),"") | D8: =IFERROR(VLOOKUP(A8,'Pass 2'!$A:$S,MATCH("Jan 2025 Traffic",'Pass 2'!$1:$1,0),FALSE()),"") | E8: =IFERROR(VLOOKUP(A8,'Pass 2'!$A:$S,MATCH("Jun 2026 Traffic",'Pass 2'!$1:$1,0),FALSE()),"") | F8: =IFERROR(VLOOKUP(A8,'Pass 2'!$A:$S,MATCH("Traffic % Change",'Pass 2'!$1:$1,0),FALSE()),"") | G8: =IFERROR(VLOOKUP(A8,'Pass 2'!$A:$S,MATCH("Jan 2025 Referring Domains",'Pass 2'!$1:$1,0),FALSE()),"") | H8: =IFERROR(VLOOKUP(A8,'Pass 2'!$A:$S,MATCH("Jun 2026 Referring Domains",'Pass 2'!$1:$1,0),FALSE()),"")
B9: =IFERROR(VLOOKUP(A9,'Pass 2'!$A:$S,MATCH("Category",'Pass 2'!$1:$1,0),FALSE()),"") | C9: =IFERROR(VLOOKUP(A9,'Pass 1 Archive'!$A:$AD,MATCH("LinkedIn Employee Count",'Pass 1 Archive'!$1:$1,0),FALSE()),"") | D9: =IFERROR(VLOOKUP(A9,'Pass 2'!$A:$S,MATCH("Jan 2025 Traffic",'Pass 2'!$1:$1,0),FALSE()),"") | E9: =IFERROR(VLOOKUP(A9,'Pass 2'!$A:$S,MATCH("Jun 2026 Traffic",'Pass 2'!$1:$1,0),FALSE()),"") | F9: =IFERROR(VLOOKUP(A9,'Pass 2'!$A:$S,MATCH("Traffic % Change",'Pass 2'!$1:$1,0),FALSE()),"") | G9: =IFERROR(VLOOKUP(A9,'Pass 2'!$A:$S,MATCH("Jan 2025 Referring Domains",'Pass 2'!$1:$1,0),FALSE()),"") | H9: =IFERROR(VLOOKUP(A9,'Pass 2'!$A:$S,MATCH("Jun 2026 Referring Domains",'Pass 2'!$1:$1,0),FALSE()),"")
B10: =IFERROR(VLOOKUP(A10,'Pass 2'!$A:$S,MATCH("Category",'Pass 2'!$1:$1,0),FALSE()),"") | C10: =IFERROR(VLOOKUP(A10,'Pass 1 Archive'!$A:$AD,MATCH("LinkedIn Employee Count",'Pass 1 Archive'!$1:$1,0),FALSE()),"") | D10: =IFERROR(VLOOKUP(A10,'Pass 2'!$A:$S,MATCH("Jan 2025 Traffic",'Pass 2'!$1:$1,0),FALSE()),"") | E10: =IFERROR(VLOOKUP(A10,'Pass 2'!$A:$S,MATCH("Jun 2026 Traffic",'Pass 2'!$1:$1,0),FALSE()),"") | F10: =IFERROR(VLOOKUP(A10,'Pass 2'!$A:$S,MATCH("Traffic % Change",'Pass 2'!$1:$1,0),FALSE()),"") | G10: =IFERROR(VLOOKUP(A10,'Pass 2'!$A:$S,MATCH("Jan 2025 Referring Domains",'Pass 2'!$1:$1,0),FALSE()),"") | H10: =IFERROR(VLOOKUP(A10,'Pass 2'!$A:$S,MATCH("Jun 2026 Referring Domains",'Pass 2'!$1:$1,0),FALSE()),"")
B11: =IFERROR(VLOOKUP(A11,'Pass 2'!$A:$S,MATCH("Category",'Pass 2'!$1:$1,0),FALSE()),"") | C11: =IFERROR(VLOOKUP(A11,'Pass 1 Archive'!$A:$AD,MATCH("LinkedIn Employee Count",'Pass 1 Archive'!$1:$1,0),FALSE()),"") | D11: =IFERROR(VLOOKUP(A11,'Pass 2'!$A:$S,MATCH("Jan 2025 Traffic",'Pass 2'!$1:$1,0),FALSE()),"") | E11: =IFERROR(VLOOKUP(A11,'Pass 2'!$A:$S,MATCH("Jun 2026 Traffic",'Pass 2'!$1:$1,0),FALSE()),"") | F11: =IFERROR(VLOOKUP(A11,'Pass 2'!$A:$S,MATCH("Traffic % Change",'Pass 2'!$1:$1,0),FALSE()),"") | G11: =IFERROR(VLOOKUP(A11,'Pass 2'!$A:$S,MATCH("Jan 2025 Referring Domains",'Pass 2'!$1:$1,0),FALSE()),"") | H11: =IFERROR(VLOOKUP(A11,'Pass 2'!$A:$S,MATCH("Jun 2026 Referring Domains",'Pass 2'!$1:$1,0),FALSE()),"")
B12: =IFERROR(VLOOKUP(A12,'Pass 2'!$A:$S,MATCH("Category",'Pass 2'!$1:$1,0),FALSE()),"") | C12: =IFERROR(VLOOKUP(A12,'Pass 1 Archive'!$A:$AD,MATCH("LinkedIn Employee Count",'Pass 1 Archive'!$1:$1,0),FALSE()),"") | D12: =IFERROR(VLOOKUP(A12,'Pass 2'!$A:$S,MATCH("Jan 2025 Traffic",'Pass 2'!$1:$1,0),FALSE()),"") | E12: =IFERROR(VLOOKUP(A12,'Pass 2'!$A:$S,MATCH("Jun 2026 Traffic",'Pass 2'!$1:$1,0),FALSE()),"") | F12: =IFERROR(VLOOKUP(A12,'Pass 2'!$A:$S,MATCH("Traffic % Change",'Pass 2'!$1:$1,0),FALSE()),"") | G12: =IFERROR(VLOOKUP(A12,'Pass 2'!$A:$S,MATCH("Jan 2025 Referring Domains",'Pass 2'!$1:$1,0),FALSE()),"") | H12: =IFERROR(VLOOKUP(A12,'Pass 2'!$A:$S,MATCH("Jun 2026 Referring Domains",'Pass 2'!$1:$1,0),FALSE()),"")
B13: =IFERROR(VLOOKUP(A13,'Pass 2'!$A:$S,MATCH("Category",'Pass 2'!$1:$1,0),FALSE()),"") | C13: =IFERROR(VLOOKUP(A13,'Pass 1 Archive'!$A:$AD,MATCH("LinkedIn Employee Count",'Pass 1 Archive'!$1:$1,0),FALSE()),"") | D13: =IFERROR(VLOOKUP(A13,'Pass 2'!$A:$S,MATCH("Jan 2025 Traffic",'Pass 2'!$1:$1,0),FALSE()),"") | E13: =IFERROR(VLOOKUP(A13,'Pass 2'!$A:$S,MATCH("Jun 2026 Traffic",'Pass 2'!$1:$1,0),FALSE()),"") | F13: =IFERROR(VLOOKUP(A13,'Pass 2'!$A:$S,MATCH("Traffic % Change",'Pass 2'!$1:$1,0),FALSE()),"") | G13: =IFERROR(VLOOKUP(A13,'Pass 2'!$A:$S,MATCH("Jan 2025 Referring Domains",'Pass 2'!$1:$1,0),FALSE()),"") | H13: =IFERROR(VLOOKUP(A13,'Pass 2'!$A:$S,MATCH("Jun 2026 Referring Domains",'Pass 2'!$1:$1,0),FALSE()),"")
... B500: =IFERROR(VLOOKUP(A500,'Pass 2'!$A:$S,MATCH("Category",'Pass 2'!$1:$1,0),FALSE()),"") | C500: =IFERROR(VLOOKUP(A500,'Pass 1 Archive'!$A:$AD,MATCH("LinkedIn Employee Count",'Pass 1 Archive'!$1:$1,0),FALSE()),"") | D500: =IFERROR(VLOOKUP(A500,'Pass 2'!$A:$S,MATCH("Jan 2025 Traffic",'Pass 2'!$1:$1,0),FALSE()),"") | E500: =IFERROR(VLOOKUP(A500,'Pass 2'!$A:$S,MATCH("Jun 2026 Traffic",'Pass 2'!$1:$1,0),FALSE()),"") | F500: =IFERROR(VLOOKUP(A500,'Pass 2'!$A:$S,MATCH("Traffic % Change",'Pass 2'!$1:$1,0),FALSE()),"") | G500: =IFERROR(VLOOKUP(A500,'Pass 2'!$A:$S,MATCH("Jan 2025 Referring Domains",'Pass 2'!$1:$1,0),FALSE()),"") | H500: =IFERROR(VLOOKUP(A500,'Pass 2'!$A:$S,MATCH("Jun 2026 Referring Domains",'Pass 2'!$1:$1,0),FALSE()),"")

Sheet Comparison Group Database
A1: Company Name | B1: Category | C1: Employees | D1: Traffic Start | E1: Traffic End | F1: % Change | G1: Ref. Domains Start | H1: Ref. Domains End | I1: Reviewed Date | J1: Time Spent (min) | K1: Publishing Activity | L1: Growth-Associated Content Types Present? | M1: Content Types Notes | N1: Likely Decline Explanation | O1: One-Line Takeaway | P1: Confidence | Q1: Review Status | R1: Review Complete
B2: =IFERROR(VLOOKUP(A2,'Pass 2'!$A:$S,MATCH("Category",'Pass 2'!$1:$1,0),FALSE()),"") | C2: =IFERROR(VLOOKUP(A2,'Pass 1 Archive'!$A:$AD,MATCH("LinkedIn Employee Count",'Pass 1 Archive'!$1:$1,0),FALSE()),"") | D2: =IFERROR(VLOOKUP(A2,'Pass 2'!$A:$S,MATCH("Jan 2025 Traffic",'Pass 2'!$1:$1,0),FALSE()),"") | E2: =IFERROR(VLOOKUP(A2,'Pass 2'!$A:$S,MATCH("Jun 2026 Traffic",'Pass 2'!$1:$1,0),FALSE()),"") | F2: =IFERROR(VLOOKUP(A2,'Pass 2'!$A:$S,MATCH("Traffic % Change",'Pass 2'!$1:$1,0),FALSE()),"") | G2: =IFERROR(VLOOKUP(A2,'Pass 2'!$A:$S,MATCH("Jan 2025 Referring Domains",'Pass 2'!$1:$1,0),FALSE()),"") | H2: =IFERROR(VLOOKUP(A2,'Pass 2'!$A:$S,MATCH("Jun 2026 Referring Domains",'Pass 2'!$1:$1,0),FALSE()),"")
B3: =IFERROR(VLOOKUP(A3,'Pass 2'!$A:$S,MATCH("Category",'Pass 2'!$1:$1,0),FALSE()),"") | C3: =IFERROR(VLOOKUP(A3,'Pass 1 Archive'!$A:$AD,MATCH("LinkedIn Employee Count",'Pass 1 Archive'!$1:$1,0),FALSE()),"") | D3: =IFERROR(VLOOKUP(A3,'Pass 2'!$A:$S,MATCH("Jan 2025 Traffic",'Pass 2'!$1:$1,0),FALSE()),"") | E3: =IFERROR(VLOOKUP(A3,'Pass 2'!$A:$S,MATCH("Jun 2026 Traffic",'Pass 2'!$1:$1,0),FALSE()),"") | F3: =IFERROR(VLOOKUP(A3,'Pass 2'!$A:$S,MATCH("Traffic % Change",'Pass 2'!$1:$1,0),FALSE()),"") | G3: =IFERROR(VLOOKUP(A3,'Pass 2'!$A:$S,MATCH("Jan 2025 Referring Domains",'Pass 2'!$1:$1,0),FALSE()),"") | H3: =IFERROR(VLOOKUP(A3,'Pass 2'!$A:$S,MATCH("Jun 2026 Referring Domains",'Pass 2'!$1:$1,0),FALSE()),"")
B4: =IFERROR(VLOOKUP(A4,'Pass 2'!$A:$S,MATCH("Category",'Pass 2'!$1:$1,0),FALSE()),"") | C4: =IFERROR(VLOOKUP(A4,'Pass 1 Archive'!$A:$AD,MATCH("LinkedIn Employee Count",'Pass 1 Archive'!$1:$1,0),FALSE()),"") | D4: =IFERROR(VLOOKUP(A4,'Pass 2'!$A:$S,MATCH("Jan 2025 Traffic",'Pass 2'!$1:$1,0),FALSE()),"") | E4: =IFERROR(VLOOKUP(A4,'Pass 2'!$A:$S,MATCH("Jun 2026 Traffic",'Pass 2'!$1:$1,0),FALSE()),"") | F4: =IFERROR(VLOOKUP(A4,'Pass 2'!$A:$S,MATCH("Traffic % Change",'Pass 2'!$1:$1,0),FALSE()),"") | G4: =IFERROR(VLOOKUP(A4,'Pass 2'!$A:$S,MATCH("Jan 2025 Referring Domains",'Pass 2'!$1:$1,0),FALSE()),"") | H4: =IFERROR(VLOOKUP(A4,'Pass 2'!$A:$S,MATCH("Jun 2026 Referring Domains",'Pass 2'!$1:$1,0),FALSE()),"")
B5: =IFERROR(VLOOKUP(A5,'Pass 2'!$A:$S,MATCH("Category",'Pass 2'!$1:$1,0),FALSE()),"") | C5: =IFERROR(VLOOKUP(A5,'Pass 1 Archive'!$A:$AD,MATCH("LinkedIn Employee Count",'Pass 1 Archive'!$1:$1,0),FALSE()),"") | D5: =IFERROR(VLOOKUP(A5,'Pass 2'!$A:$S,MATCH("Jan 2025 Traffic",'Pass 2'!$1:$1,0),FALSE()),"") | E5: =IFERROR(VLOOKUP(A5,'Pass 2'!$A:$S,MATCH("Jun 2026 Traffic",'Pass 2'!$1:$1,0),FALSE()),"") | F5: =IFERROR(VLOOKUP(A5,'Pass 2'!$A:$S,MATCH("Traffic % Change",'Pass 2'!$1:$1,0),FALSE()),"") | G5: =IFERROR(VLOOKUP(A5,'Pass 2'!$A:$S,MATCH("Jan 2025 Referring Domains",'Pass 2'!$1:$1,0),FALSE()),"") | H5: =IFERROR(VLOOKUP(A5,'Pass 2'!$A:$S,MATCH("Jun 2026 Referring Domains",'Pass 2'!$1:$1,0),FALSE()),"")
B6: =IFERROR(VLOOKUP(A6,'Pass 2'!$A:$S,MATCH("Category",'Pass 2'!$1:$1,0),FALSE()),"") | C6: =IFERROR(VLOOKUP(A6,'Pass 1 Archive'!$A:$AD,MATCH("LinkedIn Employee Count",'Pass 1 Archive'!$1:$1,0),FALSE()),"") | D6: =IFERROR(VLOOKUP(A6,'Pass 2'!$A:$S,MATCH("Jan 2025 Traffic",'Pass 2'!$1:$1,0),FALSE()),"") | E6: =IFERROR(VLOOKUP(A6,'Pass 2'!$A:$S,MATCH("Jun 2026 Traffic",'Pass 2'!$1:$1,0),FALSE()),"") | F6: =IFERROR(VLOOKUP(A6,'Pass 2'!$A:$S,MATCH("Traffic % Change",'Pass 2'!$1:$1,0),FALSE()),"") | G6: =IFERROR(VLOOKUP(A6,'Pass 2'!$A:$S,MATCH("Jan 2025 Referring Domains",'Pass 2'!$1:$1,0),FALSE()),"") | H6: =IFERROR(VLOOKUP(A6,'Pass 2'!$A:$S,MATCH("Jun 2026 Referring Domains",'Pass 2'!$1:$1,0),FALSE()),"")
B7: =IFERROR(VLOOKUP(A7,'Pass 2'!$A:$S,MATCH("Category",'Pass 2'!$1:$1,0),FALSE()),"") | C7: =IFERROR(VLOOKUP(A7,'Pass 1 Archive'!$A:$AD,MATCH("LinkedIn Employee Count",'Pass 1 Archive'!$1:$1,0),FALSE()),"") | D7: =IFERROR(VLOOKUP(A7,'Pass 2'!$A:$S,MATCH("Jan 2025 Traffic",'Pass 2'!$1:$1,0),FALSE()),"") | E7: =IFERROR(VLOOKUP(A7,'Pass 2'!$A:$S,MATCH("Jun 2026 Traffic",'Pass 2'!$1:$1,0),FALSE()),"") | F7: =IFERROR(VLOOKUP(A7,'Pass 2'!$A:$S,MATCH("Traffic % Change",'Pass 2'!$1:$1,0),FALSE()),"") | G7: =IFERROR(VLOOKUP(A7,'Pass 2'!$A:$S,MATCH("Jan 2025 Referring Domains",'Pass 2'!$1:$1,0),FALSE()),"") | H7: =IFERROR(VLOOKUP(A7,'Pass 2'!$A:$S,MATCH("Jun 2026 Referring Domains",'Pass 2'!$1:$1,0),FALSE()),"")
B8: =IFERROR(VLOOKUP(A8,'Pass 2'!$A:$S,MATCH("Category",'Pass 2'!$1:$1,0),FALSE()),"") | C8: =IFERROR(VLOOKUP(A8,'Pass 1 Archive'!$A:$AD,MATCH("LinkedIn Employee Count",'Pass 1 Archive'!$1:$1,0),FALSE()),"") | D8: =IFERROR(VLOOKUP(A8,'Pass 2'!$A:$S,MATCH("Jan 2025 Traffic",'Pass 2'!$1:$1,0),FALSE()),"") | E8: =IFERROR(VLOOKUP(A8,'Pass 2'!$A:$S,MATCH("Jun 2026 Traffic",'Pass 2'!$1:$1,0),FALSE()),"") | F8: =IFERROR(VLOOKUP(A8,'Pass 2'!$A:$S,MATCH("Traffic % Change",'Pass 2'!$1:$1,0),FALSE()),"") | G8: =IFERROR(VLOOKUP(A8,'Pass 2'!$A:$S,MATCH("Jan 2025 Referring Domains",'Pass 2'!$1:$1,0),FALSE()),"") | H8: =IFERROR(VLOOKUP(A8,'Pass 2'!$A:$S,MATCH("Jun 2026 Referring Domains",'Pass 2'!$1:$1,0),FALSE()),"")
B9: =IFERROR(VLOOKUP(A9,'Pass 2'!$A:$S,MATCH("Category",'Pass 2'!$1:$1,0),FALSE()),"") | C9: =IFERROR(VLOOKUP(A9,'Pass 1 Archive'!$A:$AD,MATCH("LinkedIn Employee Count",'Pass 1 Archive'!$1:$1,0),FALSE()),"") | D9: =IFERROR(VLOOKUP(A9,'Pass 2'!$A:$S,MATCH("Jan 2025 Traffic",'Pass 2'!$1:$1,0),FALSE()),"") | E9: =IFERROR(VLOOKUP(A9,'Pass 2'!$A:$S,MATCH("Jun 2026 Traffic",'Pass 2'!$1:$1,0),FALSE()),"") | F9: =IFERROR(VLOOKUP(A9,'Pass 2'!$A:$S,MATCH("Traffic % Change",'Pass 2'!$1:$1,0),FALSE()),"") | G9: =IFERROR(VLOOKUP(A9,'Pass 2'!$A:$S,MATCH("Jan 2025 Referring Domains",'Pass 2'!$1:$1,0),FALSE()),"") | H9: =IFERROR(VLOOKUP(A9,'Pass 2'!$A:$S,MATCH("Jun 2026 Referring Domains",'Pass 2'!$1:$1,0),FALSE()),"")
B10: =IFERROR(VLOOKUP(A10,'Pass 2'!$A:$S,MATCH("Category",'Pass 2'!$1:$1,0),FALSE()),"") | C10: =IFERROR(VLOOKUP(A10,'Pass 1 Archive'!$A:$AD,MATCH("LinkedIn Employee Count",'Pass 1 Archive'!$1:$1,0),FALSE()),"") | D10: =IFERROR(VLOOKUP(A10,'Pass 2'!$A:$S,MATCH("Jan 2025 Traffic",'Pass 2'!$1:$1,0),FALSE()),"") | E10: =IFERROR(VLOOKUP(A10,'Pass 2'!$A:$S,MATCH("Jun 2026 Traffic",'Pass 2'!$1:$1,0),FALSE()),"") | F10: =IFERROR(VLOOKUP(A10,'Pass 2'!$A:$S,MATCH("Traffic % Change",'Pass 2'!$1:$1,0),FALSE()),"") | G10: =IFERROR(VLOOKUP(A10,'Pass 2'!$A:$S,MATCH("Jan 2025 Referring Domains",'Pass 2'!$1:$1,0),FALSE()),"") | H10: =IFERROR(VLOOKUP(A10,'Pass 2'!$A:$S,MATCH("Jun 2026 Referring Domains",'Pass 2'!$1:$1,0),FALSE()),"")
B11: =IFERROR(VLOOKUP(A11,'Pass 2'!$A:$S,MATCH("Category",'Pass 2'!$1:$1,0),FALSE()),"") | C11: =IFERROR(VLOOKUP(A11,'Pass 1 Archive'!$A:$AD,MATCH("LinkedIn Employee Count",'Pass 1 Archive'!$1:$1,0),FALSE()),"") | D11: =IFERROR(VLOOKUP(A11,'Pass 2'!$A:$S,MATCH("Jan 2025 Traffic",'Pass 2'!$1:$1,0),FALSE()),"") | E11: =IFERROR(VLOOKUP(A11,'Pass 2'!$A:$S,MATCH("Jun 2026 Traffic",'Pass 2'!$1:$1,0),FALSE()),"") | F11: =IFERROR(VLOOKUP(A11,'Pass 2'!$A:$S,MATCH("Traffic % Change",'Pass 2'!$1:$1,0),FALSE()),"") | G11: =IFERROR(VLOOKUP(A11,'Pass 2'!$A:$S,MATCH("Jan 2025 Referring Domains",'Pass 2'!$1:$1,0),FALSE()),"") | H11: =IFERROR(VLOOKUP(A11,'Pass 2'!$A:$S,MATCH("Jun 2026 Referring Domains",'Pass 2'!$1:$1,0),FALSE()),"")
B12: =IFERROR(VLOOKUP(A12,'Pass 2'!$A:$S,MATCH("Category",'Pass 2'!$1:$1,0),FALSE()),"") | C12: =IFERROR(VLOOKUP(A12,'Pass 1 Archive'!$A:$AD,MATCH("LinkedIn Employee Count",'Pass 1 Archive'!$1:$1,0),FALSE()),"") | D12: =IFERROR(VLOOKUP(A12,'Pass 2'!$A:$S,MATCH("Jan 2025 Traffic",'Pass 2'!$1:$1,0),FALSE()),"") | E12: =IFERROR(VLOOKUP(A12,'Pass 2'!$A:$S,MATCH("Jun 2026 Traffic",'Pass 2'!$1:$1,0),FALSE()),"") | F12: =IFERROR(VLOOKUP(A12,'Pass 2'!$A:$S,MATCH("Traffic % Change",'Pass 2'!$1:$1,0),FALSE()),"") | G12: =IFERROR(VLOOKUP(A12,'Pass 2'!$A:$S,MATCH("Jan 2025 Referring Domains",'Pass 2'!$1:$1,0),FALSE()),"") | H12: =IFERROR(VLOOKUP(A12,'Pass 2'!$A:$S,MATCH("Jun 2026 Referring Domains",'Pass 2'!$1:$1,0),FALSE()),"")
B13: =IFERROR(VLOOKUP(A13,'Pass 2'!$A:$S,MATCH("Category",'Pass 2'!$1:$1,0),FALSE()),"") | C13: =IFERROR(VLOOKUP(A13,'Pass 1 Archive'!$A:$AD,MATCH("LinkedIn Employee Count",'Pass 1 Archive'!$1:$1,0),FALSE()),"") | D13: =IFERROR(VLOOKUP(A13,'Pass 2'!$A:$S,MATCH("Jan 2025 Traffic",'Pass 2'!$1:$1,0),FALSE()),"") | E13: =IFERROR(VLOOKUP(A13,'Pass 2'!$A:$S,MATCH("Jun 2026 Traffic",'Pass 2'!$1:$1,0),FALSE()),"") | F13: =IFERROR(VLOOKUP(A13,'Pass 2'!$A:$S,MATCH("Traffic % Change",'Pass 2'!$1:$1,0),FALSE()),"") | G13: =IFERROR(VLOOKUP(A13,'Pass 2'!$A:$S,MATCH("Jan 2025 Referring Domains",'Pass 2'!$1:$1,0),FALSE()),"") | H13: =IFERROR(VLOOKUP(A13,'Pass 2'!$A:$S,MATCH("Jun 2026 Referring Domains",'Pass 2'!$1:$1,0),FALSE()),"")
... B500: =IFERROR(VLOOKUP(A500,'Pass 2'!$A:$S,MATCH("Category",'Pass 2'!$1:$1,0),FALSE()),"") | C500: =IFERROR(VLOOKUP(A500,'Pass 1 Archive'!$A:$AD,MATCH("LinkedIn Employee Count",'Pass 1 Archive'!$1:$1,0),FALSE()),"") | D500: =IFERROR(VLOOKUP(A500,'Pass 2'!$A:$S,MATCH("Jan 2025 Traffic",'Pass 2'!$1:$1,0),FALSE()),"") | E500: =IFERROR(VLOOKUP(A500,'Pass 2'!$A:$S,MATCH("Jun 2026 Traffic",'Pass 2'!$1:$1,0),FALSE()),"") | F500: =IFERROR(VLOOKUP(A500,'Pass 2'!$A:$S,MATCH("Traffic % Change",'Pass 2'!$1:$1,0),FALSE()),"") | G500: =IFERROR(VLOOKUP(A500,'Pass 2'!$A:$S,MATCH("Jan 2025 Referring Domains",'Pass 2'!$1:$1,0),FALSE()),"") | H500: =IFERROR(VLOOKUP(A500,'Pass 2'!$A:$S,MATCH("Jun 2026 Referring Domains",'Pass 2'!$1:$1,0),FALSE()),"")

Sheet Research Log
A1: Log ID | B1: Date | C1: Related Company ID | D1: Category Tag | E1: Observation | F1: Why It's Interesting | G1: Action Needed | H1: Status
A2: 1 | B2: 2026-06-27 | C2: Reply.io, Workday, BoldDesk, EngageBay, Sobot | D2: finding | E2: Five companies across five unrelated verticals (Sales Engagement, HR/People Ops, Customer Support x3) show the same shape: genuine mid-window growth into a peak, followed by a pullback severe enough to flip the net Jan2025-Jun2026 classification to Declined. | F2: If this keeps recurring as more verticals are entered, it suggests a meaningful share of 'declining' B2B SaaS companies aren't chronically shrinking -- they grew into a cliff. That's a more interesting and more accurate headline than a flat decline narrative, and worth testing for statistical weight once all 100 are in. | G2: Re-check this pattern's prevalence once all 10 verticals are entered. If it holds at scale, consider as a primary report finding. | H2: Open
A3: 2 | B3: 2026-06-27 | C3: Keka, Justworks | D3: question | E3: Both companies show one anomalous single-month traffic collapse in their final data point (Keka: -59% MoM May->Jun 2026; Justworks: -21.5% MoM same months) that is far steeper than any other month-over-month move in their series. | F3: Unclear whether this reflects a real business event, a domain/tracking change, or an Ahrefs measurement artifact. Treating it as ordinary organic decline without checking could distort both companies' trajectory classification. | G3: Investigate both during Pass 3 deep dive / comparison group selection: check for site migrations, Google updates, or other dated events around May-Jun 2026. | H3: Open
A4: 3 | B4: 2026-06-27 | C4: Front, Freshworks, LiveAgent, EngageBay, TriNet, Keka, Justworks, Help Scout, ZoomInfo | D4: future-research | E4: Nine companies across multiple verticals show all-time historical traffic peaks that predate the Jan 2025 study window by 1-5 years, several clustering in the 2021-2024 range, well above any traffic seen within the study window itself. | F4: This may point to a sector-wide organic decay pattern (post-ZIRP marketing pullback, a Google core update, category maturity) that is bigger than any single company's story -- exactly the kind of cross-company signal this research project is designed to surface, as opposed to company-specific narratives. | G4: Track whether this clustering continues as the remaining 5 verticals are entered. If the historical-peak dates cluster further, consider a dedicated chart/finding on sector-wide organic decay timing. | H4: Open
A5: 4 | B5: 2026-06-27 | C5: Sobot, TeamSupport | D5: methodology-note | E5: Both companies are classified Grew off extremely large percentage changes (Sobot +395%, TeamSupport +298%) driven by tiny Jan 2025 starting traffic (1,149 and 596/mo respectively), not real momentum at scale. | F5: Leading with the percentage alone in the report would overstate these as standout growth stories when the underlying absolute traffic remains small and, in both cases, the trajectory shape is volatile/plateaued rather than sustained growth. | G5: When writing the report, always pair small-base percentage changes with absolute traffic numbers; flag for exclusion from any 'top growth' ranking that doesn't control for starting base. | H5: Open
A6: 5 | B6: 2026-06-27 | C6: All companies entered to date (57 of 100, 5 of 10 verticals) | D6: finding | E6: Declined-rate varies sharply by vertical so far: Customer Success 31% Declined, Sales Engagement 45%, Marketing Automation 64%, HR/People Operations 73%, Customer Support/Help Desk 73%. | F6: Organic decline isn't uniform across B2B SaaS categories -- if this spread holds once all 10 verticals are in, it suggests category-level dynamics (competitive intensity, AI-answer-engine disruption, category maturity) matter more than company-specific execution for at least some verticals. Preliminary only -- based on 5 of 10 categories and small per-category samples (11-13 each). | G6: Re-run this breakdown once all 100 companies are entered. If the spread holds, it's a strong candidate for a report section on which B2B SaaS categories are most exposed to organic decline. | H6: Open
A7: 6 | B7: 2026-06-28 | C7: Semaphore | D7: finding | E7: Semaphore (Developer Tools/DevOps) had literally 0 organic traffic in Jan-Feb 2025 and built its entire organic presence (0 -> 27,797 monthly traffic) during the study window itself. | F7: Every other company in the dataset had pre-existing organic traffic before the study window began. Semaphore is the only true from-zero organic launch observed -- a fundamentally different growth story than 'declined' or 'grew from an established base.' Worth a closer look at what drove the Mar 2025 inflection and the sustained 2026 acceleration. | G7: Flag as Deep Dive candidate during the selection pass -- a from-zero launch case study would be a distinctive, evidence-backed narrative for content/positioning. | H7: Open
A8: 7 | B8: 2026-06-28 | C8: GitHub | D8: finding | E8: GitHub's organic traffic fell ~72% from Jan 2025 (172.3M) to a Feb 2026 trough (39.6M), with the all-time peak (214.7M) occurring just 3 months before the study window opened (Oct 2024) -- by far the largest decline of any company in the dataset, on what is likely its single most authoritative domain. | F8: The scale and timing (peak right before the window, freefall through 2025, partial stabilization in 2026) lines up with the period when AI coding assistants and chat-based search became mainstream developer workflow. If even GitHub -- a domain with enormous existing authority -- is losing this much organic search traffic, it's a strong data point for the project's core AEO/GEO thesis: traditional SEO authority does not protect against AI-mediated answer retrieval bypassing the search click entirely. | G8: Treat as a hypothesis, not confirmed causation. Worth checking whether the decline correlates with known Google algorithm updates, AI Overview rollout dates, or GitHub-specific product/SEO changes before citing this as an AEO/GEO proof point externally. | H8: Open
A9: 8 | B9: 2026-06-28 | C9: Whatfix | D9: anomaly | E9: Whatfix's traffic spiked to 990,660 in Jul2025 (over 16x its Jan2025 baseline of 319,454 and 3x the surrounding months), then declined almost continuously and severely afterward, falling to 27,947 by Jun2026 -- a -91.25% net change over the window and -97.18% off the spike peak. This is the single most extreme traffic pattern recorded anywhere in this study, exceeding even GitHub's decline in magnitude. | F9: The size and isolation of the Jul2025 spike (one month, ~2x even the next-highest month) raises real doubt about whether the subsequent 'decline' is a genuine organic collapse or simply reversion to baseline after a one-time event (viral content, a short-lived high-volume SERP feature, or a measurement/tracking anomaly). If genuine, it would be one of the most dramatic single-company collapses in the dataset and worth flagging as an extreme case in any cross-company synthesis; if it's an artifact, including it uncorrected would badly distort vertical-level averages. | G9: Pass 3: pull keyword-level data for Jul2025 to identify what drove the spike before drawing any conclusion. Do not include Whatfix's raw % change in any vertical-level summary statistic until this is resolved -- it will skew the Product Analytics/PM average significantly. | H9: Open

Sheet Pattern Tracker
A1: Pattern ID | B1: Pattern | C1: Supporting Companies | D1: Contradicting Companies | E1: Evidence | F1: Confidence | G1: Status | H1: Potential Report Section | I1: Cross-Cut Notes (Buying Motion / Buyer Type) | J1: Last Updated | K1: Notes

Sheet Lists
A1: Categories | B1: GrowthDriver | C1: ContentType | D1: TrafficTrajectory
A2: Sales Engagement / Sales Intelligence | B2: Docs hub | C2: Comparison pages | D2: Continuous Acceleration
A3: Marketing Automation | B3: Comparison pages | C3: Alternatives pages | D3: Steady Growth
A4: Customer Support / Help Desk | B4: Alternatives pages | C4: Documentation/Help center | D4: Growth then Pullback
A5: Customer Success | B5: Free tool | C5: Glossary/Definitional | D5: Early Peak then Plateau
A6: HR / People Operations | B6: Brand/domain strength | C6: Product/Feature pages | D6: Early Peak then Decline
A7: Finance / Spend Management | B7: Content refreshes | C7: Educational/How-to | D7: Decline then Recovery
A8: Project Management / Collaboration | B8: New product/category expansion | C8: Original data/Research | D8: Flat
A9: Developer Tools / DevOps | B9: Backlink growth | C9: Customer stories/Case studies | D9: Steady Decline
A10: Security / Compliance | B10: Unclear | C10: Free tool/Calculator | D10: Volatile
A11: Product Analytics / Product Management | C11: Other
