Workbook

Sheet Dashboard
A1: S.LAB Research Project #1 — Dashboard
A2: Pulls live from Candidate Companies / Deep Dive Database / Comparison Group Database. Do not type values into column B below row 5 except where noted.
A4: Metric | B4: Count
A5: Companies screened | B5: =COUNTA('Pass 1 Archive'!A2:A500) -> 195
A6: Companies included | B6: =COUNTA('Pass 2'!A2:A500) -> 13
A7: Companies excluded | B7: =COUNTIF('Pass 1 Archive'!X2:X500,"Exclude") -> 23
A8: Companies pending decision | B8: =COUNTIF('Pass 1 Archive'!X2:X500,"Pending") -> 24
A9: Traffic classifications complete | B9: =COUNTA('Pass 2'!R2:R500) -> 13
A10: — Grew | B10: =COUNTIF('Pass 2'!R2:R500,"Grew") -> 0
A11: — Flat | B11: =COUNTIF('Pass 2'!R2:R500,"Flat") -> 4
A12: — Declined | B12: =COUNTIF('Pass 2'!R2:R500,"Declined") -> 0
A13: Deep dives selected | B13: =COUNTIF('Pass 1 Archive'!Z2:Z500,"Yes") -> 0
A14: Deep dives complete | B14: =COUNTIF('Deep Dive Database'!AK2:AK500,"Complete") -> 0
A15: Comparison reviews selected | B15: =COUNTIF('Pass 1 Archive'!AA2:AA500,"Yes") -> 0
A16: Comparison reviews complete | B16: =COUNTIF('Comparison Group Database'!Q2:Q500,"Complete") -> 0
A17: Patterns logged | B17: =COUNTA('Pattern Tracker'!A2:A500) -> 0
A18: Research log entries | B18: =COUNTA('Research Log'!A2:A500) -> 0
A20: Companies included by category (target 10 each)
A21: Category | B21: Included | C21: Target
A22: Sales Engagement / Sales Intelligence | B22: =COUNTIF('Pass 2'!B2:B500,A22) -> 0 | C22: 10
A23: Marketing Automation | B23: =COUNTIF('Pass 2'!B2:B500,A23) -> 0 | C23: 10
A24: Customer Support / Help Desk | B24: =COUNTIF('Pass 2'!B2:B500,A24) -> 0 | C24: 10
A25: Customer Success | B25: =COUNTIF('Pass 2'!B2:B500,A25) -> 13 | C25: 10
A26: HR / People Operations | B26: =COUNTIF('Pass 2'!B2:B500,A26) -> 0 | C26: 10
A27: Finance / Spend Management | B27: =COUNTIF('Pass 2'!B2:B500,A27) -> 0 | C27: 10
A28: Project Management / Collaboration | B28: =COUNTIF('Pass 2'!B2:B500,A28) -> 0 | C28: 10
A29: Developer Tools / DevOps | B29: =COUNTIF('Pass 2'!B2:B500,A29) -> 0 | C29: 10
A30: Security / Compliance | B30: =COUNTIF('Pass 2'!B2:B500,A30) -> 0 | C30: 10
A31: Product Analytics / Product Management | B31: =COUNTIF('Pass 2'!B2:B500,A31) -> 0 | C31: 10
A32: Total | B32: =SUM(B22:B31) -> 13

Sheet Field Reference
A1: Field Reference — schema documentation for every tab in this workbook
A2: Read this before entering data. Each row documents one column: what it is, its data type, and its dropdown values (if any). Column order here matches the actual workflow order in each tab — it is not alphabetical.
A4: Tab | B4: Column | C4: Description | D4: Data Type | E4: Dropdown Values / Notes
A5: Company Tracker | B5: Company Name | C5: Locked/included company. Join key used across Pass 1 Archive, Deep Dive Database, and Comparison Group Database — must match exactly across all four sheets. | D5: Text
A6: Company Tracker | B6: Category | C6: Sourcing category carried over from Pass 1 Archive at lock time. | D6: Dropdown | E6: 10 locked categories (see Lists tab)
A7: Company Tracker | B7: Jan 2025 Traffic | C7: Organic traffic at study window start. From Ahrefs Performance report export. | D7: Number
A8: Company Tracker | B8: Jun 2026 Traffic | C8: Organic traffic at study window end. | D8: Number
A9: Company Tracker | B9: Traffic % Change | C9: Auto-calculated. Do not type into this column. | D9: Formula | E9: =IFERROR((JUN2026-JAN2025)/JAN2025,"")
A10: Company Tracker | B10: Jan 2025 Traffic Value | C10: Ahrefs Organic Traffic Value at study window start. | D10: Number
A11: Company Tracker | B11: Jun 2026 Traffic Value | C11: Ahrefs Organic Traffic Value at study window end. | D11: Number
A12: Company Tracker | B12: Traffic Value % Change | C12: Auto-calculated. Do not type into this column. | D12: Formula | E12: =IFERROR((end-start)/start,"")
A13: Company Tracker | B13: Jan 2025 Referring Domains | C13: Ahrefs Referring Domains at study window start. | D13: Number
A14: Company Tracker | B14: Jun 2026 Referring Domains | C14: Ahrefs Referring Domains at study window end. | D14: Number
A15: Company Tracker | B15: Referring Domains % Change | C15: Auto-calculated. Do not type into this column. | D15: Formula | E15: =IFERROR((end-start)/start,"")
A16: Company Tracker | B16: Study Window Peak Traffic | C16: Highest monthly organic traffic observed WITHIN the study window (Jan 2025-June 2026) only. | D16: Number
A17: Company Tracker | B17: Study Window Peak Month | C17: Month the within-window peak occurred (e.g., "March 2026"). Pairs with Study Window Peak Traffic. | D17: Text
A18: Company Tracker | B18: Historical Peak Traffic | C18: All-time peak monthly organic traffic, including before the study window (expanded to all 100 companies as of V1.2 - previously Pass-3-only). Pairs with Historical Peak Month. | D18: Number
A19: Company Tracker | B19: Historical Peak Month | C19: Month the all-time historical peak occurred. May fall before or during the study window. | D19: Text
A20: Company Tracker | B20: Distance from Historical Peak % | C20: Auto-calculated: how current (Jun 2026) traffic compares to the company's all-time historical peak. Negative = still below all-time peak; positive = has exceeded it. | D20: Formula | E20: =IFERROR((jun2026traffic-historicalpeaktraffic)/historicalpeaktraffic,"")
A21: Company Tracker | B21: Traffic Trajectory | C21: Describes how the company arrived at its Classification using the within-study-window time series only - shape, not outcome. Official 9-value taxonomy - choose closest match rather than inventing a new label. | D21: Dropdown | E21: Continuous Acceleration, Steady Growth, Growth then Pullback, Early Peak then Plateau, Early Peak then Decline, Decline then Recovery, Flat, Steady Decline, Volatile
A22: Company Tracker | B22: Classification | C22: Pass 2 outcome, determined from the study window only. | D22: Dropdown | E22: Grew, Flat, Declined
A23: Company Tracker | B23: Notes | C23: Freeform. | D23: Text
A24: Pass 1 Archive | B24: Company Name | C24: Join key. Every candidate ever screened gets a row here, regardless of Inclusion Decision. | D24: Text
A25: Pass 1 Archive | B25: Website/Domain | C25: Primary domain used for Ahrefs lookups. | D25: Text (URL)
A26: Pass 1 Archive | B26: Category | C26: Sourcing category from the locked 10-category list (Section 3 of operating manual). Source of truth for the Category field carried over to Company Tracker at lock time. | D26: Dropdown
A27: Pass 1 Archive | B27: Date Added | C27: Date the candidate was first logged. | D27: Date
A28: Pass 1 Archive | B28: Source List | C28: Where the candidate was discovered. | D28: Dropdown | E28: G2, Crozdesk, GetApp, Capterra, Other
A29: Pass 1 Archive | B29: Source URL | C29: Link to the specific G2/directory page the candidate was pulled from. | D29: Text (URL)
A30: Pass 1 Archive | B30: Screened By | C30: Who ran the inclusion screen. | D30: Text
A31: Pass 1 Archive | B31: Screening Date | C31: Date the inclusion screen was run. | D31: Date
A32: Pass 1 Archive | B32: B2B SaaS Confirmed? | C32: Gate 1 - quick judgment call from the company's own homepage. | D32: Dropdown | E32: Yes, No
A33: Pass 1 Archive | B33: One-Line Description | C33: What the company sells, in plain language. | D33: Text
A34: Pass 1 Archive | B34: Founded Year | C34: From Crunchbase or company site. | D34: Number
A35: Pass 1 Archive | B35: Public/Private | C35: From Crunchbase. | D35: Dropdown | E35: Public, Private
A36: Pass 1 Archive | B36: LinkedIn Employee Count | C36: Descriptive metadata only (V1.1) - not a screening gate. Standardized single source; do not average across conflicting sources. | D36: Number
A37: Pass 1 Archive | B37: Employee Count Source/Date | C37: E.g. 'LinkedIn, 2026-07-01' - keeps the standardization auditable. | D37: Text
A38: Pass 1 Archive | B38: Funding Status / Total Raised | C38: From Crunchbase. | D38: Text
A39: Pass 1 Archive | B39: M&A Status | C39: Gate 2 - exclude if the M&A/rebrand was recent or disruptive enough to break continuous attributable history; include-with-flag if clean. Requires a documented treatment decision, not just a status label. | D39: Dropdown | E39: Independent, Acquired, Merged, Rebranded
A40: Pass 1 Archive | B40: M&A Notes | C40: Date, acquirer, and the treatment decision reasoning. | D40: Text
A41: Pass 1 Archive | B41: Domain Stable During Window? | C41: Gate 3 - No = exclude (breaks Ahrefs trend continuity). | D41: Dropdown | E41: Yes, No
A42: Pass 1 Archive | B42: Primary ICP | C42: Company's own stated target customer - not G2's segment grid. | D42: Dropdown | E42: SMB, Mid-Market, Enterprise
A43: Pass 1 Archive | B43: Buying Motion | C43: Metadata only, not a selection criterion. | D43: Dropdown | E43: PLG, Sales-led, Hybrid
A44: Pass 1 Archive | B44: Primary Buyer | C44: Metadata only, not a selection criterion. | D44: Dropdown | E44: Technical, Non-technical
A45: Pass 1 Archive | B45: Non-Core Asset Flag | C45: Yes if a free tool/calculator/template library/content hub drives a meaningful share of traffic. A flag, not an exclusion. | D45: Dropdown | E45: Yes, No
A46: Pass 1 Archive | B46: Non-Core Asset Notes | C46: What the non-core asset is, if flagged. | D46: Text
A47: Pass 1 Archive | B47: Inclusion Decision | C47: Final screening outcome across all 5 gates. Keep excluded rows - don't delete them. Include = company is also added to Company Tracker. | D47: Dropdown | E47: Include, Exclude, Pending
A48: Pass 1 Archive | B48: Exclusion Reason | C48: Required if Inclusion Decision = Exclude. 'Looked fine' is not an acceptable reason. | D48: Text
A49: Pass 1 Archive | B49: Selected for Deep Dive? | C49: Top 8-10 growth winners, selected after Pass 2 classification. | D49: Dropdown | E49: Yes, No
A50: Pass 1 Archive | B50: Selected for Comparison Group? | C50: ~8 decliners, selected after Pass 2 classification. | D50: Dropdown | E50: Yes, No
A51: Pass 1 Archive | B51: Research Status | C51: Overall review progress for this company. | D51: Dropdown | E51: Not Started, In Progress, Complete
A52: Pass 1 Archive | B52: Tags | C52: Freeform, comma-separated (e.g. 'PLG, comparison-pages-heavy'). | D52: Text
A53: Pass 1 Archive | B53: Last Updated | C53: Bump whenever the row changes. | D53: Date
A54: Deep Dive Database | B54: Company Name | C54: Typed key - must match a Company Name in Company Tracker exactly. | D54: Text
A55: Deep Dive Database | B55: Category / Traffic Start/End / % Change / Ref. Domains Start/End | C55: Auto-pulled via VLOOKUP from Company Tracker. Do not type. | D55: Formula
A56: Deep Dive Database | B56: Employees | C56: Auto-pulled via VLOOKUP from Pass 1 Archive. Do not type. | D56: Formula
A57: Deep Dive Database | B57: Reviewed Date | C57: Date the deep dive was conducted. | D57: Date
A58: Deep Dive Database | B58: Time Spent (min) | C58: Time-box target: 60-90 minutes. | D58: Number
A59: Deep Dive Database | B59: Reviewer | C59: Who did the review. | D59: Text
A60: Deep Dive Database | B60: Growth URL 1-5 (URL / Content Type / Est. Traffic Change) | C60: The core of the deep dive - required. If fewer than 5 pages account for the bulk of growth, leave remaining rows blank; that concentration is itself a finding. | D60: Text/Dropdown/Number | E60: Content Type = see Content Type list
A61: Deep Dive Database | B61: Growth Concentration | C61: Concentrated = a few pages did most of the work. | D61: Dropdown | E61: Concentrated, Distributed
A62: Deep Dive Database | B62: Content Origin | C62: Net-new vs. refreshed existing content. | D62: Dropdown | E62: Net-new, Refreshed, Both
A63: Deep Dive Database | B63: Growth Timing | C63: Gradual climb vs. step-changes tied to specific publishes. | D63: Dropdown | E63: Gradual, Step-change
A64: Deep Dive Database | B64: Referring Domain Notes | C64: Notable new referring domains and any pattern in them. | D64: Text
A65: Deep Dive Database | B65: Internal Linking Observations | C65: Any visible internal-linking pattern connecting growth pages to core product pages. | D65: Text
A66: Deep Dive Database | B66: AI Visibility Spot-Check Notes | C66: Manual ChatGPT/Perplexity prompt checks, if time allows. | D66: Text
A67: Deep Dive Database | B67: Anything Surprising | C67: Required field - name at least one thing. | D67: Text
A68: Deep Dive Database | B68: Anything Contradicting Hypotheses | C68: Required field - if nothing contradicts, say so explicitly. | D68: Text
A69: Deep Dive Database | B69: Quotable Pattern Candidates | C69: Exact phrasing/numbers that could become a line in the report. | D69: Text
A70: Deep Dive Database | B70: Primary Growth Driver (confirmed) | C70: Post-deep-dive confirmed value - may differ from the original hypothesis. | D70: Dropdown | E70: See Growth Driver list
A71: Deep Dive Database | B71: Review Status | D71: Dropdown | E71: Not Started, In Progress, Complete
A72: Deep Dive Database | B72: Notes/Follow-ups | D72: Text
A73: Deep Dive Database | B73: Review Complete | C73: Simple completion flag for filtering as the project scales. Complements Review Status; does not replace it. | D73: Dropdown | E73: Yes, No
A74: Deep Dive Database | B74: Long-Term Traffic Story | C74: 1-3 sentence narrative of the company's overall long-term traffic pattern (e.g., large historical peak, long decline, recovery beginning mid-window). Interpretation, not measurement - never changes Pass 2 Classification. | D74: Text
A75: Deep Dive Database | B75: Major Inflection Points | C75: Notable dates/events where the traffic trend visibly changed direction, pre- or post-window. | D75: Text
A76: Deep Dive Database | B76: Acquisitions / Mergers | C76: Any M&A history, including pre-window, relevant to interpreting the company's trajectory. Does not retroactively change the Pass 1 Include/Exclude decision. | D76: Text
A77: Deep Dive Database | B77: Rebrands | C77: Any rebrand history relevant to interpreting the traffic story. | D77: Text
A78: Deep Dive Database | B78: Domain Migrations | C78: Any domain migration history relevant to interpreting the traffic story. | D78: Text
A79: Deep Dive Database | B79: Product Launches / Notable Events | C79: Other notable events (product launches, funding events, major press) useful for interpreting the trajectory, when discoverable. | D79: Text
A80: Comparison Group Database | B80: Company Name | C80: Typed key - must match a Company Name in Company Tracker exactly. | D80: Text
A81: Comparison Group Database | B81: Category / Employees / Traffic & Referring Domain trend | C81: Auto-pulled via VLOOKUP from Company Tracker / Pass 1 Archive. | D81: Formula
A82: Comparison Group Database | B82: Reviewed Date | D82: Date
A83: Comparison Group Database | B83: Time Spent (min) | C83: Time-box target: 20-30 minutes. | D83: Number
A84: Comparison Group Database | B84: Publishing Activity | C84: Visible publishing activity during the window, or largely static. | D84: Dropdown | E84: Active, Minimal, Static
A85: Comparison Group Database | B85: Growth-Associated Content Types Present? | C85: Are the content types associated with winners present but underperforming, or genuinely absent? | D85: Dropdown | E85: Present-underperforming, Absent, Unclear
A86: Comparison Group Database | B86: Content Types Notes | D86: Text
A87: Comparison Group Database | B87: Likely Decline Explanation | C87: Most likely plain-language explanation. | D87: Dropdown | E87: Algorithm change, Lack of publishing, Competitive displacement, Product/market issue, Other, Unclear
A88: Comparison Group Database | B88: One-Line Takeaway | D88: Text
A89: Comparison Group Database | B89: Confidence | D89: Dropdown | E89: High, Medium, Low, Unclear
A90: Comparison Group Database | B90: Review Status | D90: Dropdown | E90: Not Started, In Progress, Complete
A91: Comparison Group Database | B91: Review Complete | C91: Simple completion flag for filtering as the project scales. Complements Review Status; does not replace it. | D91: Dropdown | E91: Yes, No
A92: Research Log | B92: Log ID | C92: Format LOG-001, increments. | D92: Text
A93: Research Log | B93: Date | D93: Date
A94: Research Log | B94: Related Company | C94: Optional - not every entry ties to one company. | D94: Text
A95: Research Log | B95: Category Tag | D95: Dropdown | E95: Finding, Surprise, Question, Future-research, LinkedIn-post, Newsletter, Methodology-note
A96: Research Log | B96: Observation | D96: Text
A97: Research Log | B97: Why It's Interesting | D97: Text
A98: Research Log | B98: Action Needed | D98: Text
A99: Research Log | B99: Status | D99: Dropdown | E99: Open, Actioned, Archived
A100: Pattern Tracker | B100: Pattern ID | C100: Format PAT-001. | D100: Text
A101: Pattern Tracker | B101: Pattern | C101: Stated as a claim, e.g. 'Winners concentrate growth in comparison pages.' | D101: Text
...

Sheet Pass 2
A1: Company Name | B1: Category | C1: Jan 2025 Traffic | D1: Jun 2026 Traffic | E1: Traffic % Change | F1: Jan 2025 Traffic Value | G1: Jun 2026 Traffic Value | H1: Traffic Value % Change | I1: Jan 2025 Referring Domains | J1: Jun 2026 Referring Domains | K1: Referring Domains % Change | L1: Study Window Peak Traffic | M1: Study Window Peak Month | N1: Historical Peak Traffic | O1: Historical Peak Month | P1: Distance from Historical Peak % | Q1: Traffic Trajectory | R1: Classification | S1: Notes
A2: Gainsight | B2: Customer Success | C2: 40301 | D2: 142301 | E2: =IFERROR((D2-C2)/C2,"") -> 2.5309546 | F2: 190281 | G2: 373192 | H2: =IFERROR((G2-F2)/F2,"") -> 0.96126781 | I2: 3088 | J2: 7438 | K2: =IFERROR((J2-I2)/I2,"") -> 1.4086788 | L2: 142301 | M2: Jun 2026 | N2: 142301 | O2: Jun 2026 | P2: =IFERROR((D2-N2)/N2,"") -> 0 | Q2: Continuous Acceleration | R2: Winner | S2: Traffic, traffic value, and referring domains all increased consistently throughout the study window with no meaningful pullback. The historical peak occurred at the end of the study window, indicating sustained momentum.
A3: Planhat | B3: Customer Success | C3: 10085 | D3: 10716 | E3: =IFERROR((D3-C3)/C3,"") -> 0.062568171 | F3: 98425 | G3: 114192 | H3: =IFERROR((G3-F3)/F3,"") -> 0.16019304 | I3: 653 | J3: 1107 | K3: =IFERROR((J3-I3)/I3,"") -> 0.69525268 | L3: 12270 | M3: Mar 2025 | N3: 12270 | O3: Mar 2025 | P3: =IFERROR((D3-N3)/N3,"") -> -0.12665037 | Q3: Flat | R3: Flat | S3: Traffic peaked early in the study window before settling into a relatively stable range. Traffic value and referring domains continued to grow despite minimal net traffic growth. The historical peak occurred during the study window.
A4: ClientSuccess | B4: Customer Success | C4: 3593 | D4: 3458 | E4: =IFERROR((D4-C4)/C4,"") -> -0.037573059 | F4: 17048 | G4: 25297 | H4: =IFERROR((G4-F4)/F4,"") -> 0.48386908 | I4: 766 | J4: 955 | K4: =IFERROR((J4-I4)/I4,"") -> 0.24673629 | L4: 4303 | M4: Apr 2025 | N4: 4831 | O4: Jun 2024 | P4: =IFERROR((D4-N4)/N4,"") -> -0.28420617 | Q4: Flat | R4: Flat | S4: Traffic peaked early in the study window before gradually returning to approximately its January 2025 level. Traffic value and referring domains continued to increase despite essentially flat organic traffic. The historical peak occurred before the study window.
A5: Vitally | B5: Customer Success | C5: 5692 | D5: 3609 | E5: =IFERROR((D5-C5)/C5,"") -> -0.36595221 | F5: 32421 | G5: 26642 | H5: =IFERROR((G5-F5)/F5,"") -> -0.17824867 | I5: 1018 | J5: 1540 | K5: =IFERROR((J5-I5)/I5,"") -> 0.51277014 | L5: 6859 | M5: Sep 2025 | N5: 6859 | O5: Sep 2025 | P5: =IFERROR((D5-N5)/N5,"") -> -0.47383 | Q5: Growth then Pullback | R5: Decline | S5: Traffic grew steadily through September 2025 before reversing and finishing well below its January 2025 level. Traffic value also declined, while referring domains continued to grow significantly. The historical peak occurred during the study window.
A6: Custify | B6: Customer Success | C6: 19997 | D6: 13081 | E6: =IFERROR((D6-C6)/C6,"") -> -0.34585188 | F6: 64847 | G6: 47773 | H6: =IFERROR((G6-F6)/F6,"") -> -0.26329668 | I6: 1541 | J6: 2478 | K6: =IFERROR((J6-I6)/I6,"") -> 0.60804672 | L6: 22299 | M6: Oct 2025 | N6: 22299 | O6: Oct 2025 | P6: =IFERROR((D6-N6)/N6,"") -> -0.41338177 | Q6: Growth then Pullback | R6: Decline | S6: Traffic increased through October 2025 before declining steadily through the remainder of the study window. Traffic value declined alongside traffic, while referring domains continued to grow substantially. The historical peak occurred during the study window.
A7: Akita | B7: Customer Success | C7: 233 | D7: 666 | E7: =IFERROR((D7-C7)/C7,"") -> 1.8583691 | F7: 219 | G7: 1696 | H7: =IFERROR((G7-F7)/F7,"") -> 6.7442922 | I7: 200 | J7: 554 | K7: =IFERROR((J7-I7)/I7,"") -> 1.77 | L7: 666 | M7: Jun 2026 | N7: 666 | O7: Jun 2026 | P7: =IFERROR((D7-N7)/N7,"") -> 0 | Q7: Continuous Acceleration | R7: Winner | S7: Organic traffic, traffic value, and referring domains increased consistently throughout the study window with no meaningful pullback. The historical peak occurred at the end of the study window, indicating continued upward momentum.
A8: Kapta | B8: Customer Success | C8: 5166 | D8: 3118 | E8: =IFERROR((D8-C8)/C8,"") -> -0.39643825 | F8: 7231 | G8: 4575 | H8: =IFERROR((G8-F8)/F8,"") -> -0.36730743 | I8: 467 | J8: 805 | K8: =IFERROR((J8-I8)/I8,"") -> 0.72376874 | L8: 7754 | M8: Mar 2025 | N8: 7754 | O8: Mar 2025 | P8: =IFERROR((D8-N8)/N8,"") -> -0.59788496 | Q8: Early Peak then Decline | R8: Decline | S8: Traffic surged to its highest level early in the study window (March 2025) before entering a sustained decline through June 2026. Traffic value fell alongside traffic, while referring domains continued to grow. The historical peak occurred during the study window.
A9: ChurnZero | B9: Customer Success | C9: 18682 | D9: 23558 | E9: =IFERROR((D9-C9)/C9,"") -> 0.26099989 | F9: 236975 | G9: 181454 | H9: =IFERROR((G9-F9)/F9,"") -> -0.23429054 | I9: 1271 | J9: 2454 | K9: =IFERROR((J9-I9)/I9,"") -> 0.93076318 | L9: 37436 | M9: Mar 2026 | N9: 37436 | O9: Mar 2026 | P9: =IFERROR((D9-N9)/N9,"") -> -0.37071268 | Q9: Growth then Pullback | R9: Winner | S9: Traffic accelerated to an all-time high in March 2026 before pulling back, but still finished above its January 2025 level. Traffic value declined despite overall traffic growth, while referring domains nearly doubled. The historical peak occurred during the study window.
A10: UserGuiding | B10: Customer Success | C10: 36151 | D10: 7095 | E10: =IFERROR((D10-C10)/C10,"") -> -0.80373987 | F10: 93086 | G10: 46249 | H10: =IFERROR((G10-F10)/F10,"") -> -0.50315837 | I10: 3442 | J10: 4503 | K10: =IFERROR((J10-I10)/I10,"") -> 0.30825102 | L10: 48608 | M10: Aug 2025 | N10: 149605 | O10: Apr 2023 | P10: =IFERROR((D10-N10)/N10,"") -> -0.95257511 | Q10: Steady Decline | R10: Decline | S10: Traffic reached its study-window peak in August 2025 before entering a sustained decline through June 2026. Traffic value also declined substantially, while referring domains continued to grow. The historical peak occurred well before the study window (April 2023).
A11: Velaris | B11: Customer Success | C11: 975 | D11: 4887 | E11: =IFERROR((D11-C11)/C11,"") -> 4.0123077 | F11: 2002 | G11: 11764 | H11: =IFERROR((G11-F11)/F11,"") -> 4.8761239 | I11: 227 | J11: 692 | K11: =IFERROR((J11-I11)/I11,"") -> 2.0484581 | L11: 8085 | M11: Apr 2026 | N11: 8085 | O11: Apr 2026 | P11: =IFERROR((D11-N11)/N11,"") -> -0.39554731 | Q11: Growth then Pullback | R11: Winner | S11: Traffic grew rapidly throughout the study window, reaching an all-time high in April 2026 before pulling back modestly by June 2026. Traffic value and referring domains also increased substantially. The historical peak occurred during the study window.
A12: Rocketlane | B12: Customer Success | C12: 16602 | D12: 17994 | E12: =IFERROR((D12-C12)/C12,"") -> 0.08384532 | F12: 73974 | G12: 97479 | H12: =IFERROR((G12-F12)/F12,"") -> 0.31774678 | I12: 711 | J12: 2001 | K12: =IFERROR((J12-I12)/I12,"") -> 1.814346 | L12: 18375 | M12: Feb 2026 | N12: 19426 | O12: Sep 2024 | P12: =IFERROR((D12-N12)/N12,"") -> -0.073715639 | Q12: Flat | R12: Flat | S12: Traffic remained relatively stable throughout the study window, reaching a modest peak in February 2026 before ending slightly above its January 2025 level. Traffic value and referring domains increased substantially. The historical peak occurred before the study window (September 2024).
A13: Higher Logic | B13: Customer Success | C13: 6257 | D13: 8272 | E13: =IFERROR((D13-C13)/C13,"") -> 0.32203932 | F13: 22244 | G13: 28467 | H13: =IFERROR((G13-F13)/F13,"") -> 0.27976083 | I13: 1926 | J13: 2897 | K13: =IFERROR((J13-I13)/I13,"") -> 0.50415369 | L13: 9250 | M13: Apr 2026 | N13: 11653 | O13: Dec 2021 | P13: =IFERROR((D13-N13)/N13,"") -> -0.29013988 | Q13: Growth then Pullback | R13: Winner | S13: Traffic grew steadily through the study window, reaching a peak in April 2026 before pulling back modestly by June 2026. Traffic value and referring domains also increased. The historical peak occurred before the study window (December 2021).
A14: EverAfter | B14: Customer Success | C14: 1542 | D14: 1443 | E14: =IFERROR((D14-C14)/C14,"") -> -0.064202335 | F14: 1486 | G14: 3521 | H14: =IFERROR((G14-F14)/F14,"") -> 1.3694482 | I14: 289 | J14: 423 | K14: =IFERROR((J14-I14)/I14,"") -> 0.46366782 | L14: 1542 | M14: Jan 2025 | N14: 2594 | O14: May 2024 | P14: =IFERROR((D14-N14)/N14,"") -> -0.44371627 | Q14: Steady Decline | R14: Flat | S14: Organic traffic declined gradually throughout the study window after entering at its highest study-window level. Despite the modest traffic decline, traffic value more than doubled and referring domains increased steadily. The historical peak occurred before the study window (May 2024).
E15: =IFERROR((D15-C15)/C15,"") | H15: =IFERROR((G15-F15)/F15,"") | K15: =IFERROR((J15-I15)/I15,"") | P15: =IFERROR((D15-N15)/N15,"")
E16: =IFERROR((D16-C16)/C16,"") | H16: =IFERROR((G16-F16)/F16,"") | K16: =IFERROR((J16-I16)/I16,"") | P16: =IFERROR((D16-N16)/N16,"")
E17: =IFERROR((D17-C17)/C17,"") | H17: =IFERROR((G17-F17)/F17,"") | K17: =IFERROR((J17-I17)/I17,"") | P17: =IFERROR((D17-N17)/N17,"")
E18: =IFERROR((D18-C18)/C18,"") | H18: =IFERROR((G18-F18)/F18,"") | K18: =IFERROR((J18-I18)/I18,"") | P18: =IFERROR((D18-N18)/N18,"")
E19: =IFERROR((D19-C19)/C19,"") | H19: =IFERROR((G19-F19)/F19,"") | K19: =IFERROR((J19-I19)/I19,"") | P19: =IFERROR((D19-N19)/N19,"")
E20: =IFERROR((D20-C20)/C20,"") | H20: =IFERROR((G20-F20)/F20,"") | K20: =IFERROR((J20-I20)/I20,"") | P20: =IFERROR((D20-N20)/N20,"")
E21: =IFERROR((D21-C21)/C21,"") | H21: =IFERROR((G21-F21)/F21,"") | K21: =IFERROR((J21-I21)/I21,"") | P21: =IFERROR((D21-N21)/N21,"")
E22: =IFERROR((D22-C22)/C22,"") | H22: =IFERROR((G22-F22)/F22,"") | K22: =IFERROR((J22-I22)/I22,"") | P22: =IFERROR((D22-N22)/N22,"")
E23: =IFERROR((D23-C23)/C23,"") | H23: =IFERROR((G23-F23)/F23,"") | K23: =IFERROR((J23-I23)/I23,"") | P23: =IFERROR((D23-N23)/N23,"")
E24: =IFERROR((D24-C24)/C24,"") | H24: =IFERROR((G24-F24)/F24,"") | K24: =IFERROR((J24-I24)/I24,"") | P24: =IFERROR((D24-N24)/N24,"")
E25: =IFERROR((D25-C25)/C25,"") | H25: =IFERROR((G25-F25)/F25,"") | K25: =IFERROR((J25-I25)/I25,"") | P25: =IFERROR((D25-N25)/N25,"")
E26: =IFERROR((D26-C26)/C26,"") | H26: =IFERROR((G26-F26)/F26,"") | K26: =IFERROR((J26-I26)/I26,"") | P26: =IFERROR((D26-N26)/N26,"")
... E500: =IFERROR((D500-C500)/C500,"") | H500: =IFERROR((G500-F500)/F500,"") | K500: =IFERROR((J500-I500)/I500,"") | P500: =IFERROR((D500-N500)/N500,"")

Sheet Pass 1 Archive
A1: Company Name | B1: Website/Domain | C1: Category | D1: Date Added | E1: Source List | F1: Source URL | G1: Screened By | H1: Screening Date | I1: B2B SaaS Confirmed? | J1: One-Line Description | K1: Founded Year | L1: Public/Private | M1: LinkedIn Employee Count | N1: Employee Count Source/Date | O1: Funding Status / Total Raised | P1: M&A Status | Q1: M&A Notes | R1: Domain Stable During Window? | S1: Primary ICP | T1: Buying Motion | U1: Primary Buyer | V1: Non-Core Asset Flag | W1: Non-Core Asset Notes | X1: Inclusion Decision | Y1: Exclusion Reason | Z1: Selected for Deep Dive? | AA1: Selected for Comparison Group? | AB1: Research Status | AC1: Tags | AD1: Last Updated
A2: Apollo.io | B2: apollo.io | C2: Sales Engagement / Sales Intelligence | D2: 2026-06-26 | E2: G2 | F2: https://www.g2.com/categories/sales-engagement | G2: Claude (S.LAB Research) | H2: 2026-06-26 | I2: Yes | J2: AI-powered sales engagement and intelligence platform (sequencing, dialer, contact database). | K2: 2015 | L2: Private | M2: 1,431 | N2: LinkedIn (cross-checked via job postings/RocketReach), 2026-06-26 — G2 page field showed placeholder '1 employee' DataOps artifact; verified independently | P2: Independent | R2: Yes | X2: Include | AB2: In Progress | AC2: Sourced from both SE and SI G2 category pages. G2 LinkedIn-employee field is a known data artifact for this company; real figure verified independently. | AD2: 2026-06-26
A3: Outreach | B3: outreach.io | C3: Sales Engagement / Sales Intelligence | D3: 2026-06-26 | E3: G2 | F3: https://www.g2.com/categories/sales-engagement | G3: Claude (S.LAB Research) | H3: 2026-06-26 | I3: Yes | J3: Sales engagement platform: multichannel sequencing, dialer, conversation intelligence. | R3: Yes | X3: Include | AB3: In Progress | AC3: Founded year/employee count/M&A status not yet verified this session — flagged for follow-up before Pass 3. | AD3: 2026-06-26
A4: Salesloft | B4: salesloft.com | C4: Sales Engagement / Sales Intelligence | D4: 2026-06-26 | E4: G2 | F4: https://www.g2.com/categories/sales-engagement | G4: Claude (S.LAB Research) | H4: 2026-06-26 | I4: Yes | J4: Sales engagement platform: cadences, dialer, deal/revenue orchestration. | P4: Independent | Q4: Merged with Clari, Dec 2025 (inside study window). Clari's revenue-intelligence/forecasting capability was absorbed into Salesloft; Clari ceases to exist as a standalone entity. Per 2026-06-26 decision, documented here only — no separate Clari row created. | R4: Yes | X4: Include | AB4: In Progress | AC4: Founded year/employee count/M&A status not yet verified this session — flagged for follow-up before Pass 3. | AD4: 2026-06-26
A5: Close | B5: close.com | C5: Sales Engagement / Sales Intelligence | D5: 2026-06-26 | E5: G2 | F5: https://www.g2.com/categories/sales-engagement | G5: Claude (S.LAB Research) | H5: 2026-06-26 | I5: Yes | J5: CRM with built-in calling/email sales engagement, aimed at SMB sales teams. | R5: Yes | X5: Include | AB5: In Progress | AC5: Founded year/employee count/M&A status not yet verified this session — flagged for follow-up before Pass 3. | AD5: 2026-06-26
A6: Amplemarket | B6: amplemarket.com | C6: Sales Engagement / Sales Intelligence | D6: 2026-06-26 | E6: G2 | F6: https://www.g2.com/categories/sales-engagement | G6: Claude (S.LAB Research) | H6: 2026-06-26 | I6: Yes | J6: AI sales platform combining lead sourcing, intelligence, and multichannel outreach. | K6: 2019 | L6: Private | M6: 40 | N6: LinkedIn (cross-checked via RocketReach), 2026-06-26 — G2 page field showed placeholder '1 employee' DataOps artifact; verified independently | P6: Independent | R6: Yes | X6: Include | AB6: In Progress | AC6: G2 LinkedIn-employee field is a known data artifact for this company; real figure verified independently. | AD6: 2026-06-26
A7: lemlist | B7: lemlist.com | C7: Sales Engagement / Sales Intelligence | D7: 2026-06-26 | E7: G2 | F7: https://www.g2.com/categories/sales-engagement | G7: Claude (S.LAB Research) | H7: 2026-06-26 | I7: Yes | J7: Cold email and multichannel sales engagement / outreach automation tool. | R7: Yes | X7: Include | AB7: In Progress | AC7: Founded year/employee count/M&A status not yet verified this session — flagged for follow-up before Pass 3. | AD7: 2026-06-26
A8: Instantly | B8: instantly.ai | C8: Sales Engagement / Sales Intelligence | D8: 2026-06-26 | E8: G2 | F8: https://www.g2.com/categories/sales-intelligence | G8: Claude (S.LAB Research) | H8: 2026-06-26 | I8: Yes | J8: Cold email outreach and deliverability platform for sales engagement. | K8: 2021 | L8: Private | M8: 275 | N8: LinkedIn (per G2), 2026-06-26 | P8: Independent | R8: Yes | X8: Include | AB8: In Progress | AC8: G2's structured 'Year Founded' field showed 2001 (data-entry error); body text and independent search confirm 2021. Confirmed 'Instantly' and 'Instantly.ai' are the same company. | AD8: 2026-06-26
A9: GetAccept | B9: getaccept.com | C9: Sales Engagement / Sales Intelligence | D9: 2026-06-26 | E9: G2 | F9: https://www.g2.com/categories/sales-engagement | G9: Claude (S.LAB Research) | H9: 2026-06-26 | I9: Yes | J9: Sales engagement, digital sales room, and e-signature platform. | R9: Yes | X9: Include | AB9: In Progress | AC9: Founded year/employee count/M&A status not yet verified this session — flagged for follow-up before Pass 3. | AD9: 2026-06-26
A10: Mixmax | B10: mixmax.com | C10: Sales Engagement / Sales Intelligence | D10: 2026-06-26 | E10: G2 | F10: https://www.g2.com/categories/sales-engagement | G10: Claude (S.LAB Research) | H10: 2026-06-26 | I10: Yes | J10: Sales engagement and email productivity platform. | R10: Yes | X10: Include | AB10: In Progress | AC10: Founded year/employee count/M&A status not yet verified this session — flagged for follow-up before Pass 3. | AD10: 2026-06-26
A11: Reply.io | B11: reply.io | C11: Sales Engagement / Sales Intelligence | D11: 2026-06-26 | E11: G2 | F11: https://www.g2.com/categories/sales-engagement | G11: Claude (S.LAB Research) | H11: 2026-06-26 | I11: Yes | J11: Multichannel sales engagement and outreach automation platform. | R11: Yes | X11: Include | AB11: In Progress | AC11: Founded year/employee count/M&A status not yet verified this session — flagged for follow-up before Pass 3. | AD11: 2026-06-26
A12: ZoomInfo (GTM Workspace) | B12: zoominfo.com | C12: Sales Engagement / Sales Intelligence | D12: 2026-06-26 | E12: G2 | F12: https://www.g2.com/categories/sales-intelligence | G12: Claude (S.LAB Research) | H12: 2026-06-26 | I12: Yes | J12: Go-to-market intelligence platform: contact/company data, intent signals. | K12: 2000 | L12: Public | M12: 4,221 | N12: LinkedIn (per G2), 2026-06-26 | P12: Independent | R12: Yes | X12: Include | AB12: In Progress | AC12: Listed on G2 under rebranded product name 'GTM Workspace'; parent company is ZoomInfo Technologies (NASDAQ: ZI). | AD12: 2026-06-26
A13: Cognism | B13: cognism.com | C13: Sales Engagement / Sales Intelligence | D13: 2026-06-26 | E13: G2 | F13: https://www.g2.com/categories/sales-intelligence | G13: Claude (S.LAB Research) | H13: 2026-06-26 | I13: Yes | J13: B2B sales intelligence platform: contact data, intent signals, compliance-focused (EU/UK). | K13: 2015 | L13: Private | M13: 451 | N13: LinkedIn (per G2), 2026-06-26 | P13: Independent | R13: Yes | X13: Include | AB13: In Progress | AD13: 2026-06-26
A14: Seamless.AI | B14: seamless.ai | C14: Sales Engagement / Sales Intelligence | D14: 2026-06-26 | E14: G2 | F14: https://www.g2.com/categories/sales-intelligence | G14: Claude (S.LAB Research) | H14: 2026-06-26 | I14: Yes | J14: Real-time sales lead/contact database and prospecting intelligence platform. | K14: 2015 | L14: Private | P14: Independent | R14: Yes | X14: Include | AB14: In Progress | AC14: Listed on G2 as 'Seamless' (Seamless.AI). Employee count not shown in captured G2 excerpt — flagged for follow-up. | AD14: 2026-06-26
A15: Lusha | B15: lusha.com | C15: Sales Engagement / Sales Intelligence | D15: 2026-06-26 | E15: G2 | F15: https://www.g2.com/categories/sales-intelligence | G15: Claude (S.LAB Research) | H15: 2026-06-26 | I15: Yes | J15: B2B contact and company data / sales intelligence platform. | K15: 2016 | L15: Private | M15: 359-370 | N15: LinkedIn (per G2), 2026-06-26 — range reflects minor source discrepancy | P15: Independent | R15: Yes | X15: Include | AB15: In Progress | AD15: 2026-06-26
A16: RocketReach | B16: rocketreach.co | C16: Sales Engagement / Sales Intelligence | D16: 2026-06-26 | E16: G2 | F16: https://www.g2.com/categories/sales-intelligence | G16: Claude (S.LAB Research) | H16: 2026-06-26 | I16: Yes | J16: Contact-finding and sales intelligence / prospecting database platform. | K16: 2016 | L16: Private | M16: 95 | N16: LinkedIn (per G2), 2026-06-26 | P16: Independent | R16: Yes | X16: Include | AB16: In Progress | AD16: 2026-06-26
A17: Mailshake | B17: mailshake.com | C17: Sales Engagement / Sales Intelligence | D17: 2026-06-26 | E17: G2 | F17: https://www.g2.com/categories/sales-engagement | G17: Claude (S.LAB Research) | H17: 2026-06-26 | I17: Yes | J17: Cold email outreach and sales engagement automation tool for SMB sales teams. | R17: Yes | X17: Pending | AB17: Pending | AC17: Founded year/employee count/M&A status not yet verified this session — flagged for follow-up before Pass 3. Passed all Pass 1 gates; not selected for this round's top 15. Marked Pending — available for future rounds or swaps, per 2026-06-26 decision. | AD17: 2026-06-26
A18: Saleshandy | B18: saleshandy.com | C18: Sales Engagement / Sales Intelligence | D18: 2026-06-26 | E18: G2 | F18: https://www.g2.com/categories/sales-engagement | G18: Claude (S.LAB Research) | H18: 2026-06-26 | I18: Yes | J18: Cold email outreach and sales engagement platform with deliverability tooling. | R18: Yes | X18: Pending | AB18: Pending | AC18: Founded year/employee count/M&A status not yet verified this session — flagged for follow-up before Pass 3. Passed all Pass 1 gates; not selected for this round's top 15. Marked Pending — available for future rounds or swaps, per 2026-06-26 decision. | AD18: 2026-06-26
A19: Wiza | B19: wiza.co | C19: Sales Engagement / Sales Intelligence | D19: 2026-06-26 | E19: G2 | F19: https://www.g2.com/categories/sales-intelligence | G19: Claude (S.LAB Research) | H19: 2026-06-26 | I19: Yes | J19: LinkedIn-based contact/lead extraction and sales intelligence tool. | K19: 2019 | L19: Private | M19: 53 | N19: LinkedIn (per G2), 2026-06-26 | P19: Independent | R19: Yes | X19: Pending | AB19: Pending | AC19: Passed all Pass 1 gates; not selected for this round's top 15. Marked Pending — available for future rounds or swaps, per 2026-06-26 decision. | AD19: 2026-06-26
A20: Skrapp.io | B20: skrapp.io | C20: Sales Engagement / Sales Intelligence | D20: 2026-06-26 | E20: G2 | F20: https://www.g2.com/categories/sales-intelligence | G20: Claude (S.LAB Research) | H20: 2026-06-26 | I20: Yes | J20: Email-finding and B2B lead intelligence tool. | K20: 2019 | L20: Private | M20: 14 | N20: LinkedIn (per G2), 2026-06-26 | P20: Independent | R20: Yes | X20: Pending | AB20: Pending | AC20: Passed all Pass 1 gates; not selected for this round's top 15. Marked Pending — available for future rounds or swaps, per 2026-06-26 decision. | AD20: 2026-06-26
A21: Prospeo.io | B21: prospeo.io | C21: Sales Engagement / Sales Intelligence | D21: 2026-06-26 | E21: G2 | F21: https://www.g2.com/categories/sales-intelligence | G21: Claude (S.LAB Research) | H21: 2026-06-26 | I21: Yes | J21: Email/phone finding and verification tool for sales prospecting. | K21: 2019 | L21: Private | M21: 31 | N21: LinkedIn (per G2), 2026-06-26 | P21: Independent | R21: Yes | X21: Pending | AB21: Pending | AC21: Passed all Pass 1 gates; not selected for this round's top 15. Marked Pending — available for future rounds or swaps, per 2026-06-26 decision. | AD21: 2026-06-26
A22: BookYourData | B22: bookyourdata.com | C22: Sales Engagement / Sales Intelligence | D22: 2026-06-26 | E22: G2 | F22: https://www.g2.com/categories/sales-intelligence | G22: Claude (S.LAB Research) | H22: 2026-06-26 | I22: Yes | J22: B2B contact list and data provider for sales prospecting. | K22: 2015 | L22: Private | M22: 7 | N22: LinkedIn (per G2), 2026-06-26 | P22: Independent | R22: Yes | X22: Pending | AB22: Pending | AC22: Passed all Pass 1 gates; not selected for this round's top 15. Marked Pending — available for future rounds or swaps, per 2026-06-26 decision. | AD22: 2026-06-26
A23: Mr. E by EasyLeadz | B23: easyleadz.com | C23: Sales Engagement / Sales Intelligence | D23: 2026-06-26 | E23: G2 | F23: https://www.g2.com/categories/sales-intelligence | G23: Claude (S.LAB Research) | H23: 2026-06-26 | I23: Yes | J23: Direct-dial / contact-finding sales intelligence tool. | K23: 2016 | L23: Private | M23: 33 | N23: LinkedIn (per G2), 2026-06-26 | P23: Independent | R23: Yes | X23: Pending | AB23: Pending | AC23: Passed all Pass 1 gates; not selected for this round's top 15. Marked Pending — available for future rounds or swaps, per 2026-06-26 decision. | AD23: 2026-06-26
A24: Revenue Grid | B24: revenuegrid.com | C24: Sales Engagement / Sales Intelligence | D24: 2026-06-26 | E24: G2 | F24: https://www.g2.com/categories/sales-engagement | G24: Claude (S.LAB Research) | H24: 2026-06-26 | I24: Yes | J24: Sales engagement and revenue intelligence / guided-selling platform. | R24: Yes | X24: Pending | AB24: Pending | AC24: Founded year/employee count/M&A status not yet verified this session — flagged for follow-up before Pass 3. Passed all Pass 1 gates; not selected for this round's top 15. Marked Pending — available for future rounds or swaps, per 2026-06-26 decision. | AD24: 2026-06-26
A25: 6sense (Sales Intelligence) | B25: 6sense.com | C25: Sales Engagement / Sales Intelligence | D25: 2026-06-26 | E25: G2 | F25: https://www.g2.com/categories/sales-intelligence | G25: Claude (S.LAB Research) | H25: 2026-06-26 | I25: Yes | J25: Account-based intent and sales intelligence platform. | K25: 2013 | L25: Private | M25: 1,576 | N25: LinkedIn (per G2), 2026-06-26 | P25: Independent | R25: Yes | X25: Pending | AB25: Pending | AC25: Passed all Pass 1 gates; not selected for this round's top 15. Marked Pending — available for future rounds or swaps, per 2026-06-26 decision. | AD25: 2026-06-26
A26: Gong | B26: gong.io | C26: Sales Engagement / Sales Intelligence | D26: 2026-06-26 | E26: G2 | F26: https://www.g2.com/categories/sales-engagement | G26: Claude (S.LAB Research) | H26: 2026-06-26 | I26: Yes | J26: Revenue / conversation intelligence platform (call recording, deal insights). | R26: Yes | X26: Pending | AB26: Pending | AC26: Founded year/employee count/M&A status not yet verified this session — flagged for follow-up before Pass 3. Category fit borderline — conversation/revenue intelligence, adjacent to but distinct from contact-data sales intelligence (ZoomInfo/Apollo/Cognism style). Passed all Pass 1 gates; not selected for this round's top 15. Marked Pending — available for future rounds or swaps, per 2026-06-26 decision. | AD26: 2026-06-26
A27: Nooks | B27: nooks.ai | C27: Sales Engagement / Sales Intelligence | D27: 2026-06-26 | E27: G2 | F27: https://www.g2.com/categories/sales-engagement | G27: Claude (S.LAB Research) | H27: 2026-06-26 | I27: Yes | J27: AI-powered sales engagement: parallel dialer and virtual sales floor platform. | R27: Yes | X27: Pending | AB27: Pending | AC27: Founded year/employee count/M&A status not yet verified this session — flagged for follow-up before Pass 3. CONFLICT OF INTEREST FLAG: Nooks is an existing S.LAB client (case study at /case-studies/nooks-aeo). Passed all Pass 1 screening gates on the merits. Marked Pending rather than Include/Exclude per 2026-06-26 decision — requires explicit go/no-go before any use in deep-dive or comparison work. | AD27: 2026-06-26
A28: Agentforce Sales (Salesforce) | B28: salesforce.com | C28: Sales Engagement / Sales Intelligence | D28: 2026-06-26 | E28: G2 | F28: https://www.g2.com/categories/sales-engagement | G28: Claude (S.LAB Research) | H28: 2026-06-26 | I28: Yes | J28: AI sales agent / Sales Cloud module within the broader Salesforce CRM platform. | R28: Yes | X28: Exclude | Y28: Gate 4 fail — category fit weak. Core product is a module within Salesforce's broader CRM platform, not a standalone sales engagement product (cf. Outreach/Salesloft). | AB28: Complete | AC28: Founded year/employee count/M&A status not yet verified this session — flagged for follow-up before Pass 3. | AD28: 2026-06-26
A29: HubSpot Sales Hub | B29: hubspot.com | C29: Sales Engagement / Sales Intelligence | D29: 2026-06-26 | E29: G2 | F29: https://www.g2.com/categories/sales-engagement | G29: Claude (S.LAB Research) | H29: 2026-06-26 | I29: Yes | J29: Sales engagement module within HubSpot's broader marketing/sales/service suite. | R29: Yes | X29: Exclude | Y29: Gate 4 fail — category fit weak. Sales Hub is one module within HubSpot's broader platform, not a standalone sales engagement product. | AB29: Complete | AC29: Founded year/employee count/M&A status not yet verified this session — flagged for follow-up before Pass 3. | AD29: 2026-06-26
A30: Zoho CRM | B30: zoho.com/crm | C30: Sales Engagement / Sales Intelligence | D30: 2026-06-26 | E30: G2 | F30: https://www.g2.com/categories/sales-engagement | G30: Claude (S.LAB Research) | H30: 2026-06-26 | I30: Yes | J30: Horizontal CRM product within the broader Zoho One business suite. | R30: Yes | X30: Exclude | Y30: Gate 4 fail — category fit weak. Core product is a horizontal CRM within the broader Zoho suite, not a standalone sales engagement/intelligence product. | AB30: Complete | AC30: Founded year/employee count/M&A status not yet verified this session — flagged for follow-up before Pass 3. | AD30: 2026-06-26
A31: Bigin by Zoho CRM | B31: zoho.com/bigin | C31: Sales Engagement / Sales Intelligence | D31: 2026-06-26 | E31: G2 | F31: https://www.g2.com/categories/sales-engagement | G31: Claude (S.LAB Research) | H31: 2026-06-26 | I31: Yes | J31: Lightweight CRM product within the broader Zoho suite, aimed at small businesses. | R31: Yes | X31: Exclude | Y31: Gate 4 fail — category fit weak. Lightweight CRM module of the Zoho suite, not a standalone sales engagement product. | AB31: Complete | AC31: Founded year/employee count/M&A status not yet verified this session — flagged for follow-up before Pass 3. | AD31: 2026-06-26
A32: ActiveCampaign | B32: activecampaign.com | C32: Sales Engagement / Sales Intelligence | D32: 2026-06-26 | E32: G2 | F32: https://www.g2.com/categories/sales-engagement | G32: Claude (S.LAB Research) | H32: 2026-06-26 | I32: Yes | J32: Email marketing automation platform with bundled CRM/sales features. | R32: Yes | X32: Exclude | Y32: Gate 4 fail — category fit weak. Core product is email marketing automation; sales/CRM features are a bundled add-on, not the core product. | AB32: Complete | AC32: Founded year/employee count/M&A status not yet verified this session — flagged for follow-up before Pass 3. | AD32: 2026-06-26
A33: LinkedIn Sales Navigator | B33: linkedin.com | C33: Sales Engagement / Sales Intelligence | D33: 2026-06-26 | E33: G2 | F33: https://www.g2.com/categories/sales-intelligence | G33: Claude (S.LAB Research) | H33: 2026-06-26 | I33: Yes | J33: Prospecting and sales intelligence tool bundled into the LinkedIn platform. | K33: 2003 | L33: Private (Microsoft-owned) | M33: 23,847 | N33: LinkedIn (per G2), 2026-06-26 | P33: Acquired | Q33: Owned by Microsoft since 2016 acquisition of LinkedIn. | R33: Yes | X33: Exclude | Y33: Gate 1 fail — primary business is not B2B SaaS. LinkedIn's primary business is a professional social network; Sales Navigator is one product line within a company owned by Microsoft, not a standalone B2B SaaS company. | AB33: Complete | AD33: 2026-06-26
A34: Microsoft Relationship Sales | B34: microsoft.com | C34: Sales Engagement / Sales Intelligence | D34: 2026-06-26 | E34: G2 | F34: https://www.g2.com/categories/sales-intelligence | G34: Claude (S.LAB Research) | H34: 2026-06-26 | I34: Yes | J34: Bundled LinkedIn Sales Navigator + Dynamics 365 sales product line. | K34: 1975 | L34: Public | M34: 231,632 | N34: LinkedIn (per G2), 2026-06-26 | P34: Independent | R34: Yes | X34: Exclude | Y34: Gate 1 fail — primary business is not B2B SaaS. Microsoft is a diversified technology conglomerate (OS, cloud infrastructure, hardware, gaming, productivity); Relationship Sales is a bundled product line, not the company's core/primary business. | AB34: Complete | AD34: 2026-06-26
A35: LinkedIn Sales Insights | B35: linkedin.com | C35: Sales Engagement / Sales Intelligence | D35: 2026-06-26 | E35: G2 | F35: https://www.g2.com/categories/sales-intelligence | G35: Claude (S.LAB Research) | H35: 2026-06-26 | I35: Yes | J35: Sales analytics product bundled into the LinkedIn platform; discontinued Dec 31, 2024. | P35: Acquired | Q35: Owned by Microsoft since 2016 acquisition of LinkedIn. | R35: Yes | X35: Exclude | Y35: Gate 1 and Gate 3 fail — primary business not B2B SaaS (see LinkedIn Sales Navigator), and product was discontinued Dec 31, 2024, before the study window (Jan 2025–Jun 2026) began — fully inactive for the entire window. | AB35: Complete | AC35: Per G2's own page text, product was discontinued Dec 31, 2024. | AD35: 2026-06-26
A36: DealHub | B36: dealhub.io | C36: Sales Engagement / Sales Intelligence | D36: 2026-06-26 | E36: G2 | F36: https://www.g2.com/categories/sales-engagement | G36: Claude (S.LAB Research) | H36: 2026-06-26 | I36: Yes | J36: CPQ (configure-price-quote) and deal management platform. | R36: Yes | X36: Exclude | Y36: Gate 4 fail — category fit weak. Core product is CPQ/deal management, not sales engagement or sales intelligence. | AB36: Complete | AC36: Founded year/employee count/M&A status not yet verified this session — flagged for follow-up before Pass 3. | AD36: 2026-06-26
A37: Seismic Enablement Cloud | B37: seismic.com | C37: Sales Engagement / Sales Intelligence | D37: 2026-06-26 | E37: G2 | F37: https://www.g2.com/categories/sales-engagement | G37: Claude (S.LAB Research) | H37: 2026-06-26 | I37: Yes | J37: Sales enablement and content management platform. | R37: Yes | X37: Exclude | Y37: Gate 4 fail — category fit weak. Core product is sales enablement/content management, a distinct category from sales engagement (cadence/sequencing) or sales intelligence (contact/intent data). | AB37: Complete | AC37: Founded year/employee count/M&A status not yet verified this session — flagged for follow-up before Pass 3. | AD37: 2026-06-26
A38: CaptivateIQ | B38: captivateiq.com | C38: Sales Engagement / Sales Intelligence | D38: 2026-06-26 | E38: G2 | F38: https://www.g2.com/categories/sales-intelligence | G38: Claude (S.LAB Research) | H38: 2026-06-26 | I38: Yes | J38: Sales compensation / SPM (commission management) platform. | K38: 2017 | L38: Private | M38: 271 | N38: LinkedIn (per G2), 2026-06-26 | P38: Independent | R38: Yes | X38: Exclude | Y38: Gate 4 fail — wrong category entirely. Core product is sales compensation/SPM (commission management), not sales engagement or sales intelligence. | AB38: Complete | AD38: 2026-06-26
A39: D&B Hoovers | B39: dnb.com | C39: Sales Engagement / Sales Intelligence | D39: 2026-06-26 | E39: G2 | F39: https://www.g2.com/categories/sales-intelligence | G39: Claude (S.LAB Research) | H39: 2026-06-26 | I39: Yes | J39: Sales intelligence and business data platform (Dun & Bradstreet). | L39: Private (post take-private) | M39: 5,747 | N39: LinkedIn (per G2), 2026-06-26 | P39: Acquired | Q39: Parent company Dun & Bradstreet taken private by Clearlake Capital, $7.7B, deal closed Aug 26, 2025 (inside study window: Jan 2025–Jun 2026); NYSE delisting. | R39: Yes | X39: Exclude | Y39: Gate 2/3 fail — recent, disruptive M&A event inside the study window per manual's M&A treatment rule; no clean continuous ownership/attribution story available. | AB39: Complete | AC39: G2 page lists 'Ownership: NYSE: DNB' — outdated as of Aug 2025 take-private. Verify independently if revisited. | AD39: 2026-06-26
A40: Klaviyo | B40: klaviyo.com | C40: Marketing Automation | D40: 2026-06-26 | E40: G2 | F40: https://www.g2.com/categories/marketing-automation | G40: Claude (S.LAB Research) | H40: 2026-06-26 | I40: Yes | J40: Email/SMS marketing automation and customer data platform built for ecommerce brands. | L40: Public (NYSE: KVYO) | O40: Public company; IPO Sept 2023 | P40: Independent | Q40: Acquired Gatsby (social automation), Aug 14, 2025 — Klaviyo as acquirer; not disruptive to Klaviyo itself. | R40: Yes | X40: Include | AB40: In Progress | AC40: LOCKED — Marketing Automation vertical (15). Founded year and employee count not verified this session — flag for follow-up before Pass 2. | AD40: 2026-06-26
A41: Braze | B41: braze.com | C41: Marketing Automation | D41: 2026-06-26 | E41: G2 | F41: https://www.g2.com/categories/marketing-automation | G41: Claude (S.LAB Research) | H41: 2026-06-26 | I41: Yes | J41: Cross-channel customer engagement platform (push, email, SMS, in-app) for marketing automation. | L41: Public (NASDAQ: BRZE) | O41: Public company | P41: Independent | Q41: Acquired OfferFit ($325M, cash + stock), completed June 2, 2025 — Braze as acquirer; not disruptive to Braze itself. | R41: Yes | X41: Include | AB41: In Progress | AC41: LOCKED — Marketing Automation vertical (15). Founded year and employee count not verified this session — flag for follow-up before Pass 2. | AD41: 2026-06-26
A42: HubSpot Marketing Hub | B42: hubspot.com | C42: Marketing Automation | D42: 2026-06-26 | E42: G2 | F42: https://www.g2.com/categories/marketing-automation | G42: Claude (S.LAB Research) | H42: 2026-06-26 | I42: Yes | J42: Marketing automation product line (email, landing pages, workflows, lead nurturing) within the HubSpot platform. | L42: Public (NYSE: HUBS) | O42: Public company | P42: Independent | R42: Yes | V42: Yes | W42: Part of HubSpot's broader CRM platform, but core product function matches the category (unlike Sales Hub in the Sales Engagement vertical). | X42: Include | AB42: In Progress | AC42: LOCKED — Marketing Automation vertical (15). Gate-4 judgment note: unlike HubSpot Sales Hub (excluded from Sales Engagement vertical as a generic CRM module), Marketing Hub's core function IS marketing automation/email — this is the company's original, namesake product line, not an adjacent bundled module. Founded year/employee count not verified this session. | AD42: 2026-06-26
A43: ActiveCampaign | B43: activecampaign.com | C43: Marketing Automation | D43: 2026-06-26 | E43: G2 | F43: https://www.g2.com/categories/marketing-automation | G43: Claude (S.LAB Research) | H43: 2026-06-26 | I43: Yes | J43: Email marketing automation and CRM platform for small and mid-sized businesses. | R43: Yes | X43: Include | AB43: In Progress | AC43: LOCKED — Marketing Automation vertical (15). Cross-vertical reassignment: excluded from Sales Engagement/Sales Intelligence vertical (2026-06-26) on Gate 4 grounds because its core product is marketing automation, not sales engagement. Per user decision (one company, one best-fit category), it is included here instead, where Marketing Automation is its correct primary category. M&A/employee count not verified this session — flag for follow-up before Pass 2. | AD43: 2026-06-26
A44: Customer.io | B44: customer.io | C44: Marketing Automation | D44: 2026-06-26 | E44: G2 | F44: https://www.g2.com/categories/marketing-automation | G44: Claude (S.LAB Research) | H44: 2026-06-26 | I44: Yes | J44: Customer messaging and marketing automation platform for product-led growth companies. | L44: Private | O44: $40.3M total raised across 6 rounds; $690M valuation set in 2022 Series A ($35M) | P44: Independent | Q44: Acquired Parcel (productivity/business software), Aug 23, 2022 — Customer.io as acquirer; not disruptive. Reported $100M ARR as of Sept 2025 (revenue metric, not funding). | R44: Yes | X44: Include | AB44: In Progress | AC44: LOCKED — Marketing Automation vertical (15). Founded year/employee count not verified this session — flag for follow-up before Pass 2. | AD44: 2026-06-26
A45: Omnisend | B45: omnisend.com | C45: Marketing Automation | D45: 2026-06-26 | E45: G2 | F45: https://www.g2.com/categories/marketing-automation | G45: Claude (S.LAB Research) | H45: 2026-06-26 | I45: Yes | J45: Email and SMS marketing automation platform for ecommerce brands. | L45: Private | O45: $1.57M total raised, single round (Dec 18, 2019) — minimal external VC funding, bootstrapped-leaning | P45: Independent | R45: Yes | X45: Include | AB45: In Progress | AC45: LOCKED — Marketing Automation vertical (15). Founded year/employee count not verified this session — flag for follow-up before Pass 2. | AD45: 2026-06-26
A46: Attentive | B46: attentive.com | C46: Marketing Automation | D46: 2026-06-26 | E46: G2 | F46: https://www.g2.com/categories/marketing-automation | G46: Claude (S.LAB Research) | H46: 2026-06-26 | I46: Yes | J46: SMS and email marketing platform for ecommerce and retail brands. | L46: Private | O46: $922M total raised | P46: Independent | Q46: Acquired Yotpo's email and SMS marketing customer base, Aug 6, 2025 — Attentive as acquirer (Yotpo exited the category and laid off ~200 staff); not disruptive to Attentive itself. | R46: Yes | X46: Include | AB46: In Progress | AC46: LOCKED — Marketing Automation vertical (15). Founded year/employee count not verified this session — flag for follow-up before Pass 2. | AD46: 2026-06-26
A47: Iterable | B47: iterable.com | C47: Marketing Automation | D47: 2026-06-26 | E47: G2 | F47: https://www.g2.com/categories/marketing-automation | G47: Claude (S.LAB Research) | H47: 2026-06-26 | I47: Yes | J47: Cross-channel customer engagement and marketing automation platform. | K47: 2013 | L47: Private | M47: 867 | N47: Tracxn (LinkedIn-sourced), as of 2026-04-30 | O47: $343M total raised; $200M Series E, June 15, 2021 | P47: Independent | Q47: No acquisitions made or received as of this screening. | R47: Yes | X47: Include | AB47: In Progress | AC47: LOCKED — Marketing Automation vertical (15). | AD47: 2026-06-26
A48: Brevo | B48: brevo.com | C48: Marketing Automation | D48: 2026-06-26 | E48: G2 | F48: https://www.g2.com/categories/email-marketing | G48: Claude (S.LAB Research) | H48: 2026-06-26 | I48: Yes | J48: Customer engagement platform (email, SMS, CRM) for SMBs; formerly Sendinblue, rebranded 2022. | L48: Private (unicorn, 2025) | M48: 898 | N48: LinkedIn (per G2), 2026-06-26 | O48: €500M (~$583M) round in 2025 led by General Atlantic and Oakley Capital; valuation exceeds $1B | P48: Independent | Q48: Acquired Cohort, Sept 17, 2025 — Brevo as acquirer; not disruptive. Note: rebranded from "Sendinblue" to "Brevo" in 2022 — same legal entity, not an M&A event. | R48: Yes | X48: Include | AB48: In Progress | AC48: LOCKED — Marketing Automation vertical (15). Founded year not verified this session. | AD48: 2026-06-26
A49: Insider | B49: useinsider.com | C49: Marketing Automation | D49: 2026-06-26 | E49: G2 | F49: https://www.g2.com/categories/marketing-automation | G49: Claude (S.LAB Research) | H49: 2026-06-26 | I49: Yes | J49: AI-native omnichannel customer engagement and personalization platform. | K49: 2012 | L49: Private | O49: $771M total raised; $500M Series E led by General Atlantic (Oct 2024) | P49: Independent | Q49: No acquisitions found. | R49: Yes | X49: Include | AB49: In Progress | AC49: LOCKED — Marketing Automation vertical (15). G2 product listing name is 'Insider One'; company/brand is 'Insider' (useinsider.com). Company press materials cite ~1,100+ team members, but this is not an independently confirmed LinkedIn company-page figure — left blank pending verification rather than recording an unconfirmed number. | AD49: 2026-06-26
A50: CleverTap | B50: clevertap.com | C50: Marketing Automation | D50: 2026-06-26 | E50: G2 | F50: https://www.g2.com/categories/marketing-automation | G50: Claude (S.LAB Research) | H50: 2026-06-26 | I50: Yes | J50: Customer engagement and retention platform (push, in-app, email, web) with CDP capabilities. | L50: Private | M50: 472 | N50: Tracxn (LinkedIn-sourced), as of 2025-04-30 | O50: $303M total raised per one source ($182M over 8 rounds per another — sources disagree, flagging both) | P50: Independent | Q50: Acquired Rehook.ai, Apr 15, 2025, and Leanplum (2022) — CleverTap as acquirer in both cases. ~60-70 Leanplum-origin staff laid off in 2025 during integration (operating note, not disruptive to CleverTap continuity). | R50: Yes | X50: Include | AB50: In Progress | AC50: LOCKED — Marketing Automation vertical (15). Founded year not verified this session. Funding total figure disagreement between sources — disclosed, not resolved. | AD50: 2026-06-26
A51: GetResponse | B51: getresponse.com | C51: Marketing Automation | D51: 2026-06-26 | E51: G2 | F51: https://www.g2.com/categories/marketing-automation | G51: Claude (S.LAB Research) | H51: 2026-06-26 | I51: Yes | J51: Email marketing and marketing automation platform with lifecycle/CRM features. | K51: 1998 | L51: Private | M51: 428 | N51: LinkedIn (per G2), 2026-06-26 | P51: Independent | Q51: No acquisitions found. HQ: Poland. | R51: Yes | X51: Include | AB51: In Progress | AC51: LOCKED — Marketing Automation vertical (15). Sourced from both Marketing Automation and Email Marketing G2 category pages. | AD51: 2026-06-26
A52: ContactPigeon | B52: contactpigeon.com | C52: Marketing Automation | D52: 2026-06-26 | E52: G2 | F52: https://www.g2.com/categories/marketing-automation | G52: Claude (S.LAB Research) | H52: 2026-06-26 | I52: Yes | J52: Omnichannel customer engagement and marketing automation platform for ecommerce/retail. | K52: 2014 | L52: Private | P52: Independent | Q52: No acquisitions found. HQ: Athens, Greece (registered HQ New York, US). | R52: Yes | X52: Include | AB52: In Progress | AC52: LOCKED — Marketing Automation vertical (15). Employee count sources disagreed/imprecise (e.g., "51-100" for one office location only) — left blank rather than recording an unconfirmed figure; flag for follow-up. | AD52: 2026-06-26
A53: MailerLite | B53: mailerlite.com | C53: Marketing Automation | D53: 2026-06-26 | E53: G2 | F53: https://www.g2.com/categories/email-marketing | G53: Claude (S.LAB Research) | H53: 2026-06-26 | I53: Yes | J53: Email marketing and automation platform for creators and small businesses. | K53: 2010 | L53: Private | M53: 168 | N53: LinkedIn (per G2), 2026-06-26 | P53: Independent | Q53: No acquisitions found. HQ: San Francisco, CA (Lithuania origin). | R53: Yes | X53: Include | AB53: In Progress | AC53: LOCKED — Marketing Automation vertical (15). | AD53: 2026-06-26
A54: Flodesk | B54: flodesk.com | C54: Marketing Automation | D54: 2026-06-26 | E54: G2 | F54: https://www.g2.com/categories/email-marketing | G54: Claude (S.LAB Research) | H54: 2026-06-26 | I54: Yes | J54: Email marketing platform for small businesses and creators with brand-first design tools. | K54: 2018 | L54: Private | M54: 88 | N54: LinkedIn (per G2), 2026-06-26 | O54: Bootstrapped, no external funding; $36M+ ARR, profitable since second week after launch | P54: Independent | Q54: No acquisitions found. HQ: San Francisco, CA. | R54: Yes | X54: Include | AB54: In Progress | AC54: LOCKED — Marketing Automation vertical (15). G2 page shows a discrepancy: long-form description says 'Founded in 2019,' but the structured 'Year Founded' field says 2018 — used the structured field (2018) per established standardization practice, flagging the discrepancy. | AD54: 2026-06-26
A55: Bloomreach | B55: bloomreach.com | C55: Marketing Automation | D55: 2026-06-26 | E55: G2 | F55: https://www.g2.com/categories/marketing-automation | G55: Claude (S.LAB Research) | H55: 2026-06-26 | I55: Yes | J55: Ecommerce-focused marketing automation and customer data platform with AI-driven personalization. | K55: 2009 | L55: Private | O55: $422M total raised; $2.2B valuation following $175M round led by Goldman Sachs Asset Management (2022) | P55: Independent | Q55: Acquired Exponea (CDP/marketing automation) and Radiance Commerce (Jan 2024) as acquirer — exact Exponea acquisition date not verified this session. No acquisitions in 2025 per available sources. | R55: Yes | X55: Pending | AB55: Pending | AC55: PENDING alternate — Marketing Automation vertical. Employee count not verified this session. | AD55: 2026-06-26
A56: Mailchimp (Intuit Mailchimp) | B56: mailchimp.com | C56: Marketing Automation | D56: 2026-06-26 | E56: G2 | F56: https://www.g2.com/categories/marketing-automation | G56: Claude (S.LAB Research) | H56: 2026-06-26 | I56: Yes | J56: All-in-one email marketing and marketing automation platform for small businesses. | K56: 2001 | L56: Private subsidiary of Intuit (public parent, NASDAQ: INTU) | M56: 1,553 | N56: LinkedIn (per G2, Email Marketing category listing), 2026-06-26 | P56: Acquired (continuous) | Q56: Acquired by Intuit — announced Sept 13, 2021 (~$12B), closed end of Jan 2022. Well before the Jan 2025 study window; continuous integration since. Per manual calibration, include-with-flag (not exclude) — pre-window, well-documented, continuous. | R56: Yes | V56: Yes | W56: Intuit's primary business is broader financial software (TurboTax, QuickBooks); Mailchimp is a major acquired, non-core product line. | X56: Pending | AB56: Pending | AC56: PENDING alternate — Marketing Automation vertical. Sourced from both Marketing Automation ("All-in-One Marketing Platform") and Email Marketing ("Email Marketing") G2 listings — same underlying product/company. | AD56: 2026-06-26
A57: Dotdigital | B57: dotdigital.com | C57: Marketing Automation | D57: 2026-06-26 | E57: G2 | F57: https://www.g2.com/categories/marketing-automation | G57: Claude (S.LAB Research) | H57: 2026-06-26 | I57: Yes | J57: Cross-channel marketing automation platform (email, SMS, and more) for ecommerce/retail. | K57: 1999 | L57: Public (LSE: DOTD) | M57: 465 | N57: LinkedIn (per G2 Email Marketing page's structured field), 2026-06-26 | P57: Independent | Q57: M&A status not explicitly verified this session — flag for follow-up before Pass 2. | R57: Yes | X57: Pending | AB57: Pending | AC57: PENDING alternate — Marketing Automation vertical. Formerly Dotmailer. Sourced from both Marketing Automation and Email Marketing G2 pages. Minor employee-count discrepancy: company's own description text says '450+', G2's structured LinkedIn field says 465 — used 465 per standard practice of trusting the structured field. | AD57: 2026-06-26
A58: Adobe Marketo Engage | B58: marketo.com | C58: Marketing Automation | D58: 2026-06-26 | E58: G2 | F58: https://www.g2.com/categories/marketing-automation | G58: Claude (S.LAB Research) | H58: 2026-06-26 | I58: Yes | J58: Enterprise B2B marketing automation platform (lead management, campaign orchestration). | L58: Subsidiary of Adobe (public parent, NASDAQ: ADBE) | P58: Acquired (continuous) | Q58: Acquired by Adobe, Oct 31, 2018 (~$4.74B cash); Adobe itself had acquired Marketo from Vista Equity Partners (which bought it May 2016). Well before the study window; continuous integration since as "Marketo Engage" within Adobe Experience/Marketing Cloud. Per manual calibration, include-with-flag. | R58: Yes | V58: Yes | W58: Adobe's primary business is broader creative/digital-experience software; Marketo Engage is one component within Adobe Experience Cloud, though its core function is still marketing automation (Gate 4 pass). | X58: Pending | AB58: Pending | AC58: PENDING alternate — Marketing Automation vertical. Founded year and employee count not verified this session. | AD58: 2026-06-26
A59: Agentforce Marketing (Salesforce Marketing Cloud) | B59: salesforce.com | C59: Marketing Automation | D59: 2026-06-26 | E59: G2 | F59: https://www.g2.com/categories/marketing-automation | G59: Claude (S.LAB Research) | H59: 2026-06-26 | I59: Yes | J59: Enterprise marketing automation and cross-channel engagement platform; renamed from "Salesforce Marketing Cloud" to "Agentforce Marketing" in 2025. | L59: Subsidiary product of Salesforce (public parent, NYSE: CRM) | P59: Independent | Q59: No ownership change — internal product rebrand announced at Dreamforce 2025 (part of Salesforce dropping the "Cloud" naming convention fleet-wide in favor of "Agentforce"). Underlying product traces to the ExactTarget acquisition (2013), well before the study window. | R59: Yes | V59: Yes | W59: Salesforce's primary business is broad CRM platform; Agentforce Marketing is one of several Agentforce-branded product lines, though its core function is still marketing automation (Gate 4 pass). | X59: Pending | AB59: Pending | AC59: PENDING alternate — Marketing Automation vertical. Founded year and employee count not verified this session. 2025 rebrand is a renaming, not an M&A event. | AD59: 2026-06-26
A60: EngageBay | B60: engagebay.com | C60: Marketing Automation | D60: 2026-06-26 | E60: G2 | F60: https://www.g2.com/categories/marketing-automation | G60: Claude (S.LAB Research) | H60: 2026-06-26 | I60: Yes | J60: All-in-one marketing, sales, and support CRM software for small businesses. | L60: Private, bootstrapped | M60: 28 | N60: As of 2025-07-31 (source citing company-reported headcount; down 41% YoY) | O60: No external funding reported | P60: Independent | Q60: No acquisitions found. | R60: Yes | X60: Pending | AB60: Pending | AC60: PENDING alternate — Marketing Automation vertical. Headcount decline noted as an operating trend; not a gate factor since employee count is metadata-only per manual V1.1. | AD60: 2026-06-26
A61: Constant Contact | B61: constantcontact.com | C61: Marketing Automation | D61: 2026-06-26 | E61: G2 | F61: https://www.g2.com/categories/email-marketing | G61: Claude (S.LAB Research) | H61: 2026-06-26 | I61: Yes | J61: Email marketing and digital marketing platform for small businesses. | K61: 1995 | L61: Private, PE-owned (Clearlake Capital Group) | M61: 1,147 | N61: LinkedIn (per G2), 2026-06-26 | O61: New Clearlake-managed strategic investment closed Oct 7, 2025 (capital raise, not ownership change) | P61: Independent (continuous PE ownership) | Q61: Majority-owned by Clearlake Capital since early 2024; previously a Clearlake/Siris Capital joint venture spun out of Endurance International Group in 2021 — continuous ownership, not a disruptive event inside the window. Acquired Moosend, June 6, 2025, as acquirer (see Moosend exclusion row). | R61: Yes | X61: Pending | AB61: Pending | AC61: PENDING alternate — Marketing Automation vertical. | AD61: 2026-06-26
A62: Sender.net | B62: sender.net | C62: Marketing Automation | D62: 2026-06-26 | E62: G2 | F62: https://www.g2.com/categories/email-marketing | G62: Claude (S.LAB Research) | H62: 2026-06-26 | I62: Yes | J62: Email and SMS marketing automation platform for small businesses. | K62: 2012 | L62: Private | M62: 30 | N62: LinkedIn (per G2), 2026-06-26 | Q62: M&A status not explicitly verified this session — flag for follow-up before Pass 2. | R62: Yes | X62: Pending | AB62: Pending | AC62: PENDING alternate — Marketing Automation vertical. HQ: Vilnius, Lithuania. | AD62: 2026-06-26
A63: Levitate | B63: levitate.ai | C63: Marketing Automation | D63: 2026-06-26 | E63: G2 | F63: https://www.g2.com/categories/email-marketing | G63: Claude (S.LAB Research) | H63: 2026-06-26 | I63: Yes | J63: Relationship-marketing platform for small businesses (personalized email/SMS at scale, client engagement). | K63: 2017 | L63: Private | M63: 432 | N63: LinkedIn (per G2), 2026-06-26 | Q63: M&A status not explicitly verified this session — flag for follow-up before Pass 2. | R63: Yes | X63: Pending | AB63: Pending | AC63: PENDING alternate — Marketing Automation vertical. Founded by Jesse Lipson (creator of ShareFile). HQ: Raleigh, NC. | AD63: 2026-06-26
A64: Systeme.io | B64: systeme.io | C64: Marketing Automation | D64: 2026-06-26 | E64: G2 | F64: https://www.g2.com/categories/email-marketing | G64: Claude (S.LAB Research) | H64: 2026-06-26 | I64: Yes | J64: All-in-one online business platform (funnels, email marketing, courses) for entrepreneurs. | K64: 2017 | L64: Private | M64: 217 | N64: LinkedIn (per G2), 2026-06-26 | Q64: M&A status not explicitly verified this session — flag for follow-up before Pass 2. | R64: Yes | X64: Pending | AB64: Pending | AC64: PENDING alternate — Marketing Automation vertical. HQ: Dublin (Tyrrelstown). | AD64: 2026-06-26
A65: Zoho Campaigns | B65: zoho.com/campaigns | C65: Marketing Automation | D65: 2026-06-26 | E65: G2 | F65: https://www.g2.com/categories/email-marketing | G65: Claude (S.LAB Research) | H65: 2026-06-26 | I65: Yes | J65: Email marketing and automation product within the Zoho suite. | K65: 1996 | L65: Private (Zoho Corp — bootstrapped, never raised VC, never acquired) | M65: 30,766 | N65: LinkedIn (per G2), 2026-06-26 — company-wide Zoho Corp figure, NOT specific to the Campaigns product | P65: Independent | Q65: No acquisitions found for Zoho Corp. | R65: Yes | V65: Yes | W65: Zoho Campaigns is one of dozens of products in Zoho's broad horizontal SaaS suite — flagging for Pass 2 category-fit judgment given how large/diversified the parent suite is. | X65: Pending | AB65: Pending | AC65: PENDING alternate — Marketing Automation vertical. Employee count is a known parent-company-wide figure, not product-specific — same data-confound pattern flagged elsewhere in this project. | AD65: 2026-06-26
A66: Netcore Cloud (Customer Engagement Platform) | B66: netcorecloud.com | C66: Marketing Automation | D66: 2026-06-26 | E66: G2 | F66: https://www.g2.com/categories/marketing-automation | G66: Claude (S.LAB Research) | H66: 2026-06-26 | I66: Yes | J66: AI-powered customer engagement and marketing platform (email, push, in-app, WhatsApp). | L66: Private | Q66: Not verified this session — flag for follow-up before Pass 2. | R66: Yes | X66: Pending | AB66: Pending | AC66: PENDING alternate — Marketing Automation vertical. Consolidated entry: G2 separately lists 'Netcore Customer Engagement Platform' (Marketing Automation page) and 'Netcore Email API' (Email Marketing page) as separate product pages under the same parent company (Netcore Cloud, formerly Netcore Smartech) — kept as one candidate; see Netcore Email API exclusion row. | AD66: 2026-06-26
A67: Evam | B67: evam.com | C67: Marketing Automation | D67: 2026-06-26 | E67: G2 | F67: https://www.g2.com/categories/marketing-automation | G67: Claude (S.LAB Research) | H67: 2026-06-26 | I67: Uncertain — Gate 1 concern | J67: Real-time, cross-channel customer engagement/martech platform; clients include Vodafone, T-Mobile, Turkcell, ING Bank, Garanti BBVA. | X67: Pending | AB67: Pending | AC67: FLAGGED for user decision — Marketing Automation vertical. Gate 1 ambiguity: serves telecom/banking enterprise clients at carrier/bank scale, which is more characteristic of licensed enterprise software or systems-integration-style deployment than confirmed self-serve multi-tenant SaaS. Not enough evidence gathered this session to confirm or rule out B2B SaaS classification — recommend exclude on Gate 1 caution pending confirmation, per standing 'ask if unsure' rule. | AD67: 2026-06-26
A68: Zapier | B68: zapier.com | C68: Marketing Automation | D68: 2026-06-26 | E68: G2 | F68: https://www.g2.com/categories/marketing-automation | G68: Claude (S.LAB Research) | H68: 2026-06-26 | I68: Yes | J68: Workflow/iPaaS automation platform connecting apps via triggers and actions. | R68: Yes | X68: Exclude | Y68: Gate 4 fail — wrong category entirely. Core product is workflow/iPaaS automation connecting apps, not marketing automation or email marketing software, even though marketers use it adjacently. | AB68: Complete | AD68: 2026-06-26
A69: Pipedrive | B69: pipedrive.com | C69: Marketing Automation | D69: 2026-06-26 | E69: G2 | F69: https://www.g2.com/categories/email-marketing | G69: Claude (S.LAB Research) | H69: 2026-06-26 | I69: Yes | J69: Sales CRM with customizable pipelines, used by sales teams to close deals. | K69: 2010 | M69: 1,045 | N69: LinkedIn (per G2), 2026-06-26 | R69: Yes | X69: Exclude | Y69: Gate 4 fail — wrong category entirely. Core product is CRM/sales pipeline management, not email marketing software, despite appearing on G2's Email Marketing category page. | AB69: Complete | AC69: HQ: New York. | AD69: 2026-06-26
A70: GMass | B70: gmass.co | C70: Marketing Automation | D70: 2026-06-26 | E70: G2 | F70: https://www.g2.com/categories/email-marketing | G70: Claude (S.LAB Research) | H70: 2026-06-26 | I70: Yes | J70: Gmail-based mail-merge and cold-outreach automation tool (follow-up sequences, deliverability testing). | K70: 2014 | M70: 12 | N70: LinkedIn (per G2), 2026-06-26 | R70: Yes | X70: Exclude | Y70: Gate 4 fail — better category fit elsewhere. Core function (Gmail-based mail merge, cold-outreach follow-up sequences) matches the Sales Engagement/cold-outreach category (same use case as Instantly/lemlist), not marketing-team email marketing software. Not screened against the Sales Engagement vertical, which is already closed. | AB70: Complete | AC70: HQ: Chicago, IL. | AD70: 2026-06-26
A71: Success.ai | B71: success.ai | C71: Marketing Automation | D71: 2026-06-26 | E71: G2 | F71: https://www.g2.com/categories/email-marketing | G71: Claude (S.LAB Research) | H71: 2026-06-26 | I71: Yes | J71: B2B lead-generation and cold email outreach platform (700M+ contact database, email warm-up, AI writer). | M71: 87 | N71: LinkedIn (per G2), 2026-06-26 | R71: Yes | X71: Exclude | Y71: Gate 4 fail — better category fit elsewhere. Explicitly positioned for B2B lead generation and cold email outreach by sales teams — same category as Instantly/lemlist (Sales Engagement, already a closed vertical), not marketing-team email marketing software. | AB71: Complete | AC71: HQ: Sheridan, WY. | AD71: 2026-06-26
A72: Sendpilot AI | B72: sendpilot.ai | C72: Marketing Automation | D72: 2026-06-26 | E72: G2 | F72: https://www.g2.com/categories/marketing-automation | G72: Claude (S.LAB Research) | H72: 2026-06-26 | I72: Yes | J72: LinkedIn outreach and revenue-management tool (sequence builder, LinkedIn lead database). | R72: Yes | X72: Exclude | Y72: Gate 4 fail — wrong category. Core product is a LinkedIn outreach/sales-engagement tool, not marketing automation or email marketing software. Appears to be a G2 miscategorization/cross-listing. | AB72: Complete | AD72: 2026-06-26
A73: Comarch Marketing Automation | B73: comarch.com | C73: Marketing Automation | D73: 2026-06-26 | E73: G2 | F73: https://www.g2.com/categories/marketing-automation | G73: Claude (S.LAB Research) | H73: 2026-06-26 | I73: No | J73: Marketing automation module within Comarch, a diversified IT solutions provider and systems integrator. | R73: Yes | X73: Exclude | Y73: Gate 1 fail — parent’s primary business is not B2B SaaS. Comarch operates as a diversified IT solutions provider/systems integrator across telecom, banking, ERP, and public-sector verticals, combining SaaS, PaaS, IaaS, and consulting/systems-integration services rather than operating primarily as a B2B SaaS company. | AB73: Complete | AD73: 2026-06-26
A74: Birdeye | B74: birdeye.com | C74: Marketing Automation | D74: 2026-06-26 | E74: G2 | F74: https://www.g2.com/categories/marketing-automation | G74: Claude (S.LAB Research) | H74: 2026-06-26 | I74: Yes | J74: Reputation and review management platform for multi-location brands, with bundled marketing automation features. | R74: Yes | X74: Exclude | Y74: Gate 4 fail — category fit weak. Core/foundational product is online reputation and review management; marketing automation is a secondary capability layered onto that core, not the product's primary function. | AB74: Complete | AD74: 2026-06-26
A75: Instantly | B75: instantly.ai | C75: Marketing Automation | D75: 2026-06-26 | E75: G2 | F75: https://www.g2.com/categories/email-marketing | G75: Claude (S.LAB Research) | H75: 2026-06-26 | I75: Yes | J75: Cold email outreach platform with sending infrastructure and AI-assisted campaigns. | M75: 275 | N75: LinkedIn (per G2), 2026-06-26 | R75: Yes | X75: Exclude | Y75: Already locked to the Sales Engagement/Sales Intelligence vertical per the 2026-06-26 user decision: one company, one best-fit category. Not double-counted here even though it appears on G2’s Email Marketing category page. | AB75: Complete | AC75: G2 structured "Year Founded" field shows 2001 — known recurring data error for this company; actual founding year is 2021 (confirmed independently in the Sales Engagement vertical screening). | AD75: 2026-06-26
A76: lemlist | B76: lemlist.com | C76: Marketing Automation | D76: 2026-06-26 | E76: G2 | F76: https://www.g2.com/categories/email-marketing | G76: Claude (S.LAB Research) | H76: 2026-06-26 | I76: Yes | J76: Cold email and multichannel outreach platform for sales teams. | K76: 2018 | M76: 245 | N76: LinkedIn (per G2), 2026-06-26 | R76: Yes | X76: Exclude | Y76: Already locked to the Sales Engagement/Sales Intelligence vertical per the 2026-06-26 user decision: one company, one best-fit category. Not double-counted here even though it appears on G2’s Email Marketing category page. | AB76: Complete | AC76: Founded year (2018) newly verified via this G2 page — fills a gap left blank in the already-written Sales Engagement Pass 1 Archive row for lemlist; consider backfilling that row. | AD76: 2026-06-26
A77: Moosend | B77: moosend.com | C77: Marketing Automation | D77: 2026-06-26 | E77: G2 | F77: https://www.g2.com/categories/email-marketing | G77: Claude (S.LAB Research) | H77: 2026-06-26 | I77: Yes | J77: Email marketing and automation platform, now owned by Constant Contact. | M77: 1,147 | N77: LinkedIn (per G2) — this is Constant Contact’s (the acquirer’s) company-wide figure, not Moosend-specific | P77: Acquired (recent, in-window) | Q77: Acquired by Constant Contact, June 6, 2025 (from Sitecore) — inside the Jan 2025–Jun 2026 study window. | R77: Yes | X77: Exclude | Y77: Gate 2/3 fail — recent, disruptive M&A event inside the study window. Acquired by Constant Contact, June 6, 2025. Per the manual's M&A calibration default, recent acquisitions inside the window lean toward exclude; Constant Contact (the acquirer) is retained in the pool as the surviving entity. | AB77: Complete | AD77: 2026-06-26
A78: Netcore Email API | B78: netcorecloud.com/email/email-api | C78: Marketing Automation | D78: 2026-06-26 | E78: G2 | F78: https://www.g2.com/categories/email-marketing | G78: Claude (S.LAB Research) | H78: 2026-06-26 | I78: Yes | J78: Cloud-based transactional/marketing email delivery API, a product of Netcore Cloud. | R78: Yes | X78: Exclude | Y78: Duplicate listing — same parent company/product family as Netcore Customer Engagement Platform (Netcore Cloud), which is retained as the consolidated candidate. Email API is one channel/component within Netcore’s broader engagement platform, not a separately screened company. | AB78: Complete | AD78: 2026-06-26
A79: Gainsight | B79: gainsight.com | C79: Customer Success | D79: 2026-06-26 | I79: Yes | J79: Customer success and product experience platform for B2B SaaS companies managing renewals, expansion, and onboarding at scale. | R79: Yes | X79: Include | AB79: Locked (Pass 2) | AC79: BACKFILL — Customer Success vertical (13, locked in Pass 2/Company Tracker). Original Pass 1 gate-screening data (founded year, employee count, funding status, M&A detail, ICP/buying motion) predates the current Pass 1 Archive schema and was not preserved in this workbook. Operating manual V1.2 addendum confirms 13 as the finalized count. Founded year, employee count, funding, and M&A status left blank — verify before Deep Dive selection. | AD79: 2026-06-26
A80: Planhat | B80: planhat.com | C80: Customer Success | D80: 2026-06-26 | I80: Yes | J80: Customer success platform combining health scoring, customer data hub, and revenue analytics for B2B SaaS teams. | R80: Yes | X80: Include | AB80: Locked (Pass 2) | AC80: BACKFILL — Customer Success vertical (13, locked in Pass 2/Company Tracker). Original Pass 1 gate-screening data (founded year, employee count, funding status, M&A detail, ICP/buying motion) predates the current Pass 1 Archive schema and was not preserved in this workbook. Operating manual V1.2 addendum confirms 13 as the finalized count. Founded year, employee count, funding, and M&A status left blank — verify before Deep Dive selection. | AD80: 2026-06-26
A81: ClientSuccess | B81: clientsuccess.com | C81: Customer Success | D81: 2026-06-26 | I81: Yes | J81: Customer success management software focused on health scoring, onboarding, and renewal/expansion tracking for SaaS companies. | R81: Yes | X81: Include | AB81: Locked (Pass 2) | AC81: BACKFILL — Customer Success vertical (13, locked in Pass 2/Company Tracker). Original Pass 1 gate-screening data (founded year, employee count, funding status, M&A detail, ICP/buying motion) predates the current Pass 1 Archive schema and was not preserved in this workbook. Operating manual V1.2 addendum confirms 13 as the finalized count. Founded year, employee count, funding, and M&A status left blank — verify before Deep Dive selection. | AD81: 2026-06-26
A82: Vitally | B82: vitally.io | C82: Customer Success | D82: 2026-06-26 | I82: Yes | J82: Customer success platform built on a customer data hub, combining health scoring, workflows, and analytics for B2B SaaS teams. | R82: Yes | X82: Include | AB82: Locked (Pass 2) | AC82: BACKFILL — Customer Success vertical (13, locked in Pass 2/Company Tracker). Original Pass 1 gate-screening data (founded year, employee count, funding status, M&A detail, ICP/buying motion) predates the current Pass 1 Archive schema and was not preserved in this workbook. Operating manual V1.2 addendum confirms 13 as the finalized count. Founded year, employee count, funding, and M&A status left blank — verify before Deep Dive selection. | AD82: 2026-06-26
A83: Custify | B83: custify.com | C83: Customer Success | D83: 2026-06-26 | I83: Yes | J83: Customer success platform for SaaS companies, providing health scores, automated playbooks, and churn-risk alerts. | R83: Yes | X83: Include | AB83: Locked (Pass 2) | AC83: BACKFILL — Customer Success vertical (13, locked in Pass 2/Company Tracker). Original Pass 1 gate-screening data (founded year, employee count, funding status, M&A detail, ICP/buying motion) predates the current Pass 1 Archive schema and was not preserved in this workbook. Operating manual V1.2 addendum confirms 13 as the finalized count. Founded year, employee count, funding, and M&A status left blank — verify before Deep Dive selection. | AD83: 2026-06-26
A84: Akita | B84: akitaapp.com | C84: Customer Success | D84: 2026-06-26 | I84: Yes | J84: Customer success management platform offering health scoring and customer data integration for SaaS businesses; Dublin-headquartered. | R84: Yes | X84: Include | AB84: Locked (Pass 2) | AC84: BACKFILL — Customer Success vertical (13, locked in Pass 2/Company Tracker). Original Pass 1 gate-screening data (founded year, employee count, funding status, M&A detail, ICP/buying motion) predates the current Pass 1 Archive schema and was not preserved in this workbook. Operating manual V1.2 addendum confirms 13 as the finalized count. Founded year, employee count, funding, and M&A status left blank — verify before Deep Dive selection. | AD84: 2026-06-26
A85: Kapta | B85: kapta.com | C85: Customer Success | D85: 2026-06-26 | I85: Yes | J85: Key account management and customer success software for B2B teams focused on retention and expansion of existing accounts. | R85: Yes | X85: Include | AB85: Locked (Pass 2) | AC85: BACKFILL — Customer Success vertical (13, locked in Pass 2/Company Tracker). Original Pass 1 gate-screening data (founded year, employee count, funding status, M&A detail, ICP/buying motion) predates the current Pass 1 Archive schema and was not preserved in this workbook. Operating manual V1.2 addendum confirms 13 as the finalized count. Founded year, employee count, funding, and M&A status left blank — verify before Deep Dive selection. | AD85: 2026-06-26
A86: ChurnZero | B86: churnzero.com | C86: Customer Success | D86: 2026-06-26 | I86: Yes | J86: Customer success and growth platform providing health scoring, automated engagement, and renewal/upsell workflows for subscription businesses. | R86: Yes | X86: Include | AB86: Locked (Pass 2) | AC86: BACKFILL — Customer Success vertical (13, locked in Pass 2/Company Tracker). Original Pass 1 gate-screening data (founded year, employee count, funding status, M&A detail, ICP/buying motion) predates the current Pass 1 Archive schema and was not preserved in this workbook. Operating manual V1.2 addendum confirms 13 as the finalized count. Founded year, employee count, funding, and M&A status left blank — verify before Deep Dive selection. | AD86: 2026-06-26
A87: UserGuiding | B87: userguiding.com | C87: Customer Success | D87: 2026-06-26 | I87: Yes | J87: No-code product adoption and user onboarding platform used by customer success and product teams to drive activation. | R87: Yes | X87: Include | AB87: Locked (Pass 2) | AC87: BACKFILL — Customer Success vertical (13, locked in Pass 2/Company Tracker). Original Pass 1 gate-screening data (founded year, employee count, funding status, M&A detail, ICP/buying motion) predates the current Pass 1 Archive schema and was not preserved in this workbook. Operating manual V1.2 addendum confirms 13 as the finalized count. Founded year, employee count, funding, and M&A status left blank — verify before Deep Dive selection. | AD87: 2026-06-26
A88: Velaris | B88: velaris.io | C88: Customer Success | D88: 2026-06-26 | I88: Yes | J88: AI-native customer success platform for mid-market and enterprise B2B SaaS teams, covering health scoring, onboarding, renewals, and expansion. | R88: Yes | X88: Include | AB88: Locked (Pass 2) | AC88: BACKFILL — Customer Success vertical (13, locked in Pass 2/Company Tracker). Original Pass 1 gate-screening data (founded year, employee count, funding status, M&A detail, ICP/buying motion) predates the current Pass 1 Archive schema and was not preserved in this workbook. Operating manual V1.2 addendum confirms 13 as the finalized count. Founded year, employee count, funding, and M&A status left blank — verify before Deep Dive selection. | AD88: 2026-06-26
A89: Rocketlane | B89: rocketlane.com | C89: Customer Success | D89: 2026-06-26 | I89: Yes | J89: Customer onboarding and professional services automation platform used by customer success and implementation teams. | R89: Yes | X89: Include | AB89: Locked (Pass 2) | AC89: BACKFILL — Customer Success vertical (13, locked in Pass 2/Company Tracker). Original Pass 1 gate-screening data (founded year, employee count, funding status, M&A detail, ICP/buying motion) predates the current Pass 1 Archive schema and was not preserved in this workbook. Operating manual V1.2 addendum confirms 13 as the finalized count. Founded year, employee count, funding, and M&A status left blank — verify before Deep Dive selection. | AD89: 2026-06-26
A90: Higher Logic | B90: higherlogic.com | C90: Customer Success | D90: 2026-06-26 | I90: Yes | J90: Online community and customer engagement software (including Higher Logic Vanilla) used by customer success teams for self-service and retention. | R90: Yes | X90: Include | AB90: Locked (Pass 2) | AC90: BACKFILL — Customer Success vertical (13, locked in Pass 2/Company Tracker). Original Pass 1 gate-screening data (founded year, employee count, funding status, M&A detail, ICP/buying motion) predates the current Pass 1 Archive schema and was not preserved in this workbook. Operating manual V1.2 addendum confirms 13 as the finalized count. Founded year, employee count, funding, and M&A status left blank — verify before Deep Dive selection. | AD90: 2026-06-26
A91: EverAfter | B91: everafter.ai | C91: Customer Success | D91: 2026-06-26 | I91: Yes | J91: AI-powered digital customer success platform providing a shared customer-facing workspace for onboarding, adoption, and renewal preparation. | R91: Yes | X91: Include | AB91: Locked (Pass 2) | AC91: BACKFILL — Customer Success vertical (13, locked in Pass 2/Company Tracker). Original Pass 1 gate-screening data (founded year, employee count, funding status, M&A detail, ICP/buying motion) predates the current Pass 1 Archive schema and was not preserved in this workbook. Operating manual V1.2 addendum confirms 13 as the finalized count. Founded year, employee count, funding, and M&A status left blank — verify before Deep Dive selection. | AD91: 2026-06-26
A92: Rippling | B92: rippling.com | C92: HR / People Operations | D92: 2026-06-26 | E92: G2 | F92: https://www.g2.com/categories/core-hr | G92: Claude (S.LAB Research) | H92: 2026-06-26 | I92: Yes | J92: Unified HR, IT, and finance platform (payroll, benefits, device management, spend) for businesses managing global workforces. | K92: 2016 | L92: Private | M92: 7569 | N92: LeadIQ/Tracxn aggregate, May 2026 (third-party estimate, not directly verified) | O92: Private; VC-backed, recent rounds valued company above $16B (exact current total raised not independently verified this session) | P92: Independent | Q92: No M&A this study window. | R92: Yes | X92: Include | AB92: In Progress | AC92: Customer Success-style verification depth applied (LinkedIn/Crunchbase/Tracxn aggregates via web search, June 2026). HR/People Operations vertical (15, locked). Employee counts vary across third-party aggregators for several candidates (flagged per-row) — treat as directional, not precise, until independently re-verified via LinkedIn directly. | AD92: 2026-06-26
A93: BambooHR | B93: bamboohr.com | C93: HR / People Operations | D93: 2026-06-26 | E93: G2 | F93: https://www.g2.com/categories/core-hr | G93: Claude (S.LAB Research) | H93: 2026-06-26 | I93: Yes | J93: HR software for small and midsize businesses covering hiring, onboarding, employee records, and culture/performance tools. | K93: 2008 | L93: Private | M93: 1899 | N93: Tracxn/Crunchbase aggregate, May 2026 | O93: Private; sources vary (bootstrapped historically, also reported $125M round in 2024 at $2.5B valuation) — total raised not independently verified this session | P93: Independent | Q93: No M&A this study window. | R93: Yes | X93: Include | AB93: In Progress | AC93: Customer Success-style verification depth applied (LinkedIn/Crunchbase/Tracxn aggregates via web search, June 2026). HR/People Operations vertical (15, locked). Employee counts vary across third-party aggregators for several candidates (flagged per-row) — treat as directional, not precise, until independently re-verified via LinkedIn directly. | AD93: 2026-06-26
A94: Gusto | B94: gusto.com | C94: HR / People Operations | D94: 2026-06-26 | E94: G2 | F94: https://www.g2.com/categories/core-hr | G94: Claude (S.LAB Research) | H94: 2026-06-26 | I94: Yes | J94: Payroll, benefits, and HR platform built for small and midsize businesses. | K94: 2012 | L94: Private | M94: 4000 | N94: Tracxn/Growjo aggregate, 2026 | O94: Private; ~$746M total raised; completed $200M+ tender offer June 2025 at $9.3B valuation | P94: Independent | Q94: No M&A this study window. | R94: Yes | X94: Include | AB94: In Progress | AC94: Customer Success-style verification depth applied (LinkedIn/Crunchbase/Tracxn aggregates via web search, June 2026). HR/People Operations vertical (15, locked). Employee counts vary across third-party aggregators for several candidates (flagged per-row) — treat as directional, not precise, until independently re-verified via LinkedIn directly. | AD94: 2026-06-26
A95: HiBob | B95: hibob.com | C95: HR / People Operations | D95: 2026-06-26 | E95: G2 | F95: https://www.g2.com/categories/core-hr | G95: Claude (S.LAB Research) | H95: 2026-06-26 | I95: Yes | J95: HRIS platform ("Bob") for mid-market companies, covering people data, performance, compensation, and engagement. | K95: 2015 | L95: Private | M95: 2000 | N95: Tracxn/Growjo aggregate, 2026 | O95: Private; ~$574M total raised; $2.5B valuation (2023, $150M Series D) | P95: Independent | Q95: No M&A this study window. | R95: Yes | X95: Include | AB95: In Progress | AC95: Customer Success-style verification depth applied (LinkedIn/Crunchbase/Tracxn aggregates via web search, June 2026). HR/People Operations vertical (15, locked). Employee counts vary across third-party aggregators for several candidates (flagged per-row) — treat as directional, not precise, until independently re-verified via LinkedIn directly. | AD95: 2026-06-26
A96: Paylocity | B96: paylocity.com | C96: HR / People Operations | D96: 2026-06-26 | E96: G2 | F96: https://www.g2.com/categories/core-hr | G96: Claude (S.LAB Research) | H96: 2026-06-26 | I96: Yes | J96: Cloud HR and payroll software platform for midsize organizations, including talent, workforce management, and benefits. | K96: 1997 | L96: Public (NASDAQ: PCTY) | M96: 6700 | N96: Company-reported aggregate, 2026 | O96: Public company; IPO 2014 | P96: Independent | Q96: No M&A this study window. | R96: Yes | X96: Include | AB96: In Progress | AC96: Customer Success-style verification depth applied (LinkedIn/Crunchbase/Tracxn aggregates via web search, June 2026). HR/People Operations vertical (15, locked). Employee counts vary across third-party aggregators for several candidates (flagged per-row) — treat as directional, not precise, until independently re-verified via LinkedIn directly. | AD96: 2026-06-26
A97: Deel HR | B97: deel.com | C97: HR / People Operations | D97: 2026-06-26 | E97: G2 | F97: https://www.g2.com/categories/core-hr | G97: Claude (S.LAB Research) | H97: 2026-06-26 | I97: Yes | J97: Global payroll, HR, and Employer-of-Record (EOR) platform for hiring and paying international teams. | K97: 2019 | L97: Private | M97: 9619 | N97: Tracxn aggregate, May 2026 | O97: Private; ~$982M total raised; $17.3B valuation (Oct 2025, $300M Series E) | P97: Independent | Q97: No M&A this study window; active acquirer of smaller tools (does not affect own domain stability). | R97: Yes | X97: Include | AB97: In Progress | AC97: Customer Success-style verification depth applied (LinkedIn/Crunchbase/Tracxn aggregates via web search, June 2026). HR/People Operations vertical (15, locked). Employee counts vary across third-party aggregators for several candidates (flagged per-row) — treat as directional, not precise, until independently re-verified via LinkedIn directly. | AD97: 2026-06-26
A98: Keka | B98: keka.com | C98: HR / People Operations | D98: 2026-06-26 | E98: G2 | F98: https://www.g2.com/categories/core-hr | G98: Claude (S.LAB Research) | H98: 2026-06-26 | I98: Yes | J98: HR, payroll, and performance management software for mid-market companies, primarily in India. | K98: 2014 | L98: Private | M98: 1000 | N98: Sources vary 886-1,241 across LinkedIn/Tracxn/EasyLeadz, 2025-2026 — not independently verified to a single figure | O98: Private; reported ~$59.2M raised (incl. WestBridge Capital); also reported as largely bootstrapped/revenue-funded ($85.9M ARR per Latka) | P98: Independent | Q98: No M&A this study window. | R98: Yes | X98: Include | AB98: In Progress | AC98: Customer Success-style verification depth applied (LinkedIn/Crunchbase/Tracxn aggregates via web search, June 2026). HR/People Operations vertical (15, locked). Employee counts vary across third-party aggregators for several candidates (flagged per-row) — treat as directional, not precise, until independently re-verified via LinkedIn directly. | AD98: 2026-06-26
A99: TriNet | B99: trinet.com | C99: HR / People Operations | D99: 2026-06-26 | E99: G2 | F99: https://www.g2.com/categories/core-hr | G99: Claude (S.LAB Research) | H99: 2026-06-26 | I99: Yes | J99: Professional Employer Organization (PEO) providing HR, payroll, benefits, and risk management for small and midsize businesses. | K99: 1988 | L99: Public (NYSE: TNET) | N99: Not verified this session — public filings would have exact headcount | O99: Public company; IPO 2014 | P99: Independent | Q99: No M&A this study window. | R99: Yes | X99: Include | AB99: In Progress | AC99: Customer Success-style verification depth applied (LinkedIn/Crunchbase/Tracxn aggregates via web search, June 2026). HR/People Operations vertical (15, locked). Employee counts vary across third-party aggregators for several candidates (flagged per-row) — treat as directional, not precise, until independently re-verified via LinkedIn directly. | AD99: 2026-06-26
A100: Remote | B100: remote.com | C100: HR / People Operations | D100: 2026-06-26 | E100: G2 | F100: https://www.g2.com/categories/core-hr | G100: Claude (S.LAB Research) | H100: 2026-06-26 | I100: Yes | J100: Global HR platform offering Employer-of-Record, global payroll, and contractor management for distributed teams. | K100: 2019 | L100: Private | M100: 11900 | N100: Tracxn aggregate, 2026 (other sources report up to 14,569 — range not reconciled) | O100: Private; ~$506M total raised; $3B valuation (Series C, April 2022) | P100: Independent | Q100: No M&A this study window; active acquirer of smaller tools (Atlas, Jan 2026; Bravas, Apr 2026) — does not affect own domain stability but may add inorganic traffic; note for Pass 2 interpretation. | R100: Yes | X100: Include | AB100: In Progress | AC100: Customer Success-style verification depth applied (LinkedIn/Crunchbase/Tracxn aggregates via web search, June 2026). HR/People Operations vertical (15, locked). Employee counts vary across third-party aggregators for several candidates (flagged per-row) — treat as directional, not precise, until independently re-verified via LinkedIn directly. | AD100: 2026-06-26
...

Sheet Deep Dive Database
A1: Company Name | B1: Category | C1: Employees | D1: Traffic Start | E1: Traffic End | F1: % Change | G1: Ref. Domains Start | H1: Ref. Domains End | I1: Reviewed Date | J1: Time Spent (min) | K1: Reviewer | L1: URL 1 | M1: Content Type 1 | N1: Traffic Change 1 | O1: URL 2 | P1: Content Type 2 | Q1: Traffic Change 2 | R1: URL 3 | S1: Content Type 3 | T1: Traffic Change 3 | U1: URL 4 | V1: Content Type 4 | W1: Traffic Change 4 | X1: URL 5 | Y1: Content Type 5 | Z1: Traffic Change 5 | AA1: Growth Concentration | AB1: Content Origin | AC1: Growth Timing | AD1: Referring Domain Notes | AE1: Internal Linking Observations | AF1: AI Visibility Spot-Check Notes | AG1: Anything Surprising | AH1: Anything Contradicting Hypotheses | AI1: Quotable Pattern Candidates | AJ1: Primary Growth Driver (confirmed) | AK1: Review Status | AL1: Notes/Follow-ups | AM1: Review Complete | AN1: Long-Term Traffic Story | AO1: Major Inflection Points | AP1: Acquisitions / Mergers | AQ1: Rebrands | AR1: Domain Migrations | AS1: Product Launches / Notable Events
B2: =IFERROR(VLOOKUP(A2,'company tracker'!$a:$s,MATCH("Category",'company tracker'!$1:$1,0),FALSE()),"") | C2: =IFERROR(VLOOKUP(A2,'Pass 1 Archive'!$A:$AD,MATCH("LinkedIn Employee Count",'Pass 1 Archive'!$1:$1,0),FALSE()),"") | D2: =IFERROR(VLOOKUP(A2,'company tracker'!$a:$s,MATCH("Jan 2025 Traffic",'company tracker'!$1:$1,0),FALSE()),"") | E2: =IFERROR(VLOOKUP(A2,'company tracker'!$a:$s,MATCH("Jun 2026 Traffic",'company tracker'!$1:$1,0),FALSE()),"") | F2: =IFERROR(VLOOKUP(A2,'company tracker'!$a:$s,MATCH("Traffic % Change",'company tracker'!$1:$1,0),FALSE()),"") | G2: =IFERROR(VLOOKUP(A2,'company tracker'!$a:$s,MATCH("Jan 2025 Referring Domains",'company tracker'!$1:$1,0),FALSE()),"") | H2: =IFERROR(VLOOKUP(A2,'company tracker'!$a:$s,MATCH("Jun 2026 Referring Domains",'company tracker'!$1:$1,0),FALSE()),"")
B3: =IFERROR(VLOOKUP(A3,'company tracker'!$a:$s,MATCH("Category",'company tracker'!$1:$1,0),FALSE()),"") | C3: =IFERROR(VLOOKUP(A3,'Pass 1 Archive'!$A:$AD,MATCH("LinkedIn Employee Count",'Pass 1 Archive'!$1:$1,0),FALSE()),"") | D3: =IFERROR(VLOOKUP(A3,'company tracker'!$a:$s,MATCH("Jan 2025 Traffic",'company tracker'!$1:$1,0),FALSE()),"") | E3: =IFERROR(VLOOKUP(A3,'company tracker'!$a:$s,MATCH("Jun 2026 Traffic",'company tracker'!$1:$1,0),FALSE()),"") | F3: =IFERROR(VLOOKUP(A3,'company tracker'!$a:$s,MATCH("Traffic % Change",'company tracker'!$1:$1,0),FALSE()),"") | G3: =IFERROR(VLOOKUP(A3,'company tracker'!$a:$s,MATCH("Jan 2025 Referring Domains",'company tracker'!$1:$1,0),FALSE()),"") | H3: =IFERROR(VLOOKUP(A3,'company tracker'!$a:$s,MATCH("Jun 2026 Referring Domains",'company tracker'!$1:$1,0),FALSE()),"")
B4: =IFERROR(VLOOKUP(A4,'company tracker'!$a:$s,MATCH("Category",'company tracker'!$1:$1,0),FALSE()),"") | C4: =IFERROR(VLOOKUP(A4,'Pass 1 Archive'!$A:$AD,MATCH("LinkedIn Employee Count",'Pass 1 Archive'!$1:$1,0),FALSE()),"") | D4: =IFERROR(VLOOKUP(A4,'company tracker'!$a:$s,MATCH("Jan 2025 Traffic",'company tracker'!$1:$1,0),FALSE()),"") | E4: =IFERROR(VLOOKUP(A4,'company tracker'!$a:$s,MATCH("Jun 2026 Traffic",'company tracker'!$1:$1,0),FALSE()),"") | F4: =IFERROR(VLOOKUP(A4,'company tracker'!$a:$s,MATCH("Traffic % Change",'company tracker'!$1:$1,0),FALSE()),"") | G4: =IFERROR(VLOOKUP(A4,'company tracker'!$a:$s,MATCH("Jan 2025 Referring Domains",'company tracker'!$1:$1,0),FALSE()),"") | H4: =IFERROR(VLOOKUP(A4,'company tracker'!$a:$s,MATCH("Jun 2026 Referring Domains",'company tracker'!$1:$1,0),FALSE()),"")
B5: =IFERROR(VLOOKUP(A5,'company tracker'!$a:$s,MATCH("Category",'company tracker'!$1:$1,0),FALSE()),"") | C5: =IFERROR(VLOOKUP(A5,'Pass 1 Archive'!$A:$AD,MATCH("LinkedIn Employee Count",'Pass 1 Archive'!$1:$1,0),FALSE()),"") | D5: =IFERROR(VLOOKUP(A5,'company tracker'!$a:$s,MATCH("Jan 2025 Traffic",'company tracker'!$1:$1,0),FALSE()),"") | E5: =IFERROR(VLOOKUP(A5,'company tracker'!$a:$s,MATCH("Jun 2026 Traffic",'company tracker'!$1:$1,0),FALSE()),"") | F5: =IFERROR(VLOOKUP(A5,'company tracker'!$a:$s,MATCH("Traffic % Change",'company tracker'!$1:$1,0),FALSE()),"") | G5: =IFERROR(VLOOKUP(A5,'company tracker'!$a:$s,MATCH("Jan 2025 Referring Domains",'company tracker'!$1:$1,0),FALSE()),"") | H5: =IFERROR(VLOOKUP(A5,'company tracker'!$a:$s,MATCH("Jun 2026 Referring Domains",'company tracker'!$1:$1,0),FALSE()),"")
B6: =IFERROR(VLOOKUP(A6,'company tracker'!$a:$s,MATCH("Category",'company tracker'!$1:$1,0),FALSE()),"") | C6: =IFERROR(VLOOKUP(A6,'Pass 1 Archive'!$A:$AD,MATCH("LinkedIn Employee Count",'Pass 1 Archive'!$1:$1,0),FALSE()),"") | D6: =IFERROR(VLOOKUP(A6,'company tracker'!$a:$s,MATCH("Jan 2025 Traffic",'company tracker'!$1:$1,0),FALSE()),"") | E6: =IFERROR(VLOOKUP(A6,'company tracker'!$a:$s,MATCH("Jun 2026 Traffic",'company tracker'!$1:$1,0),FALSE()),"") | F6: =IFERROR(VLOOKUP(A6,'company tracker'!$a:$s,MATCH("Traffic % Change",'company tracker'!$1:$1,0),FALSE()),"") | G6: =IFERROR(VLOOKUP(A6,'company tracker'!$a:$s,MATCH("Jan 2025 Referring Domains",'company tracker'!$1:$1,0),FALSE()),"") | H6: =IFERROR(VLOOKUP(A6,'company tracker'!$a:$s,MATCH("Jun 2026 Referring Domains",'company tracker'!$1:$1,0),FALSE()),"")
B7: =IFERROR(VLOOKUP(A7,'company tracker'!$a:$s,MATCH("Category",'company tracker'!$1:$1,0),FALSE()),"") | C7: =IFERROR(VLOOKUP(A7,'Pass 1 Archive'!$A:$AD,MATCH("LinkedIn Employee Count",'Pass 1 Archive'!$1:$1,0),FALSE()),"") | D7: =IFERROR(VLOOKUP(A7,'company tracker'!$a:$s,MATCH("Jan 2025 Traffic",'company tracker'!$1:$1,0),FALSE()),"") | E7: =IFERROR(VLOOKUP(A7,'company tracker'!$a:$s,MATCH("Jun 2026 Traffic",'company tracker'!$1:$1,0),FALSE()),"") | F7: =IFERROR(VLOOKUP(A7,'company tracker'!$a:$s,MATCH("Traffic % Change",'company tracker'!$1:$1,0),FALSE()),"") | G7: =IFERROR(VLOOKUP(A7,'company tracker'!$a:$s,MATCH("Jan 2025 Referring Domains",'company tracker'!$1:$1,0),FALSE()),"") | H7: =IFERROR(VLOOKUP(A7,'company tracker'!$a:$s,MATCH("Jun 2026 Referring Domains",'company tracker'!$1:$1,0),FALSE()),"")
B8: =IFERROR(VLOOKUP(A8,'company tracker'!$a:$s,MATCH("Category",'company tracker'!$1:$1,0),FALSE()),"") | C8: =IFERROR(VLOOKUP(A8,'Pass 1 Archive'!$A:$AD,MATCH("LinkedIn Employee Count",'Pass 1 Archive'!$1:$1,0),FALSE()),"") | D8: =IFERROR(VLOOKUP(A8,'company tracker'!$a:$s,MATCH("Jan 2025 Traffic",'company tracker'!$1:$1,0),FALSE()),"") | E8: =IFERROR(VLOOKUP(A8,'company tracker'!$a:$s,MATCH("Jun 2026 Traffic",'company tracker'!$1:$1,0),FALSE()),"") | F8: =IFERROR(VLOOKUP(A8,'company tracker'!$a:$s,MATCH("Traffic % Change",'company tracker'!$1:$1,0),FALSE()),"") | G8: =IFERROR(VLOOKUP(A8,'company tracker'!$a:$s,MATCH("Jan 2025 Referring Domains",'company tracker'!$1:$1,0),FALSE()),"") | H8: =IFERROR(VLOOKUP(A8,'company tracker'!$a:$s,MATCH("Jun 2026 Referring Domains",'company tracker'!$1:$1,0),FALSE()),"")
B9: =IFERROR(VLOOKUP(A9,'company tracker'!$a:$s,MATCH("Category",'company tracker'!$1:$1,0),FALSE()),"") | C9: =IFERROR(VLOOKUP(A9,'Pass 1 Archive'!$A:$AD,MATCH("LinkedIn Employee Count",'Pass 1 Archive'!$1:$1,0),FALSE()),"") | D9: =IFERROR(VLOOKUP(A9,'company tracker'!$a:$s,MATCH("Jan 2025 Traffic",'company tracker'!$1:$1,0),FALSE()),"") | E9: =IFERROR(VLOOKUP(A9,'company tracker'!$a:$s,MATCH("Jun 2026 Traffic",'company tracker'!$1:$1,0),FALSE()),"") | F9: =IFERROR(VLOOKUP(A9,'company tracker'!$a:$s,MATCH("Traffic % Change",'company tracker'!$1:$1,0),FALSE()),"") | G9: =IFERROR(VLOOKUP(A9,'company tracker'!$a:$s,MATCH("Jan 2025 Referring Domains",'company tracker'!$1:$1,0),FALSE()),"") | H9: =IFERROR(VLOOKUP(A9,'company tracker'!$a:$s,MATCH("Jun 2026 Referring Domains",'company tracker'!$1:$1,0),FALSE()),"")
B10: =IFERROR(VLOOKUP(A10,'company tracker'!$a:$s,MATCH("Category",'company tracker'!$1:$1,0),FALSE()),"") | C10: =IFERROR(VLOOKUP(A10,'Pass 1 Archive'!$A:$AD,MATCH("LinkedIn Employee Count",'Pass 1 Archive'!$1:$1,0),FALSE()),"") | D10: =IFERROR(VLOOKUP(A10,'company tracker'!$a:$s,MATCH("Jan 2025 Traffic",'company tracker'!$1:$1,0),FALSE()),"") | E10: =IFERROR(VLOOKUP(A10,'company tracker'!$a:$s,MATCH("Jun 2026 Traffic",'company tracker'!$1:$1,0),FALSE()),"") | F10: =IFERROR(VLOOKUP(A10,'company tracker'!$a:$s,MATCH("Traffic % Change",'company tracker'!$1:$1,0),FALSE()),"") | G10: =IFERROR(VLOOKUP(A10,'company tracker'!$a:$s,MATCH("Jan 2025 Referring Domains",'company tracker'!$1:$1,0),FALSE()),"") | H10: =IFERROR(VLOOKUP(A10,'company tracker'!$a:$s,MATCH("Jun 2026 Referring Domains",'company tracker'!$1:$1,0),FALSE()),"")
B11: =IFERROR(VLOOKUP(A11,'company tracker'!$a:$s,MATCH("Category",'company tracker'!$1:$1,0),FALSE()),"") | C11: =IFERROR(VLOOKUP(A11,'Pass 1 Archive'!$A:$AD,MATCH("LinkedIn Employee Count",'Pass 1 Archive'!$1:$1,0),FALSE()),"") | D11: =IFERROR(VLOOKUP(A11,'company tracker'!$a:$s,MATCH("Jan 2025 Traffic",'company tracker'!$1:$1,0),FALSE()),"") | E11: =IFERROR(VLOOKUP(A11,'company tracker'!$a:$s,MATCH("Jun 2026 Traffic",'company tracker'!$1:$1,0),FALSE()),"") | F11: =IFERROR(VLOOKUP(A11,'company tracker'!$a:$s,MATCH("Traffic % Change",'company tracker'!$1:$1,0),FALSE()),"") | G11: =IFERROR(VLOOKUP(A11,'company tracker'!$a:$s,MATCH("Jan 2025 Referring Domains",'company tracker'!$1:$1,0),FALSE()),"") | H11: =IFERROR(VLOOKUP(A11,'company tracker'!$a:$s,MATCH("Jun 2026 Referring Domains",'company tracker'!$1:$1,0),FALSE()),"")
B12: =IFERROR(VLOOKUP(A12,'company tracker'!$a:$s,MATCH("Category",'company tracker'!$1:$1,0),FALSE()),"") | C12: =IFERROR(VLOOKUP(A12,'Pass 1 Archive'!$A:$AD,MATCH("LinkedIn Employee Count",'Pass 1 Archive'!$1:$1,0),FALSE()),"") | D12: =IFERROR(VLOOKUP(A12,'company tracker'!$a:$s,MATCH("Jan 2025 Traffic",'company tracker'!$1:$1,0),FALSE()),"") | E12: =IFERROR(VLOOKUP(A12,'company tracker'!$a:$s,MATCH("Jun 2026 Traffic",'company tracker'!$1:$1,0),FALSE()),"") | F12: =IFERROR(VLOOKUP(A12,'company tracker'!$a:$s,MATCH("Traffic % Change",'company tracker'!$1:$1,0),FALSE()),"") | G12: =IFERROR(VLOOKUP(A12,'company tracker'!$a:$s,MATCH("Jan 2025 Referring Domains",'company tracker'!$1:$1,0),FALSE()),"") | H12: =IFERROR(VLOOKUP(A12,'company tracker'!$a:$s,MATCH("Jun 2026 Referring Domains",'company tracker'!$1:$1,0),FALSE()),"")
B13: =IFERROR(VLOOKUP(A13,'company tracker'!$a:$s,MATCH("Category",'company tracker'!$1:$1,0),FALSE()),"") | C13: =IFERROR(VLOOKUP(A13,'Pass 1 Archive'!$A:$AD,MATCH("LinkedIn Employee Count",'Pass 1 Archive'!$1:$1,0),FALSE()),"") | D13: =IFERROR(VLOOKUP(A13,'company tracker'!$a:$s,MATCH("Jan 2025 Traffic",'company tracker'!$1:$1,0),FALSE()),"") | E13: =IFERROR(VLOOKUP(A13,'company tracker'!$a:$s,MATCH("Jun 2026 Traffic",'company tracker'!$1:$1,0),FALSE()),"") | F13: =IFERROR(VLOOKUP(A13,'company tracker'!$a:$s,MATCH("Traffic % Change",'company tracker'!$1:$1,0),FALSE()),"") | G13: =IFERROR(VLOOKUP(A13,'company tracker'!$a:$s,MATCH("Jan 2025 Referring Domains",'company tracker'!$1:$1,0),FALSE()),"") | H13: =IFERROR(VLOOKUP(A13,'company tracker'!$a:$s,MATCH("Jun 2026 Referring Domains",'company tracker'!$1:$1,0),FALSE()),"")
... B500: =IFERROR(VLOOKUP(A500,'company tracker'!$a:$s,MATCH("Category",'company tracker'!$1:$1,0),FALSE()),"") | C500: =IFERROR(VLOOKUP(A500,'Pass 1 Archive'!$A:$AD,MATCH("LinkedIn Employee Count",'Pass 1 Archive'!$1:$1,0),FALSE()),"") | D500: =IFERROR(VLOOKUP(A500,'company tracker'!$a:$s,MATCH("Jan 2025 Traffic",'company tracker'!$1:$1,0),FALSE()),"") | E500: =IFERROR(VLOOKUP(A500,'company tracker'!$a:$s,MATCH("Jun 2026 Traffic",'company tracker'!$1:$1,0),FALSE()),"") | F500: =IFERROR(VLOOKUP(A500,'company tracker'!$a:$s,MATCH("Traffic % Change",'company tracker'!$1:$1,0),FALSE()),"") | G500: =IFERROR(VLOOKUP(A500,'company tracker'!$a:$s,MATCH("Jan 2025 Referring Domains",'company tracker'!$1:$1,0),FALSE()),"") | H500: =IFERROR(VLOOKUP(A500,'company tracker'!$a:$s,MATCH("Jun 2026 Referring Domains",'company tracker'!$1:$1,0),FALSE()),"")

Sheet Comparison Group Database
A1: Company Name | B1: Category | C1: Employees | D1: Traffic Start | E1: Traffic End | F1: % Change | G1: Ref. Domains Start | H1: Ref. Domains End | I1: Reviewed Date | J1: Time Spent (min) | K1: Publishing Activity | L1: Growth-Associated Content Types Present? | M1: Content Types Notes | N1: Likely Decline Explanation | O1: One-Line Takeaway | P1: Confidence | Q1: Review Status | R1: Review Complete
B2: =IFERROR(VLOOKUP(A2,'company tracker'!$a:$s,MATCH("Category",'company tracker'!$1:$1,0),FALSE()),"") | C2: =IFERROR(VLOOKUP(A2,'Pass 1 Archive'!$A:$AD,MATCH("LinkedIn Employee Count",'Pass 1 Archive'!$1:$1,0),FALSE()),"") | D2: =IFERROR(VLOOKUP(A2,'company tracker'!$a:$s,MATCH("Jan 2025 Traffic",'company tracker'!$1:$1,0),FALSE()),"") | E2: =IFERROR(VLOOKUP(A2,'company tracker'!$a:$s,MATCH("Jun 2026 Traffic",'company tracker'!$1:$1,0),FALSE()),"") | F2: =IFERROR(VLOOKUP(A2,'company tracker'!$a:$s,MATCH("Traffic % Change",'company tracker'!$1:$1,0),FALSE()),"") | G2: =IFERROR(VLOOKUP(A2,'company tracker'!$a:$s,MATCH("Jan 2025 Referring Domains",'company tracker'!$1:$1,0),FALSE()),"") | H2: =IFERROR(VLOOKUP(A2,'company tracker'!$a:$s,MATCH("Jun 2026 Referring Domains",'company tracker'!$1:$1,0),FALSE()),"")
B3: =IFERROR(VLOOKUP(A3,'company tracker'!$a:$s,MATCH("Category",'company tracker'!$1:$1,0),FALSE()),"") | C3: =IFERROR(VLOOKUP(A3,'Pass 1 Archive'!$A:$AD,MATCH("LinkedIn Employee Count",'Pass 1 Archive'!$1:$1,0),FALSE()),"") | D3: =IFERROR(VLOOKUP(A3,'company tracker'!$a:$s,MATCH("Jan 2025 Traffic",'company tracker'!$1:$1,0),FALSE()),"") | E3: =IFERROR(VLOOKUP(A3,'company tracker'!$a:$s,MATCH("Jun 2026 Traffic",'company tracker'!$1:$1,0),FALSE()),"") | F3: =IFERROR(VLOOKUP(A3,'company tracker'!$a:$s,MATCH("Traffic % Change",'company tracker'!$1:$1,0),FALSE()),"") | G3: =IFERROR(VLOOKUP(A3,'company tracker'!$a:$s,MATCH("Jan 2025 Referring Domains",'company tracker'!$1:$1,0),FALSE()),"") | H3: =IFERROR(VLOOKUP(A3,'company tracker'!$a:$s,MATCH("Jun 2026 Referring Domains",'company tracker'!$1:$1,0),FALSE()),"")
B4: =IFERROR(VLOOKUP(A4,'company tracker'!$a:$s,MATCH("Category",'company tracker'!$1:$1,0),FALSE()),"") | C4: =IFERROR(VLOOKUP(A4,'Pass 1 Archive'!$A:$AD,MATCH("LinkedIn Employee Count",'Pass 1 Archive'!$1:$1,0),FALSE()),"") | D4: =IFERROR(VLOOKUP(A4,'company tracker'!$a:$s,MATCH("Jan 2025 Traffic",'company tracker'!$1:$1,0),FALSE()),"") | E4: =IFERROR(VLOOKUP(A4,'company tracker'!$a:$s,MATCH("Jun 2026 Traffic",'company tracker'!$1:$1,0),FALSE()),"") | F4: =IFERROR(VLOOKUP(A4,'company tracker'!$a:$s,MATCH("Traffic % Change",'company tracker'!$1:$1,0),FALSE()),"") | G4: =IFERROR(VLOOKUP(A4,'company tracker'!$a:$s,MATCH("Jan 2025 Referring Domains",'company tracker'!$1:$1,0),FALSE()),"") | H4: =IFERROR(VLOOKUP(A4,'company tracker'!$a:$s,MATCH("Jun 2026 Referring Domains",'company tracker'!$1:$1,0),FALSE()),"")
B5: =IFERROR(VLOOKUP(A5,'company tracker'!$a:$s,MATCH("Category",'company tracker'!$1:$1,0),FALSE()),"") | C5: =IFERROR(VLOOKUP(A5,'Pass 1 Archive'!$A:$AD,MATCH("LinkedIn Employee Count",'Pass 1 Archive'!$1:$1,0),FALSE()),"") | D5: =IFERROR(VLOOKUP(A5,'company tracker'!$a:$s,MATCH("Jan 2025 Traffic",'company tracker'!$1:$1,0),FALSE()),"") | E5: =IFERROR(VLOOKUP(A5,'company tracker'!$a:$s,MATCH("Jun 2026 Traffic",'company tracker'!$1:$1,0),FALSE()),"") | F5: =IFERROR(VLOOKUP(A5,'company tracker'!$a:$s,MATCH("Traffic % Change",'company tracker'!$1:$1,0),FALSE()),"") | G5: =IFERROR(VLOOKUP(A5,'company tracker'!$a:$s,MATCH("Jan 2025 Referring Domains",'company tracker'!$1:$1,0),FALSE()),"") | H5: =IFERROR(VLOOKUP(A5,'company tracker'!$a:$s,MATCH("Jun 2026 Referring Domains",'company tracker'!$1:$1,0),FALSE()),"")
B6: =IFERROR(VLOOKUP(A6,'company tracker'!$a:$s,MATCH("Category",'company tracker'!$1:$1,0),FALSE()),"") | C6: =IFERROR(VLOOKUP(A6,'Pass 1 Archive'!$A:$AD,MATCH("LinkedIn Employee Count",'Pass 1 Archive'!$1:$1,0),FALSE()),"") | D6: =IFERROR(VLOOKUP(A6,'company tracker'!$a:$s,MATCH("Jan 2025 Traffic",'company tracker'!$1:$1,0),FALSE()),"") | E6: =IFERROR(VLOOKUP(A6,'company tracker'!$a:$s,MATCH("Jun 2026 Traffic",'company tracker'!$1:$1,0),FALSE()),"") | F6: =IFERROR(VLOOKUP(A6,'company tracker'!$a:$s,MATCH("Traffic % Change",'company tracker'!$1:$1,0),FALSE()),"") | G6: =IFERROR(VLOOKUP(A6,'company tracker'!$a:$s,MATCH("Jan 2025 Referring Domains",'company tracker'!$1:$1,0),FALSE()),"") | H6: =IFERROR(VLOOKUP(A6,'company tracker'!$a:$s,MATCH("Jun 2026 Referring Domains",'company tracker'!$1:$1,0),FALSE()),"")
B7: =IFERROR(VLOOKUP(A7,'company tracker'!$a:$s,MATCH("Category",'company tracker'!$1:$1,0),FALSE()),"") | C7: =IFERROR(VLOOKUP(A7,'Pass 1 Archive'!$A:$AD,MATCH("LinkedIn Employee Count",'Pass 1 Archive'!$1:$1,0),FALSE()),"") | D7: =IFERROR(VLOOKUP(A7,'company tracker'!$a:$s,MATCH("Jan 2025 Traffic",'company tracker'!$1:$1,0),FALSE()),"") | E7: =IFERROR(VLOOKUP(A7,'company tracker'!$a:$s,MATCH("Jun 2026 Traffic",'company tracker'!$1:$1,0),FALSE()),"") | F7: =IFERROR(VLOOKUP(A7,'company tracker'!$a:$s,MATCH("Traffic % Change",'company tracker'!$1:$1,0),FALSE()),"") | G7: =IFERROR(VLOOKUP(A7,'company tracker'!$a:$s,MATCH("Jan 2025 Referring Domains",'company tracker'!$1:$1,0),FALSE()),"") | H7: =IFERROR(VLOOKUP(A7,'company tracker'!$a:$s,MATCH("Jun 2026 Referring Domains",'company tracker'!$1:$1,0),FALSE()),"")
B8: =IFERROR(VLOOKUP(A8,'company tracker'!$a:$s,MATCH("Category",'company tracker'!$1:$1,0),FALSE()),"") | C8: =IFERROR(VLOOKUP(A8,'Pass 1 Archive'!$A:$AD,MATCH("LinkedIn Employee Count",'Pass 1 Archive'!$1:$1,0),FALSE()),"") | D8: =IFERROR(VLOOKUP(A8,'company tracker'!$a:$s,MATCH("Jan 2025 Traffic",'company tracker'!$1:$1,0),FALSE()),"") | E8: =IFERROR(VLOOKUP(A8,'company tracker'!$a:$s,MATCH("Jun 2026 Traffic",'company tracker'!$1:$1,0),FALSE()),"") | F8: =IFERROR(VLOOKUP(A8,'company tracker'!$a:$s,MATCH("Traffic % Change",'company tracker'!$1:$1,0),FALSE()),"") | G8: =IFERROR(VLOOKUP(A8,'company tracker'!$a:$s,MATCH("Jan 2025 Referring Domains",'company tracker'!$1:$1,0),FALSE()),"") | H8: =IFERROR(VLOOKUP(A8,'company tracker'!$a:$s,MATCH("Jun 2026 Referring Domains",'company tracker'!$1:$1,0),FALSE()),"")
B9: =IFERROR(VLOOKUP(A9,'company tracker'!$a:$s,MATCH("Category",'company tracker'!$1:$1,0),FALSE()),"") | C9: =IFERROR(VLOOKUP(A9,'Pass 1 Archive'!$A:$AD,MATCH("LinkedIn Employee Count",'Pass 1 Archive'!$1:$1,0),FALSE()),"") | D9: =IFERROR(VLOOKUP(A9,'company tracker'!$a:$s,MATCH("Jan 2025 Traffic",'company tracker'!$1:$1,0),FALSE()),"") | E9: =IFERROR(VLOOKUP(A9,'company tracker'!$a:$s,MATCH("Jun 2026 Traffic",'company tracker'!$1:$1,0),FALSE()),"") | F9: =IFERROR(VLOOKUP(A9,'company tracker'!$a:$s,MATCH("Traffic % Change",'company tracker'!$1:$1,0),FALSE()),"") | G9: =IFERROR(VLOOKUP(A9,'company tracker'!$a:$s,MATCH("Jan 2025 Referring Domains",'company tracker'!$1:$1,0),FALSE()),"") | H9: =IFERROR(VLOOKUP(A9,'company tracker'!$a:$s,MATCH("Jun 2026 Referring Domains",'company tracker'!$1:$1,0),FALSE()),"")
B10: =IFERROR(VLOOKUP(A10,'company tracker'!$a:$s,MATCH("Category",'company tracker'!$1:$1,0),FALSE()),"") | C10: =IFERROR(VLOOKUP(A10,'Pass 1 Archive'!$A:$AD,MATCH("LinkedIn Employee Count",'Pass 1 Archive'!$1:$1,0),FALSE()),"") | D10: =IFERROR(VLOOKUP(A10,'company tracker'!$a:$s,MATCH("Jan 2025 Traffic",'company tracker'!$1:$1,0),FALSE()),"") | E10: =IFERROR(VLOOKUP(A10,'company tracker'!$a:$s,MATCH("Jun 2026 Traffic",'company tracker'!$1:$1,0),FALSE()),"") | F10: =IFERROR(VLOOKUP(A10,'company tracker'!$a:$s,MATCH("Traffic % Change",'company tracker'!$1:$1,0),FALSE()),"") | G10: =IFERROR(VLOOKUP(A10,'company tracker'!$a:$s,MATCH("Jan 2025 Referring Domains",'company tracker'!$1:$1,0),FALSE()),"") | H10: =IFERROR(VLOOKUP(A10,'company tracker'!$a:$s,MATCH("Jun 2026 Referring Domains",'company tracker'!$1:$1,0),FALSE()),"")
B11: =IFERROR(VLOOKUP(A11,'company tracker'!$a:$s,MATCH("Category",'company tracker'!$1:$1,0),FALSE()),"") | C11: =IFERROR(VLOOKUP(A11,'Pass 1 Archive'!$A:$AD,MATCH("LinkedIn Employee Count",'Pass 1 Archive'!$1:$1,0),FALSE()),"") | D11: =IFERROR(VLOOKUP(A11,'company tracker'!$a:$s,MATCH("Jan 2025 Traffic",'company tracker'!$1:$1,0),FALSE()),"") | E11: =IFERROR(VLOOKUP(A11,'company tracker'!$a:$s,MATCH("Jun 2026 Traffic",'company tracker'!$1:$1,0),FALSE()),"") | F11: =IFERROR(VLOOKUP(A11,'company tracker'!$a:$s,MATCH("Traffic % Change",'company tracker'!$1:$1,0),FALSE()),"") | G11: =IFERROR(VLOOKUP(A11,'company tracker'!$a:$s,MATCH("Jan 2025 Referring Domains",'company tracker'!$1:$1,0),FALSE()),"") | H11: =IFERROR(VLOOKUP(A11,'company tracker'!$a:$s,MATCH("Jun 2026 Referring Domains",'company tracker'!$1:$1,0),FALSE()),"")
B12: =IFERROR(VLOOKUP(A12,'company tracker'!$a:$s,MATCH("Category",'company tracker'!$1:$1,0),FALSE()),"") | C12: =IFERROR(VLOOKUP(A12,'Pass 1 Archive'!$A:$AD,MATCH("LinkedIn Employee Count",'Pass 1 Archive'!$1:$1,0),FALSE()),"") | D12: =IFERROR(VLOOKUP(A12,'company tracker'!$a:$s,MATCH("Jan 2025 Traffic",'company tracker'!$1:$1,0),FALSE()),"") | E12: =IFERROR(VLOOKUP(A12,'company tracker'!$a:$s,MATCH("Jun 2026 Traffic",'company tracker'!$1:$1,0),FALSE()),"") | F12: =IFERROR(VLOOKUP(A12,'company tracker'!$a:$s,MATCH("Traffic % Change",'company tracker'!$1:$1,0),FALSE()),"") | G12: =IFERROR(VLOOKUP(A12,'company tracker'!$a:$s,MATCH("Jan 2025 Referring Domains",'company tracker'!$1:$1,0),FALSE()),"") | H12: =IFERROR(VLOOKUP(A12,'company tracker'!$a:$s,MATCH("Jun 2026 Referring Domains",'company tracker'!$1:$1,0),FALSE()),"")
B13: =IFERROR(VLOOKUP(A13,'company tracker'!$a:$s,MATCH("Category",'company tracker'!$1:$1,0),FALSE()),"") | C13: =IFERROR(VLOOKUP(A13,'Pass 1 Archive'!$A:$AD,MATCH("LinkedIn Employee Count",'Pass 1 Archive'!$1:$1,0),FALSE()),"") | D13: =IFERROR(VLOOKUP(A13,'company tracker'!$a:$s,MATCH("Jan 2025 Traffic",'company tracker'!$1:$1,0),FALSE()),"") | E13: =IFERROR(VLOOKUP(A13,'company tracker'!$a:$s,MATCH("Jun 2026 Traffic",'company tracker'!$1:$1,0),FALSE()),"") | F13: =IFERROR(VLOOKUP(A13,'company tracker'!$a:$s,MATCH("Traffic % Change",'company tracker'!$1:$1,0),FALSE()),"") | G13: =IFERROR(VLOOKUP(A13,'company tracker'!$a:$s,MATCH("Jan 2025 Referring Domains",'company tracker'!$1:$1,0),FALSE()),"") | H13: =IFERROR(VLOOKUP(A13,'company tracker'!$a:$s,MATCH("Jun 2026 Referring Domains",'company tracker'!$1:$1,0),FALSE()),"")
... B500: =IFERROR(VLOOKUP(A500,'company tracker'!$a:$s,MATCH("Category",'company tracker'!$1:$1,0),FALSE()),"") | C500: =IFERROR(VLOOKUP(A500,'Pass 1 Archive'!$A:$AD,MATCH("LinkedIn Employee Count",'Pass 1 Archive'!$1:$1,0),FALSE()),"") | D500: =IFERROR(VLOOKUP(A500,'company tracker'!$a:$s,MATCH("Jan 2025 Traffic",'company tracker'!$1:$1,0),FALSE()),"") | E500: =IFERROR(VLOOKUP(A500,'company tracker'!$a:$s,MATCH("Jun 2026 Traffic",'company tracker'!$1:$1,0),FALSE()),"") | F500: =IFERROR(VLOOKUP(A500,'company tracker'!$a:$s,MATCH("Traffic % Change",'company tracker'!$1:$1,0),FALSE()),"") | G500: =IFERROR(VLOOKUP(A500,'company tracker'!$a:$s,MATCH("Jan 2025 Referring Domains",'company tracker'!$1:$1,0),FALSE()),"") | H500: =IFERROR(VLOOKUP(A500,'company tracker'!$a:$s,MATCH("Jun 2026 Referring Domains",'company tracker'!$1:$1,0),FALSE()),"")

Sheet Research Log
A1: Log ID | B1: Date | C1: Related Company ID | D1: Category Tag | E1: Observation | F1: Why It's Interesting | G1: Action Needed | H1: Status

Sheet Pattern Tracker
A1: Pattern ID | B1: Pattern | C1: Supporting Companies | D1: Contradicting Companies | E1: Evidence | F1: Confidence | G1: Status | H1: Potential Report Section | I1: Cross-Cut Notes (Buying Motion / Buyer Type) | J1: Last Updated | K1: Notes

Sheet Lists
A1: Categories | B1: GrowthDriver | C1: ContentType | D1: TrafficTrajectory
A2: Sales Engagement / Sales Intelligence | B2: Docs hub | C2: Comparison pages | D2: Continuous Acceleration
A3: Marketing Automation | B3: Comparison pages | C3: Alternatives pages | D3: Steady Growth
A4: Customer Support / Help Desk | B4: Alternatives pages | C4: Documentation/Help center | D4: Growth then Pullback
A5: Customer Success | B5: Free tool | C5: Glossary/Definitional | D5: Early Peak then Plateau
A6: HR / People Operations | B6: Brand/domain strength | C6: Product/Feature pages | D6: Early Peak then Decline
A7: Finance / Spend Management | B7: Content refreshes | C7: Educational/How-to | D7: Decline then Recovery
A8: Project Management / Collaboration | B8: New product/category expansion | C8: Original data/Research | D8: Flat
A9: Developer Tools / DevOps | B9: Backlink growth | C9: Customer stories/Case studies | D9: Steady Decline
A10: Security / Compliance | B10: Unclear | C10: Free tool/Calculator | D10: Volatile
A11: Product Analytics / Product Management | C11: Other
